Workbook
Name From_20: [1]Ref!$P$2:$P$5
Name KPB_DUO_sizes: [1]Ref!$M$2:$M$6
Name KPB_sizes: [1]Ref!$K$2:$K$10
Name KVBF: [1]Ref!$Q$2
Name KVBF_sizes: [1]Ref!$L$2:$L$10
Name Up_to_18: [1]Ref!$O$2:$O$5

Sheet COST
Q2: =Q883 -> 3211396.3 | S2: =S883 -> 3211396.3 | T2: =T883 -> 170000 | U2: =U883 -> 3381396.3 | Z2: =Z883 -> 4332914.7 | AC2: =AC883 -> 6500000 | AP2: 0
B3: SN | C3: Location | D3: Fan Ref. (SN) | E3: Origin | F3: Fan Type | G3: Speed | H3: Smoke Rating | I3: Article No. | J3: Item Code (Model) | K3: Flow l/s | L3: ESP Pa | M3: Globle Price | N3: EX Price € | O3: Discount | P3: Qty. | Q3: Basic T EX Price € | R3: Discount on Basic T EX Price € | S3: Final T EX Price € | T3: Shipping | U3: CIF | V3: Customs | W3: VAT | X3: COST FACTORS | Y3: Currency rate | Z3: Dry DDP Cost € | AA3: MG | AB3: Unit Price € | AC3: Total Price € | AK3: 0 | AL3: China | AM3: Axial Inline | AN3: Variable | AO3: 300°C/2Hr | AP3: 0.05
A4: =VALUE(RIGHT(B4,LEN(B4)-2)) -> 1 | B4: F-01 | D4: FAF-A29-B02-01 | E4: Germany | F4: Axial Inline | G4: Single | H4: Ambient | I4: CAP071140001G | J4: AXC 710-9/20°-4-P (350) (3 kW) S IE3 | K4: 3560 | L4: 375 | M4: =IF(ISERROR(VLOOKUP(J4,'Germany price'!$B$1:$G$99001,6,0))," ",VLOOKUP(J4,'Germany price'!$B$1:$G$99001,6,0)) | N4: 2515 | O4: 0.58 | P4: 2 | Q4: =N4*P4*(1-O4) -> 2112.6 | R4: 0 | S4: =Q4*(1-R4) -> 2112.6 | T4: =(Q4*AE4)/AF4 -> 111.8336 | U4: =T4+S4 -> 2224.4336 | V4: 0 | W4: =1.14 -> 1.14 | X4: =1.05*1.07 -> 1.1235 | Y4: 1 | Z4: =U4*X4*Y4*W4*(1+V4) -> 2849.0323 | AA4: =(6500000/Z2)-1 -> 0.50014493 | AB4: =AC4/P4 -> 2136.9807 | AC4: =U4*X4*(1+AA4)*Y4*W4*(1+V4) -> 4273.9614 | AE4: 170000 | AF4: =Q883 -> 3211396.3 | AK4: 0.05 | AL4: Sweden | AM4: Centrifugal Inline | AN4: Single | AO4: 400°C/2Hr | AP4: 0.08
A5: =VALUE(RIGHT(B5,LEN(B5)-2)) -> 2 | B5: F-02 | D5: FAF-A29-B02-02 | E5: Germany | F5: Centrifugal Inline | G5: Single | H5: Ambient | I5: 235403 | J5: MUB 042 400EV Multibox | K5: 580 | L5: 250 | M5: =IF(ISERROR(VLOOKUP(J5,'Germany price'!$B$1:$G$99001,6,0))," ",VLOOKUP(J5,'Germany price'!$B$1:$G$99001,6,0)) -> 1199 | N5: 1199 | O5: 0.58 | P5: 1 | Q5: =N5*P5*(1-O5) -> 503.58 | R5: =R4 -> 0 | S5: =Q5*(1-R5) -> 503.58 | T5: =(Q5*AE5)/AF5 -> 26.65775 | U5: =T5+S5 -> 530.23775 | V5: 0 | W5: =1.14 -> 1.14 | X5: =X4 -> 1.1235 | Y5: =Y4 -> 1 | Z5: =U5*X5*Y5*W5*(1+V5) -> 679.12321 | AA5: =AA4 -> 0.50014493 | AB5: =AC5/P5 -> 1018.7832 | AC5: =U5*X5*(1+AA5)*Y5*W5*(1+V5) -> 1018.7832 | AE5: =AE4 -> 170000 | AF5: =AF4 -> 3211396.3 | AK5: 0.1 | AL5: Germany | AM5: Inline Fan | AN5: Double | AO5: Ambient | AP5: 0.1
A6: =VALUE(RIGHT(B6,LEN(B6)-2)) -> 3 | B6: F-03 | D6: FAF-A30-B02-01 | E6: Sweden | F6: Inline Fan | G6: Single | H6: Ambient | I6: 93097 | J6: KT 60-30-4 | K6: 855 | L6: 250 | M6: =IF(ISERROR(VLOOKUP(J6,'Germany price'!$B$1:$G$99001,6,0))," ",VLOOKUP(J6,'Germany price'!$B$1:$G$99001,6,0)) -> 1182 | N6: 1182 | O6: 0.58 | P6: 1 | Q6: =N6*P6*(1-O6) -> 496.44 | R6: =R5 -> 0 | S6: =Q6*(1-R6) -> 496.44 | T6: =(Q6*AE6)/AF6 -> 26.279783 | U6: =T6+S6 -> 522.71978 | V6: 0 | W6: =1.14 -> 1.14 | X6: =X5 -> 1.1235 | Y6: =Y5 -> 1 | Z6: =U6*X6*Y6*W6*(1+V6) -> 669.49427 | AA6: =AA5 -> 0.50014493 | AB6: =AC6/P6 -> 1004.3384 | AC6: =U6*X6*(1+AA6)*Y6*W6*(1+V6) -> 1004.3384 | AE6: =AE5 -> 170000 | AF6: =AF5 -> 3211396.3 | AK6: 0.6 | AL6: Malaysia | AM6: Wall Mounted | AO6: Explosion | AP6: 0.11
A7: =VALUE(RIGHT(B7,LEN(B7)-2)) -> 4 | B7: F-04 | D7: FAF-A35-B02-01 | E7: Germany | F7: Axial Inline | G7: Single | H7: Ambient | I7: CAP040120001F | J7: AXC 400-6/31°-2-P (160) (2.2 kW) S IE3 C | K7: 2240 | L7: 250 | M7: =IF(ISERROR(VLOOKUP(J7,'Germany price'!$B$1:$G$99001,6,0))," ",VLOOKUP(J7,'Germany price'!$B$1:$G$99001,6,0)) | N7: 1499 | O7: 0.58 | P7: 2 | Q7: =N7*P7*(1-O7) -> 1259.16 | R7: =R6 -> 0 | S7: =Q7*(1-R7) -> 1259.16 | T7: =(Q7*AE7)/AF7 -> 66.655491 | U7: =T7+S7 -> 1325.8155 | V7: 0 | W7: =1.14 -> 1.14 | X7: =X6 -> 1.1235 | Y7: =Y6 -> 1 | Z7: =U7*X7*Y7*W7*(1+V7) -> 1698.0912 | AA7: =AA6 -> 0.50014493 | AB7: =AC7/P7 -> 1273.6915 | AC7: =U7*X7*(1+AA7)*Y7*W7*(1+V7) -> 2547.3829 | AE7: =AE6 -> 170000 | AF7: =AF6 -> 3211396.3 | AL7: Italy | AM7: Fan Section | AO7: 120°C | AP7: 0.12
A8: =VALUE(RIGHT(B8,LEN(B8)-2)) -> 5 | B8: F-05 | D8: FAF-A35-B02-02 | E8: Germany | F8: Centrifugal Fan | G8: Single | H8: Ambient | I8: 334079 | J8: PRF 355D4 | K8: 1125 | L8: 250 | M8: =IF(ISERROR(VLOOKUP(J8,'Germany price'!$B$1:$G$99001,6,0))," ",VLOOKUP(J8,'Germany price'!$B$1:$G$99001,6,0)) -> 6324 | N8: 6324 | O8: 0.58 | P8: 1 | Q8: =N8*P8*(1-O8) -> 2656.08 | R8: =R7 -> 0 | S8: =Q8*(1-R8) -> 2656.08 | T8: =(Q8*AE8)/AF8 -> 140.60351 | U8: =T8+S8 -> 2796.6835 | V8: 0 | W8: =1.14 -> 1.14 | X8: =X7 -> 1.1235 | Y8: =Y7 -> 1 | Z8: =U8*X8*Y8*W8*(1+V8) -> 3581.9643 | AA8: =AA7 -> 0.50014493 | AB8: =AC8/P8 -> 5373.4656 | AC8: =U8*X8*(1+AA8)*Y8*W8*(1+V8) -> 5373.4656 | AE8: =AE7 -> 170000 | AF8: =AF7 -> 3211396.3 | AL8: UAE | AM8: Axial Roof Top | AP8: 0.13
A9: =VALUE(RIGHT(B9,LEN(B9)-2)) -> 6 | B9: F-06 | D9: FAF-B30-B02-02 | E9: Sweden | F9: Inline Fan | G9: Single | H9: Ambient | I9: 19514 | J9: K 315 L Sileo** | K9: 340 | L9: 125 | M9: =IF(ISERROR(VLOOKUP(J9,'Germany price'!$B$1:$G$99001,6,0))," ",VLOOKUP(J9,'Germany price'!$B$1:$G$99001,6,0)) -> 330 | N9: 330 | O9: 0.58 | P9: 1 | Q9: =N9*P9*(1-O9) -> 138.6 | R9: =R8 -> 0 | S9: =Q9*(1-R9) -> 138.6 | T9: =(Q9*AE9)/AF9 -> 7.3369953 | U9: =T9+S9 -> 145.937 | V9: 0 | W9: =1.14 -> 1.14 | X9: =X8 -> 1.1235 | Y9: =Y8 -> 1 | Z9: =U9*X9*Y9*W9*(1+V9) -> 186.91464 | AA9: =AA8 -> 0.50014493 | AB9: =AC9/P9 -> 280.39906 | AC9: =U9*X9*(1+AA9)*Y9*W9*(1+V9) -> 280.39906 | AE9: =AE8 -> 170000 | AF9: =AF8 -> 3211396.3 | AL9: Slovenia | AM9: Centrifugal Roof Top | AP9: 0.14
A10: =VALUE(RIGHT(B10,LEN(B10)-2)) -> 7 | B10: F-07 | D10: FAF-B35-B02-01 | E10: Sweden | F10: Inline Fan | G10: Single | H10: Ambient | I10: 93098 | J10: KT 60-35-4 | K10: 1025 | L10: 250 | M10: =IF(ISERROR(VLOOKUP(J10,'Germany price'!$B$1:$G$99001,6,0))," ",VLOOKUP(J10,'Germany price'!$B$1:$G$99001,6,0)) -> 1443 | N10: 1443 | O10: 0.58 | P10: 1 | Q10: =N10*P10*(1-O10) -> 606.06 | R10: =R9 -> 0 | S10: =Q10*(1-R10) -> 606.06 | T10: =(Q10*AE10)/AF10 -> 32.08268 | U10: =T10+S10 -> 638.14268 | V10: 0 | W10: =1.14 -> 1.14 | X10: =X9 -> 1.1235 | Y10: =Y9 -> 1 | Z10: =U10*X10*Y10*W10*(1+V10) -> 817.32676 | AA10: =AA9 -> 0.50014493 | AB10: =AC10/P10 -> 1226.1086 | AC10: =U10*X10*(1+AA10)*Y10*W10*(1+V10) -> 1226.1086 | AE10: =AE9 -> 170000 | AF10: =AF9 -> 3211396.3 | AL10: Egypt | AM10: Induction Jet Fan | AP10: 0.15
A11: =VALUE(RIGHT(B11,LEN(B11)-2)) -> 8 | B11: F-08 | D11: FAF-B35-B02-02 | E11: Germany | F11: Axial Inline | G11: Single | H11: Ambient | I11: CAPV080340001H | J11: AXC 800-6/20°-4-PV (350) (4 kW) S IE3 A | K11: 5800 | L11: 375 | M11: =IF(ISERROR(VLOOKUP(J11,'Germany price'!$B$1:$G$99001,6,0))," ",VLOOKUP(J11,'Germany price'!$B$1:$G$99001,6,0)) | N11: 3240 | O11: 0.58 | P11: 2 | Q11: =N11*P11*(1-O11) -> 2721.6 | R11: =R10 -> 0 | S11: =Q11*(1-R11) -> 2721.6 | T11: =(Q11*AE11)/AF11 -> 144.07191 | U11: =T11+S11 -> 2865.6719 | V11: 0 | W11: =1.14 -> 1.14 | X11: =X10 -> 1.1235 | Y11: =Y10 -> 1 | Z11: =U11*X11*Y11*W11*(1+V11) -> 3670.3239 | AA11: =AA10 -> 0.50014493 | AB11: =AC11/P11 -> 2753.0089 | AC11: =U11*X11*(1+AA11)*Y11*W11*(1+V11) -> 5506.0178 | AE11: =AE10 -> 170000 | AF11: =AF10 -> 3211396.3 | AL11: Turkey | AM11: Impulse Jet Fan | AP11: 0.2
A12: =VALUE(RIGHT(B12,LEN(B12)-2)) -> 9 | B12: F-09 | D12: FAF-B35-B02-03 | E12: Germany | F12: Axial Inline | G12: Single | H12: Ambient | I12: CAP045120001F | J12: AXC 450-6/23°-2-P (200) (2.2 kW) S IE3 | K12: 2405 | L12: 375 | M12: =IF(ISERROR(VLOOKUP(J12,'Germany price'!$B$1:$G$99001,6,0))," ",VLOOKUP(J12,'Germany price'!$B$1:$G$99001,6,0)) | N12: 1666 | O12: 0.58 | P12: 1 | Q12: =N12*P12*(1-O12) -> 699.72 | R12: =R11 -> 0 | S12: =Q12*(1-R12) -> 699.72 | T12: =(Q12*AE12)/AF12 -> 37.04071 | U12: =T12+S12 -> 736.76071 | V12: 0 | W12: =1.14 -> 1.14 | X12: =X11 -> 1.1235 | Y12: =Y11 -> 1 | Z12: =U12*X12*Y12*W12*(1+V12) -> 943.63575 | AA12: =AA11 -> 0.50014493 | AB12: =AC12/P12 -> 1415.5904 | AC12: =U12*X12*(1+AA12)*Y12*W12*(1+V12) -> 1415.5904 | AE12: =AE11 -> 170000 | AF12: =AF11 -> 3211396.3 | AM12: Belt Driven Box fan | AP12: 0.25
A13: =VALUE(RIGHT(B13,LEN(B13)-2)) -> 10 | B13: F-10 | D13: FAF-B35-B02-04 | E13: Sweden | F13: Inline Fan | G13: Single | H13: Ambient | I13: 27758 | J13: K 315 M sileo** | K13: 210 | L13: 250 | M13: =IF(ISERROR(VLOOKUP(J13,'Germany price'!$B$1:$G$99001,6,0))," ",VLOOKUP(J13,'Germany price'!$B$1:$G$99001,6,0)) -> 276 | N13: 276 | O13: 0.58 | P13: 1 | Q13: =N13*P13*(1-O13) -> 115.92 | R13: =R12 -> 0 | S13: =Q13*(1-R13) -> 115.92 | T13: =(Q13*AE13)/AF13 -> 6.1363961 | U13: =T13+S13 -> 122.0564 | V13: 0 | W13: =1.14 -> 1.14 | X13: =X12 -> 1.1235 | Y13: =Y12 -> 1 | Z13: =U13*X13*Y13*W13*(1+V13) -> 156.32861 | AA13: =AA12 -> 0.50014493 | AB13: =AC13/P13 -> 234.51557 | AC13: =U13*X13*(1+AA13)*Y13*W13*(1+V13) -> 234.51557 | AE13: =AE12 -> 170000 | AF13: =AF12 -> 3211396.3 | AM13: Centrifugal Box Fan | AP13: 0.3
A14: =VALUE(RIGHT(B14,LEN(B14)-2)) -> 11 | B14: F-11 | D14: FAF-C29-B02-01 | E14: Sweden | F14: Inline Fan | G14: Single | H14: Ambient | I14: 93098 | J14: KT 60-35-4 | K14: 1145 | L14: 250 | M14: =IF(ISERROR(VLOOKUP(J14,'Germany price'!$B$1:$G$99001,6,0))," ",VLOOKUP(J14,'Germany price'!$B$1:$G$99001,6,0)) -> 1443 | N14: 1443 | O14: 0.58 | P14: 1 | Q14: =N14*P14*(1-O14) -> 606.06 | R14: =R13 -> 0 | S14: =Q14*(1-R14) -> 606.06 | T14: =(Q14*AE14)/AF14 -> 32.08268 | U14: =T14+S14 -> 638.14268 | V14: 0 | W14: =1.14 -> 1.14 | X14: =X13 -> 1.1235 | Y14: =Y13 -> 1 | Z14: =U14*X14*Y14*W14*(1+V14) -> 817.32676 | AA14: =AA13 -> 0.50014493 | AB14: =AC14/P14 -> 1226.1086 | AC14: =U14*X14*(1+AA14)*Y14*W14*(1+V14) -> 1226.1086 | AE14: =AE13 -> 170000 | AF14: =AF13 -> 3211396.3 | AM14: Centrifugal Fan | AP14: 0.35
A15: =VALUE(RIGHT(B15,LEN(B15)-2)) -> 12 | B15: F-12 | D15: FAF-C29-B02-02 | E15: Sweden | F15: Inline Fan | G15: Single | H15: Ambient | I15: 93097 | J15: KT 60-30-4 | K15: 725 | L15: 250 | M15: =IF(ISERROR(VLOOKUP(J15,'Germany price'!$B$1:$G$99001,6,0))," ",VLOOKUP(J15,'Germany price'!$B$1:$G$99001,6,0)) -> 1182 | N15: 1182 | O15: 0.58 | P15: 1 | Q15: =N15*P15*(1-O15) -> 496.44 | R15: =R14 -> 0 | S15: =Q15*(1-R15) -> 496.44 | T15: =(Q15*AE15)/AF15 -> 26.279783 | U15: =T15+S15 -> 522.71978 | V15: 0 | W15: =1.14 -> 1.14 | X15: =X14 -> 1.1235 | Y15: =Y14 -> 1 | Z15: =U15*X15*Y15*W15*(1+V15) -> 669.49427 | AA15: =AA14 -> 0.50014493 | AB15: =AC15/P15 -> 1004.3384 | AC15: =U15*X15*(1+AA15)*Y15*W15*(1+V15) -> 1004.3384 | AE15: =AE14 -> 170000 | AF15: =AF14 -> 3211396.3 | AM15: Accessories | AP15: 0.4
A16: =VALUE(RIGHT(B16,LEN(B16)-2)) -> 13 | B16: F-13 | D16: FAF-C29-B02-03 | E16: Germany | F16: Axial Inline | G16: Single | H16: Ambient | I16: CAP080340001H | J16: AXC 800-6/17°-4-P (350) (4 kW) S IE3 | K16: 4450 | L16: 375 | M16: =IF(ISERROR(VLOOKUP(J16,'Germany price'!$B$1:$G$99001,6,0))," ",VLOOKUP(J16,'Germany price'!$B$1:$G$99001,6,0)) | N16: 2721 | O16: 0.58 | P16: 2 | Q16: =N16*P16*(1-O16) -> 2285.64 | R16: =R15 -> 0 | S16: =Q16*(1-R16) -> 2285.64 | T16: =(Q16*AE16)/AF16 -> 120.99372 | U16: =T16+S16 -> 2406.6337 | V16: 0 | W16: =1.14 -> 1.14 | X16: =X15 -> 1.1235 | Y16: =Y15 -> 1 | Z16: =U16*X16*Y16*W16*(1+V16) -> 3082.3924 | AA16: =AA15 -> 0.50014493 | AB16: =AC16/P16 -> 2312.0177 | AC16: =U16*X16*(1+AA16)*Y16*W16*(1+V16) -> 4624.0354 | AE16: =AE15 -> 170000 | AF16: =AF15 -> 3211396.3 | AM16: Planum Fan | AP16: 0.45
A17: =VALUE(RIGHT(B17,LEN(B17)-2)) -> 14 | B17: F-14 | D17: FAF-C29-B02-04 | E17: Germany | F17: Centrifugal Fan | G17: Single | H17: Ambient | I17: 334079 | J17: PRF 355D4 | K17: 785 | L17: 250 | M17: =IF(ISERROR(VLOOKUP(J17,'Germany price'!$B$1:$G$99001,6,0))," ",VLOOKUP(J17,'Germany price'!$B$1:$G$99001,6,0)) -> 6324 | N17: 6324 | O17: 0.58 | P17: 1 | Q17: =N17*P17*(1-O17) -> 2656.08 | R17: =R16 -> 0 | S17: =Q17*(1-R17) -> 2656.08 | T17: =(Q17*AE17)/AF17 -> 140.60351 | U17: =T17+S17 -> 2796.6835 | V17: 0 | W17: =1.14 -> 1.14 | X17: =X16 -> 1.1235 | Y17: =Y16 -> 1 | Z17: =U17*X17*Y17*W17*(1+V17) -> 3581.9643 | AA17: =AA16 -> 0.50014493 | AB17: =AC17/P17 -> 5373.4656 | AC17: =U17*X17*(1+AA17)*Y17*W17*(1+V17) -> 5373.4656 | AE17: =AE16 -> 170000 | AF17: =AF16 -> 3211396.3 | AM17: SISW Fan | AP17: 0.58
A18: =VALUE(RIGHT(B18,LEN(B18)-2)) -> 15 | B18: F-15 | D18: FAF-C35-B02-01 | E18: Sweden | F18: Inline Fan | G18: Single | H18: Ambient | I18: 27758 | J18: K 315 M sileo** | K18: 250 | L18: 125 | M18: =IF(ISERROR(VLOOKUP(J18,'Germany price'!$B$1:$G$99001,6,0))," ",VLOOKUP(J18,'Germany price'!$B$1:$G$99001,6,0)) -> 276 | N18: 276 | O18: 0.58 | P18: 1 | Q18: =N18*P18*(1-O18) -> 115.92 | R18: =R17 -> 0 | S18: =Q18*(1-R18) -> 115.92 | T18: =(Q18*AE18)/AF18 -> 6.1363961 | U18: =T18+S18 -> 122.0564 | V18: 0 | W18: =1.14 -> 1.14 | X18: =X17 -> 1.1235 | Y18: =Y17 -> 1 | Z18: =U18*X18*Y18*W18*(1+V18) -> 156.32861 | AA18: =AA17 -> 0.50014493 | AB18: =AC18/P18 -> 234.51557 | AC18: =U18*X18*(1+AA18)*Y18*W18*(1+V18) -> 234.51557 | AE18: =AE17 -> 170000 | AF18: =AF17 -> 3211396.3 | AM18: Hood Fan
A19: =VALUE(RIGHT(B19,LEN(B19)-2)) -> 16 | B19: F-16 | D19: FAF-C35-B02-03 | E19: Germany | F19: Axial Inline | G19: Single | H19: Ambient | I19: CAP035120001D | J19: AXC 355-6/25°-2-P (160) (1.1 kW) S IE3 | K19: 1248 | L19: 250 | M19: =IF(ISERROR(VLOOKUP(J19,'Germany price'!$B$1:$G$99001,6,0))," ",VLOOKUP(J19,'Germany price'!$B$1:$G$99001,6,0)) | N19: 1401 | O19: 0.58 | P19: 1 | Q19: =N19*P19*(1-O19) -> 588.42 | R19: =R18 -> 0 | S19: =Q19*(1-R19) -> 588.42 | T19: =(Q19*AE19)/AF19 -> 31.14888 | U19: =T19+S19 -> 619.56888 | V19: 0 | W19: =1.14 -> 1.14 | X19: =X18 -> 1.1235 | Y19: =Y18 -> 1 | Z19: =U19*X19*Y19*W19*(1+V19) -> 793.53763 | AA19: =AA18 -> 0.50014493 | AB19: =AC19/P19 -> 1190.4214 | AC19: =U19*X19*(1+AA19)*Y19*W19*(1+V19) -> 1190.4214 | AE19: =AE18 -> 170000 | AF19: =AF18 -> 3211396.3
A20: =VALUE(RIGHT(B20,LEN(B20)-2)) -> 17 | B20: F-17 | D20: FAF-A34-B02-01 | E20: Sweden | F20: Inline Fan | G20: Single | H20: Ambient | I20: 93097 | J20: KT 60-30-4 | K20: 745 | L20: 250 | M20: =IF(ISERROR(VLOOKUP(J20,'Germany price'!$B$1:$G$99001,6,0))," ",VLOOKUP(J20,'Germany price'!$B$1:$G$99001,6,0)) -> 1182 | N20: 1182 | O20: 0.58 | P20: 1 | Q20: =N20*P20*(1-O20) -> 496.44 | R20: =R19 -> 0 | S20: =Q20*(1-R20) -> 496.44 | T20: =(Q20*AE20)/AF20 -> 26.279783 | U20: =T20+S20 -> 522.71978 | V20: 0 | W20: =1.14 -> 1.14 | X20: =X19 -> 1.1235 | Y20: =Y19 -> 1 | Z20: =U20*X20*Y20*W20*(1+V20) -> 669.49427 | AA20: =AA19 -> 0.50014493 | AB20: =AC20/P20 -> 1004.3384 | AC20: =U20*X20*(1+AA20)*Y20*W20*(1+V20) -> 1004.3384 | AE20: =AE19 -> 170000 | AF20: =AF19 -> 3211396.3
A21: =VALUE(RIGHT(B21,LEN(B21)-2)) -> 18 | B21: F-18 | D21: FAF-A30-B01-01 | E21: Germany | F21: Axial Inline | G21: Single | H21: Ambient | I21: CAP040120001F | J21: AXC 400-6/31°-2-P (160) (2.2 kW) S IE3 C | K21: 2230 | L21: 250 | M21: =IF(ISERROR(VLOOKUP(J21,'Germany price'!$B$1:$G$99001,6,0))," ",VLOOKUP(J21,'Germany price'!$B$1:$G$99001,6,0)) | N21: 1561 | O21: 0.58 | P21: 2 | Q21: =N21*P21*(1-O21) -> 1311.24 | R21: =R20 -> 0 | S21: =Q21*(1-R21) -> 1311.24 | T21: =(Q21*AE21)/AF21 -> 69.412423 | U21: =T21+S21 -> 1380.6524 | V21: 0 | W21: =1.14 -> 1.14 | X21: =X20 -> 1.1235 | Y21: =Y20 -> 1 | Z21: =U21*X21*Y21*W21*(1+V21) -> 1768.3258 | AA21: =AA20 -> 0.50014493 | AB21: =AC21/P21 -> 1326.3725 | AC21: =U21*X21*(1+AA21)*Y21*W21*(1+V21) -> 2652.745 | AE21: =AE20 -> 170000 | AF21: =AF20 -> 3211396.3
A22: =VALUE(RIGHT(B22,LEN(B22)-2)) -> 19 | B22: F-19 | D22: FAF-A30-B01-02 | E22: Germany | F22: Centrifugal Fan | G22: Single | H22: Ambient | I22: 476764 | J22: PRF 250D4 | K22: 720 | L22: 250 | M22: =IF(ISERROR(VLOOKUP(J22,'Germany price'!$B$1:$G$99001,6,0))," ",VLOOKUP(J22,'Germany price'!$B$1:$G$99001,6,0)) -> 2020 | N22: 2020 | O22: 0.58 | P22: 1 | Q22: =N22*P22*(1-O22) -> 848.4 | R22: =R21 -> 0 | S22: =Q22*(1-R22) -> 848.4 | T22: =(Q22*AE22)/AF22 -> 44.911305 | U22: =T22+S22 -> 893.3113 | V22: 0 | W22: =1.14 -> 1.14 | X22: =X21 -> 1.1235 | Y22: =Y21 -> 1 | Z22: =U22*X22*Y22*W22*(1+V22) -> 1144.1442 | AA22: =AA21 -> 0.50014493 | AB22: =AC22/P22 -> 1716.3821 | AC22: =U22*X22*(1+AA22)*Y22*W22*(1+V22) -> 1716.3821 | AE22: =AE21 -> 170000 | AF22: =AF21 -> 3211396.3
A23: =VALUE(RIGHT(B23,LEN(B23)-2)) -> 20 | B23: F-20 | D23: FAF-A30-B01-03 | E23: Sweden | F23: Inline Fan | G23: Single | H23: Ambient | I23: 19514 | J23: K 315 L Sileo** | K23: 310 | L23: 250 | M23: =IF(ISERROR(VLOOKUP(J23,'Germany price'!$B$1:$G$99001,6,0))," ",VLOOKUP(J23,'Germany price'!$B$1:$G$99001,6,0)) -> 330 | N23: 330 | O23: 0.58 | P23: 1 | Q23: =N23*P23*(1-O23) -> 138.6 | R23: =R22 -> 0 | S23: =Q23*(1-R23) -> 138.6 | T23: =(Q23*AE23)/AF23 -> 7.3369953 | U23: =T23+S23 -> 145.937 | V23: 0 | W23: =1.14 -> 1.14 | X23: =X22 -> 1.1235 | Y23: =Y22 -> 1 | Z23: =U23*X23*Y23*W23*(1+V23) -> 186.91464 | AA23: =AA22 -> 0.50014493 | AB23: =AC23/P23 -> 280.39906 | AC23: =U23*X23*(1+AA23)*Y23*W23*(1+V23) -> 280.39906 | AE23: =AE22 -> 170000 | AF23: =AF22 -> 3211396.3
A24: =VALUE(RIGHT(B24,LEN(B24)-2)) -> 21 | B24: F-21 | D24: FAF-A30-B01-04 | E24: Sweden | F24: Inline Fan | G24: Single | H24: Ambient | I24: 19512 | J24: K 250 L sileo | K24: 235 | L24: 125 | M24: =IF(ISERROR(VLOOKUP(J24,'Germany price'!$B$1:$G$99001,6,0))," ",VLOOKUP(J24,'Germany price'!$B$1:$G$99001,6,0)) -> 223 | N24: 223 | O24: 0.58 | P24: 1 | Q24: =N24*P24*(1-O24) -> 93.66 | R24: =R23 -> 0 | S24: =Q24*(1-R24) -> 93.66 | T24: =(Q24*AE24)/AF24 -> 4.9580302 | U24: =T24+S24 -> 98.61803 | V24: 0 | W24: =1.14 -> 1.14 | X24: =X23 -> 1.1235 | Y24: =Y23 -> 1 | Z24: =U24*X24*Y24*W24*(1+V24) -> 126.30899 | AA24: =AA23 -> 0.50014493 | AB24: =AC24/P24 -> 189.48179 | AC24: =U24*X24*(1+AA24)*Y24*W24*(1+V24) -> 189.48179 | AE24: =AE23 -> 170000 | AF24: =AF23 -> 3211396.3
A25: =VALUE(RIGHT(B25,LEN(B25)-2)) -> 22 | B25: F-22 | D25: FAF-A30-B01-05 | E25: Germany | F25: Centrifugal Inline | G25: Single | H25: Ambient | I25: 235403 | J25: MUB 042 400EV Multibox | K25: 625 | L25: 250 | M25: =IF(ISERROR(VLOOKUP(J25,'Germany price'!$B$1:$G$99001,6,0))," ",VLOOKUP(J25,'Germany price'!$B$1:$G$99001,6,0)) -> 1199 | N25: 1199 | O25: 0.58 | P25: 1 | Q25: =N25*P25*(1-O25) -> 503.58 | R25: =R24 -> 0 | S25: =Q25*(1-R25) -> 503.58 | T25: =(Q25*AE25)/AF25 -> 26.65775 | U25: =T25+S25 -> 530.23775 | V25: 0 | W25: =1.14 -> 1.14 | X25: =X24 -> 1.1235 | Y25: =Y24 -> 1 | Z25: =U25*X25*Y25*W25*(1+V25) -> 679.12321 | AA25: =AA24 -> 0.50014493 | AB25: =AC25/P25 -> 1018.7832 | AC25: =U25*X25*(1+AA25)*Y25*W25*(1+V25) -> 1018.7832 | AE25: =AE24 -> 170000 | AF25: =AF24 -> 3211396.3
A26: =VALUE(RIGHT(B26,LEN(B26)-2)) -> 23 | B26: F-23 | D26: FAF-A34-B01-01 | E26: Germany | F26: Centrifugal Inline | G26: Single | H26: Ambient | I26: 276520 | J26: MUB 042 450DV Multibox | K26: 925 | L26: 250 | M26: =IF(ISERROR(VLOOKUP(J26,'Germany price'!$B$1:$G$99001,6,0))," ",VLOOKUP(J26,'Germany price'!$B$1:$G$99001,6,0)) -> 1339 | N26: 1339 | O26: 0.58 | P26: 1 | Q26: =N26*P26*(1-O26) -> 562.38 | R26: =R25 -> 0 | S26: =Q26*(1-R26) -> 562.38 | T26: =(Q26*AE26)/AF26 -> 29.770414 | U26: =T26+S26 -> 592.15041 | V26: 0 | W26: =1.14 -> 1.14 | X26: =X25 -> 1.1235 | Y26: =Y25 -> 1 | Z26: =U26*X26*Y26*W26*(1+V26) -> 758.42033 | AA26: =AA25 -> 0.50014493 | AB26: =AC26/P26 -> 1137.7404 | AC26: =U26*X26*(1+AA26)*Y26*W26*(1+V26) -> 1137.7404 | AE26: =AE25 -> 170000 | AF26: =AF25 -> 3211396.3
A27: =VALUE(RIGHT(B27,LEN(B27)-2)) -> 24 | B27: F-24 | D27: FAF-A34-B01-02 | E27: Germany | F27: Centrifugal Fan | G27: Single | H27: Ambient | I27: 476764 | J27: PRF 250D4 | K27: 545 | L27: 250 | M27: =IF(ISERROR(VLOOKUP(J27,'Germany price'!$B$1:$G$99001,6,0))," ",VLOOKUP(J27,'Germany price'!$B$1:$G$99001,6,0)) -> 2020 | N27: 2020 | O27: 0.58 | P27: 1 | Q27: =N27*P27*(1-O27) -> 848.4 | R27: =R26 -> 0 | S27: =Q27*(1-R27) -> 848.4 | T27: =(Q27*AE27)/AF27 -> 44.911305 | U27: =T27+S27 -> 893.3113 | V27: 0 | W27: =1.14 -> 1.14 | X27: =X26 -> 1.1235 | Y27: =Y26 -> 1 | Z27: =U27*X27*Y27*W27*(1+V27) -> 1144.1442 | AA27: =AA26 -> 0.50014493 | AB27: =AC27/P27 -> 1716.3821 | AC27: =U27*X27*(1+AA27)*Y27*W27*(1+V27) -> 1716.3821 | AE27: =AE26 -> 170000 | AF27: =AF26 -> 3211396.3
A28: =VALUE(RIGHT(B28,LEN(B28)-2)) -> 25 | B28: F-25 | D28: FAF-A37-B01-01 | E28: Germany | F28: Axial Inline | G28: Single | H28: Ambient | I28: CAP040120001E | J28: AXC 400-6/23°-2-P (160) (1.5 kW) S IE3 C | K28: 1780 | L28: 250 | M28: =IF(ISERROR(VLOOKUP(J28,'Germany price'!$B$1:$G$99001,6,0))," ",VLOOKUP(J28,'Germany price'!$B$1:$G$99001,6,0)) | N28: 1499 | O28: 0.58 | P28: 2 | Q28: =N28*P28*(1-O28) -> 1259.16 | R28: =R27 -> 0 | S28: =Q28*(1-R28) -> 1259.16 | T28: =(Q28*AE28)/AF28 -> 66.655491 | U28: =T28+S28 -> 1325.8155 | V28: 0 | W28: =1.14 -> 1.14 | X28: =X27 -> 1.1235 | Y28: =Y27 -> 1 | Z28: =U28*X28*Y28*W28*(1+V28) -> 1698.0912 | AA28: =AA27 -> 0.50014493 | AB28: =AC28/P28 -> 1273.6915 | AC28: =U28*X28*(1+AA28)*Y28*W28*(1+V28) -> 2547.3829 | AE28: =AE27 -> 170000 | AF28: =AF27 -> 3211396.3
A29: =VALUE(RIGHT(B29,LEN(B29)-2)) -> 26 | B29: F-26 | D29: FAF-A37-B01-02 | E29: Sweden | F29: Inline Fan | G29: Single | H29: Ambient | I29: 25365 | J29: K 160 XL sileo | K29: 155 | L29: 125 | M29: =IF(ISERROR(VLOOKUP(J29,'Germany price'!$B$1:$G$99001,6,0))," ",VLOOKUP(J29,'Germany price'!$B$1:$G$99001,6,0)) -> 171 | N29: 171 | O29: 0.58 | P29: 1 | Q29: =N29*P29*(1-O29) -> 71.82 | R29: =R28 -> 0 | S29: =Q29*(1-R29) -> 71.82 | T29: =(Q29*AE29)/AF29 -> 3.8018976 | U29: =T29+S29 -> 75.621898 | V29: 0 | W29: =1.14 -> 1.14 | X29: =X28 -> 1.1235 | Y29: =Y28 -> 1 | Z29: =U29*X29*Y29*W29*(1+V29) -> 96.85577 | AA29: =AA28 -> 0.50014493 | AB29: =AC29/P29 -> 145.29769 | AC29: =U29*X29*(1+AA29)*Y29*W29*(1+V29) -> 145.29769 | AE29: =AE28 -> 170000 | AF29: =AF28 -> 3211396.3
A30: =VALUE(RIGHT(B30,LEN(B30)-2)) -> 27 | B30: F-27 | D30: FAF-A37-B01-03 | E30: Germany | F30: Axial Inline | G30: Single | H30: Ambient | I30: CAP035120001D | J30: AXC 355-6/25°-2-P (160) (1.1 kW) S IE3 C | K30: 1250 | L30: 250 | M30: =IF(ISERROR(VLOOKUP(J30,'Germany price'!$B$1:$G$99001,6,0))," ",VLOOKUP(J30,'Germany price'!$B$1:$G$99001,6,0)) | N30: 1401 | O30: 0.58 | P30: 1 | Q30: =N30*P30*(1-O30) -> 588.42 | R30: =R29 -> 0 | S30: =Q30*(1-R30) -> 588.42 | T30: =(Q30*AE30)/AF30 -> 31.14888 | U30: =T30+S30 -> 619.56888 | V30: 0 | W30: =1.14 -> 1.14 | X30: =X29 -> 1.1235 | Y30: =Y29 -> 1 | Z30: =U30*X30*Y30*W30*(1+V30) -> 793.53763 | AA30: =AA29 -> 0.50014493 | AB30: =AC30/P30 -> 1190.4214 | AC30: =U30*X30*(1+AA30)*Y30*W30*(1+V30) -> 1190.4214 | AE30: =AE29 -> 170000 | AF30: =AF29 -> 3211396.3
A31: =VALUE(RIGHT(B31,LEN(B31)-2)) -> 28 | B31: F-28 | D31: FAF-B30-B01-02 | E31: Germany | F31: Axial Inline | G31: Single | H31: Ambient | I31: CAP071140001G | J31: AXC 710-9/20°-4-P (350) (3 kW) S IE3 C | K31: 3570 | L31: 375 | M31: =IF(ISERROR(VLOOKUP(J31,'Germany price'!$B$1:$G$99001,6,0))," ",VLOOKUP(J31,'Germany price'!$B$1:$G$99001,6,0)) | N31: 2515 | O31: 0.58 | P31: 2 | Q31: =N31*P31*(1-O31) -> 2112.6 | R31: =R30 -> 0 | S31: =Q31*(1-R31) -> 2112.6 | T31: =(Q31*AE31)/AF31 -> 111.8336 | U31: =T31+S31 -> 2224.4336 | V31: 0 | W31: =1.14 -> 1.14 | X31: =X30 -> 1.1235 | Y31: =Y30 -> 1 | Z31: =U31*X31*Y31*W31*(1+V31) -> 2849.0323 | AA31: =AA30 -> 0.50014493 | AB31: =AC31/P31 -> 2136.9807 | AC31: =U31*X31*(1+AA31)*Y31*W31*(1+V31) -> 4273.9614 | AE31: =AE30 -> 170000 | AF31: =AF30 -> 3211396.3
A32: =VALUE(RIGHT(B32,LEN(B32)-2)) -> 29 | B32: F-29 | D32: FAF-B30-B01-03 | E32: Germany | F32: Centrifugal Inline | G32: Single | H32: Ambient | I32: 235401 | J32: MUB 025 355EV Multibox | K32: 520 | L32: 125 | M32: =IF(ISERROR(VLOOKUP(J32,'Germany price'!$B$1:$G$99001,6,0))," ",VLOOKUP(J32,'Germany price'!$B$1:$G$99001,6,0)) -> 999 | N32: 999 | O32: 0.58 | P32: 1 | Q32: =N32*P32*(1-O32) -> 419.58 | R32: =R31 -> 0 | S32: =Q32*(1-R32) -> 419.58 | T32: =(Q32*AE32)/AF32 -> 22.211086 | U32: =T32+S32 -> 441.79109 | V32: 0 | W32: =1.14 -> 1.14 | X32: =X31 -> 1.1235 | Y32: =Y31 -> 1 | Z32: =U32*X32*Y32*W32*(1+V32) -> 565.8416 | AA32: =AA31 -> 0.50014493 | AB32: =AC32/P32 -> 848.84442 | AC32: =U32*X32*(1+AA32)*Y32*W32*(1+V32) -> 848.84442 | AE32: =AE31 -> 170000 | AF32: =AF31 -> 3211396.3
A33: =VALUE(RIGHT(B33,LEN(B33)-2)) -> 30 | B33: F-30 | D33: FAF-B34-B01-02 | E33: Sweden | F33: Inline Fan | G33: Single | H33: Ambient | I33: 19512 | J33: K 250 L sileo | K33: 230 | L33: 125 | M33: =IF(ISERROR(VLOOKUP(J33,'Germany price'!$B$1:$G$99001,6,0))," ",VLOOKUP(J33,'Germany price'!$B$1:$G$99001,6,0)) -> 223 | N33: 223 | O33: 0.58 | P33: 1 | Q33: =N33*P33*(1-O33) -> 93.66 | R33: =R32 -> 0 | S33: =Q33*(1-R33) -> 93.66 | T33: =(Q33*AE33)/AF33 -> 4.9580302 | U33: =T33+S33 -> 98.61803 | V33: 0 | W33: =1.14 -> 1.14 | X33: =X32 -> 1.1235 | Y33: =Y32 -> 1 | Z33: =U33*X33*Y33*W33*(1+V33) -> 126.30899 | AA33: =AA32 -> 0.50014493 | AB33: =AC33/P33 -> 189.48179 | AC33: =U33*X33*(1+AA33)*Y33*W33*(1+V33) -> 189.48179 | AE33: =AE32 -> 170000 | AF33: =AF32 -> 3211396.3
A34: =VALUE(RIGHT(B34,LEN(B34)-2)) -> 31 | B34: F-31 | D34: FAF-B34-B01-03 | E34: Germany | F34: Axial Inline | G34: Single | H34: Ambient | I34: CAP045120001F | J34: AXC 450-6/21°-2-P (200) (2.2 kW) S IE3 C | K34: 2240 | L34: 375 | M34: =IF(ISERROR(VLOOKUP(J34,'Germany price'!$B$1:$G$99001,6,0))," ",VLOOKUP(J34,'Germany price'!$B$1:$G$99001,6,0)) | N34: 1666 | O34: 0.58 | P34: 2 | Q34: =N34*P34*(1-O34) -> 1399.44 | R34: =R33 -> 0 | S34: =Q34*(1-R34) -> 1399.44 | T34: =(Q34*AE34)/AF34 -> 74.08142 | U34: =T34+S34 -> 1473.5214 | V34: 0 | W34: =1.14 -> 1.14 | X34: =X33 -> 1.1235 | Y34: =Y33 -> 1 | Z34: =U34*X34*Y34*W34*(1+V34) -> 1887.2715 | AA34: =AA33 -> 0.50014493 | AB34: =AC34/P34 -> 1415.5904 | AC34: =U34*X34*(1+AA34)*Y34*W34*(1+V34) -> 2831.1808 | AE34: =AE33 -> 170000 | AF34: =AF33 -> 3211396.3
A35: =VALUE(RIGHT(B35,LEN(B35)-2)) -> 32 | B35: F-32 | D35: FAF-B37-B01-01 | E35: Germany | F35: Axial Inline | G35: Single | H35: Ambient | I35: CAP040120001F | J35: AXC 400-6/27°-2-P (160) (2.2 kW) S IE3 | K35: 2005 | L35: 250 | M35: =IF(ISERROR(VLOOKUP(J35,'Germany price'!$B$1:$G$99001,6,0))," ",VLOOKUP(J35,'Germany price'!$B$1:$G$99001,6,0)) | N35: 1561 | O35: 0.58 | P35: 1 | Q35: =N35*P35*(1-O35) -> 655.62 | R35: =R34 -> 0 | S35: =Q35*(1-R35) -> 655.62 | T35: =(Q35*AE35)/AF35 -> 34.706211 | U35: =T35+S35 -> 690.32621 | V35: 0 | W35: =1.14 -> 1.14 | X35: =X34 -> 1.1235 | Y35: =Y34 -> 1 | Z35: =U35*X35*Y35*W35*(1+V35) -> 884.16291 | AA35: =AA34 -> 0.50014493 | AB35: =AC35/P35 -> 1326.3725 | AC35: =U35*X35*(1+AA35)*Y35*W35*(1+V35) -> 1326.3725 | AE35: =AE34 -> 170000 | AF35: =AF34 -> 3211396.3
A36: =VALUE(RIGHT(B36,LEN(B36)-2)) -> 33 | B36: F-33 | D36: FAF-B37-B01-02 | E36: Germany | F36: Axial Inline | G36: Single | H36: Ambient | I36: CAP040120001E | J36: AXC 400-6/23°-2-P (160) (1.5 kW) S IE3 C | K36: 1780 | L36: 250 | M36: =IF(ISERROR(VLOOKUP(J36,'Germany price'!$B$1:$G$99001,6,0))," ",VLOOKUP(J36,'Germany price'!$B$1:$G$99001,6,0)) | N36: 1499 | O36: 0.58 | P36: 2 | Q36: =N36*P36*(1-O36) -> 1259.16 | R36: =R35 -> 0 | S36: =Q36*(1-R36) -> 1259.16 | T36: =(Q36*AE36)/AF36 -> 66.655491 | U36: =T36+S36 -> 1325.8155 | V36: 0 | W36: =1.14 -> 1.14 | X36: =X35 -> 1.1235 | Y36: =Y35 -> 1 | Z36: =U36*X36*Y36*W36*(1+V36) -> 1698.0912 | AA36: =AA35 -> 0.50014493 | AB36: =AC36/P36 -> 1273.6915 | AC36: =U36*X36*(1+AA36)*Y36*W36*(1+V36) -> 2547.3829 | AE36: =AE35 -> 170000 | AF36: =AF35 -> 3211396.3
A37: =VALUE(RIGHT(B37,LEN(B37)-2)) -> 34 | B37: F-34 | D37: FAF-B37-B01-03 | E37: Germany | F37: Centrifugal Fan | G37: Single | H37: Ambient | I37: 334079 | J37: PRF 355D4 | K37: 1035 | L37: 250 | M37: =IF(ISERROR(VLOOKUP(J37,'Germany price'!$B$1:$G$99001,6,0))," ",VLOOKUP(J37,'Germany price'!$B$1:$G$99001,6,0)) -> 6324 | N37: 6324 | O37: 0.58 | P37: 1 | Q37: =N37*P37*(1-O37) -> 2656.08 | R37: =R36 -> 0 | S37: =Q37*(1-R37) -> 2656.08 | T37: =(Q37*AE37)/AF37 -> 140.60351 | U37: =T37+S37 -> 2796.6835 | V37: 0 | W37: =1.14 -> 1.14 | X37: =X36 -> 1.1235 | Y37: =Y36 -> 1 | Z37: =U37*X37*Y37*W37*(1+V37) -> 3581.9643 | AA37: =AA36 -> 0.50014493 | AB37: =AC37/P37 -> 5373.4656 | AC37: =U37*X37*(1+AA37)*Y37*W37*(1+V37) -> 5373.4656 | AE37: =AE36 -> 170000 | AF37: =AF36 -> 3211396.3
A38: =VALUE(RIGHT(B38,LEN(B38)-2)) -> 35 | B38: F-35 | D38: FAF-C30-B01-01 | E38: Germany | F38: Axial Inline | G38: Single | H38: Ambient | I38: CAP040120001D | J38: AXC 400-6/17°-2-P (160) (1.1 kW) S IE3 C | K38: 1400 | L38: 250 | M38: =IF(ISERROR(VLOOKUP(J38,'Germany price'!$B$1:$G$99001,6,0))," ",VLOOKUP(J38,'Germany price'!$B$1:$G$99001,6,0)) | N38: 1445 | O38: 0.58 | P38: 2 | Q38: =N38*P38*(1-O38) -> 1213.8 | R38: =R37 -> 0 | S38: =Q38*(1-R38) -> 1213.8 | T38: =(Q38*AE38)/AF38 -> 64.254293 | U38: =T38+S38 -> 1278.0543 | V38: 0 | W38: =1.14 -> 1.14 | X38: =X37 -> 1.1235 | Y38: =Y37 -> 1 | Z38: =U38*X38*Y38*W38*(1+V38) -> 1636.9192 | AA38: =AA37 -> 0.50014493 | AB38: =AC38/P38 -> 1227.808 | AC38: =U38*X38*(1+AA38)*Y38*W38*(1+V38) -> 2455.616 | AE38: =AE37 -> 170000 | AF38: =AF37 -> 3211396.3
A39: =VALUE(RIGHT(B39,LEN(B39)-2)) -> 36 | B39: F-36 | D39: FAF-C30-B01-02 | E39: Germany | F39: Axial Inline | G39: Single | H39: Ambient | I39: CAP035120001D | J39: AXC 355-6/25°-2-P (160) (1.1 kW) S IE3 | K39: 1250 | L39: 250 | M39: =IF(ISERROR(VLOOKUP(J39,'Germany price'!$B$1:$G$99001,6,0))," ",VLOOKUP(J39,'Germany price'!$B$1:$G$99001,6,0)) | N39: 1401 | O39: 0.58 | P39: 1 | Q39: =N39*P39*(1-O39) -> 588.42 | R39: =R38 -> 0 | S39: =Q39*(1-R39) -> 588.42 | T39: =(Q39*AE39)/AF39 -> 31.14888 | U39: =T39+S39 -> 619.56888 | V39: 0 | W39: =1.14 -> 1.14 | X39: =X38 -> 1.1235 | Y39: =Y38 -> 1 | Z39: =U39*X39*Y39*W39*(1+V39) -> 793.53763 | AA39: =AA38 -> 0.50014493 | AB39: =AC39/P39 -> 1190.4214 | AC39: =U39*X39*(1+AA39)*Y39*W39*(1+V39) -> 1190.4214 | AE39: =AE38 -> 170000 | AF39: =AF38 -> 3211396.3
A40: =VALUE(RIGHT(B40,LEN(B40)-2)) -> 37 | B40: F-37 | D40: FAF-C34-B01-04 | E40: Germany | F40: Axial Inline | G40: Single | H40: Ambient | I40: CAP080340001H | J40: AXC 800-6/17°-4-P (350) (4 kW) S IE3 A | K40: 4470 | L40: 375 | M40: =IF(ISERROR(VLOOKUP(J40,'Germany price'!$B$1:$G$99001,6,0))," ",VLOOKUP(J40,'Germany price'!$B$1:$G$99001,6,0)) | N40: 2721 | O40: 0.58 | P40: 2 | Q40: =N40*P40*(1-O40) -> 2285.64 | R40: =R39 -> 0 | S40: =Q40*(1-R40) -> 2285.64 | T40: =(Q40*AE40)/AF40 -> 120.99372 | U40: =T40+S40 -> 2406.6337 | V40: 0 | W40: =1.14 -> 1.14 | X40: =X39 -> 1.1235 | Y40: =Y39 -> 1 | Z40: =U40*X40*Y40*W40*(1+V40) -> 3082.3924 | AA40: =AA39 -> 0.50014493 | AB40: =AC40/P40 -> 2312.0177 | AC40: =U40*X40*(1+AA40)*Y40*W40*(1+V40) -> 4624.0354 | AE40: =AE39 -> 170000 | AF40: =AF39 -> 3211396.3
A41: =VALUE(RIGHT(B41,LEN(B41)-2)) -> 38 | B41: F-38 | D41: FAF-C35-B02-02 | E41: Germany | F41: Axial Inline | G41: Single | H41: Ambient | I41: CAP040120001E | J41: AXC 400-6/23°-2-P (160) (1.5 kW) S IE3 | K41: 2240 | L41: 250 | M41: =IF(ISERROR(VLOOKUP(J41,'Germany price'!$B$1:$G$99001,6,0))," ",VLOOKUP(J41,'Germany price'!$B$1:$G$99001,6,0)) | N41: 1499 | O41: 0.58 | P41: 2 | Q41: =N41*P41*(1-O41) -> 1259.16 | R41: =R40 -> 0 | S41: =Q41*(1-R41) -> 1259.16 | T41: =(Q41*AE41)/AF41 -> 66.655491 | U41: =T41+S41 -> 1325.8155 | V41: 0 | W41: =1.14 -> 1.14 | X41: =X40 -> 1.1235 | Y41: =Y40 -> 1 | Z41: =U41*X41*Y41*W41*(1+V41) -> 1698.0912 | AA41: =AA40 -> 0.50014493 | AB41: =AC41/P41 -> 1273.6915 | AC41: =U41*X41*(1+AA41)*Y41*W41*(1+V41) -> 2547.3829 | AE41: =AE40 -> 170000 | AF41: =AF40 -> 3211396.3
A42: =VALUE(RIGHT(B42,LEN(B42)-2)) -> 39 | B42: F-39 | D42: FAF-C37-B01-03 | E42: Germany | F42: Axial Inline | G42: Single | H42: Ambient | I42: CAP050120001H | J42: AXC 500-6/26°-2-P (200) (4 kW) S IE3 C | K42: 3560 | L42: 375 | M42: =IF(ISERROR(VLOOKUP(J42,'Germany price'!$B$1:$G$99001,6,0))," ",VLOOKUP(J42,'Germany price'!$B$1:$G$99001,6,0)) | N42: 2148 | O42: 0.58 | P42: 2 | Q42: =N42*P42*(1-O42) -> 1804.32 | R42: =R41 -> 0 | S42: =Q42*(1-R42) -> 1804.32 | T42: =(Q42*AE42)/AF42 -> 95.514339 | U42: =T42+S42 -> 1899.8343 | V42: 0 | W42: =1.14 -> 1.14 | X42: =X41 -> 1.1235 | Y42: =Y41 -> 1 | Z42: =U42*X42*Y42*W42*(1+V42) -> 2433.2888 | AA42: =AA41 -> 0.50014493 | AB42: =AC42/P42 -> 1825.1429 | AC42: =U42*X42*(1+AA42)*Y42*W42*(1+V42) -> 3650.2859 | AE42: =AE41 -> 170000 | AF42: =AF41 -> 3211396.3
A43: =VALUE(RIGHT(B43,LEN(B43)-2)) -> 40 | B43: F-40 | D43: EXF-A29-B02-01 | E43: Sweden | F43: Inline Fan | G43: Single | H43: Ambient | I43: 25362 | J43: K 150 M Sileo | K43: 85 | L43: 125 | M43: =IF(ISERROR(VLOOKUP(J43,'Germany price'!$B$1:$G$99001,6,0))," ",VLOOKUP(J43,'Germany price'!$B$1:$G$99001,6,0)) -> 145 | N43: 145 | O43: 0.58 | P43: 2 | Q43: =N43*P43*(1-O43) -> 121.8 | R43: =R42 -> 0 | S43: =Q43*(1-R43) -> 121.8 | T43: =(Q43*AE43)/AF43 -> 6.4476626 | U43: =T43+S43 -> 128.24766 | V43: 0 | W43: =1.14 -> 1.14 | X43: =X42 -> 1.1235 | Y43: =Y42 -> 1 | Z43: =U43*X43*Y43*W43*(1+V43) -> 164.25832 | AA43: =AA42 -> 0.50014493 | AB43: =AC43/P43 -> 123.20565 | AC43: =U43*X43*(1+AA43)*Y43*W43*(1+V43) -> 246.41129 | AE43: =AE42 -> 170000 | AF43: =AF42 -> 3211396.3
A44: =VALUE(RIGHT(B44,LEN(B44)-2)) -> 41 | B44: F-41 | D44: EXF-A29-B02-02 | E44: Germany | F44: Wall Mounted | G44: Single | H44: Ambient | I44: 37415 | J44: AW 630DV sileo Axial fan | K44: 3390 | L44: - | M44: =IF(ISERROR(VLOOKUP(J44,'Germany price'!$B$1:$G$99001,6,0))," ",VLOOKUP(J44,'Germany price'!$B$1:$G$99001,6,0)) -> 1352 | N44: 633.36 | O44: 0 | P44: 2 | Q44: =N44*P44*(1-O44) -> 1266.72 | R44: =R43 -> 0 | S44: =Q44*(1-R44) -> 1266.72 | T44: =(Q44*AE44)/AF44 -> 67.055691 | U44: =T44+S44 -> 1333.7757 | V44: 0 | W44: =1.14 -> 1.14 | X44: =X43 -> 1.1235 | Y44: =Y43 -> 1 | Z44: =U44*X44*Y44*W44*(1+V44) -> 1708.2866 | AA44: =AA43 -> 0.50014493 | AB44: =AC44/P44 -> 1281.3387 | AC44: =U44*X44*(1+AA44)*Y44*W44*(1+V44) -> 2562.6774 | AE44: =AE43 -> 170000 | AF44: =AF43 -> 3211396.3
A45: =VALUE(RIGHT(B45,LEN(B45)-2)) -> 42 | B45: F-42 | D45: EXF-A29-B02-03 | E45: Germany | F45: Centrifugal Inline | G45: Single | H45: Ambient | I45: 235401 | J45: MUB 025 355EV Multibox | K45: 525 | L45: 125 | M45: =IF(ISERROR(VLOOKUP(J45,'Germany price'!$B$1:$G$99001,6,0))," ",VLOOKUP(J45,'Germany price'!$B$1:$G$99001,6,0)) -> 999 | N45: 999 | O45: 0.58 | P45: 1 | Q45: =N45*P45*(1-O45) -> 419.58 | R45: =R44 -> 0 | S45: =Q45*(1-R45) -> 419.58 | T45: =(Q45*AE45)/AF45 -> 22.211086 | U45: =T45+S45 -> 441.79109 | V45: 0 | W45: =1.14 -> 1.14 | X45: =X44 -> 1.1235 | Y45: =Y44 -> 1 | Z45: =U45*X45*Y45*W45*(1+V45) -> 565.8416 | AA45: =AA44 -> 0.50014493 | AB45: =AC45/P45 -> 848.84442 | AC45: =U45*X45*(1+AA45)*Y45*W45*(1+V45) -> 848.84442 | AE45: =AE44 -> 170000 | AF45: =AF44 -> 3211396.3
A46: =VALUE(RIGHT(B46,LEN(B46)-2)) -> 43 | B46: F-43 | D46: EXF-A30-B02-01 | E46: Sweden | F46: Inline Fan | G46: Single | H46: Ambient | I46: 93267 | J46: prio 315 | K46: 775 | L46: 125 | M46: =IF(ISERROR(VLOOKUP(J46,'Germany price'!$B$1:$G$99001,6,0))," ",VLOOKUP(J46,'Germany price'!$B$1:$G$99001,6,0)) -> 801 | N46: 801 | O46: 0.58 | P46: 1 | Q46: =N46*P46*(1-O46) -> 336.42 | R46: =R45 -> 0 | S46: =Q46*(1-R46) -> 336.42 | T46: =(Q46*AE46)/AF46 -> 17.808889 | U46: =T46+S46 -> 354.22889 | V46: 0 | W46: =1.14 -> 1.14 | X46: =X45 -> 1.1235 | Y46: =Y45 -> 1 | Z46: =U46*X46*Y46*W46*(1+V46) -> 453.69282 | AA46: =AA45 -> 0.50014493 | AB46: =AC46/P46 -> 680.60498 | AC46: =U46*X46*(1+AA46)*Y46*W46*(1+V46) -> 680.60498 | AE46: =AE45 -> 170000 | AF46: =AF45 -> 3211396.3
A47: =VALUE(RIGHT(B47,LEN(B47)-2)) -> 44 | B47: F-44 | D47: EXF-A30-B02-03 | E47: Sweden | F47: Inline Fan | G47: Single | H47: Ambient | I47: 19510 | J47: K 200 L sileo | K47: 195 | L47: 125 | M47: =IF(ISERROR(VLOOKUP(J47,'Germany price'!$B$1:$G$99001,6,0))," ",VLOOKUP(J47,'Germany price'!$B$1:$G$99001,6,0)) -> 208 | N47: 208 | O47: 0.58 | P47: 1 | Q47: =N47*P47*(1-O47) -> 87.36 | R47: =R46 -> 0 | S47: =Q47*(1-R47) -> 87.36 | T47: =(Q47*AE47)/AF47 -> 4.6245304 | U47: =T47+S47 -> 91.98453 | V47: 0 | W47: =1.14 -> 1.14 | X47: =X46 -> 1.1235 | Y47: =Y46 -> 1 | Z47: =U47*X47*Y47*W47*(1+V47) -> 117.81287 | AA47: =AA46 -> 0.50014493 | AB47: =AC47/P47 -> 176.73638 | AC47: =U47*X47*(1+AA47)*Y47*W47*(1+V47) -> 176.73638 | AE47: =AE46 -> 170000 | AF47: =AF46 -> 3211396.3
A48: =VALUE(RIGHT(B48,LEN(B48)-2)) -> 45 | B48: F-45 | D48: EXF-A35-B02-01 | E48: Germany | F48: Wall Mounted | G48: Single | H48: Ambient | I48: 37412 | J48: AW 500E4 sileo Axial fan | K48: 2130 | L48: - | M48: =IF(ISERROR(VLOOKUP(J48,'Germany price'!$B$1:$G$99001,6,0))," ",VLOOKUP(J48,'Germany price'!$B$1:$G$99001,6,0)) -> 632 | N48: 327.18 | O48: 0 | P48: 2 | Q48: =N48*P48*(1-O48) -> 654.36 | R48: =R47 -> 0 | S48: =Q48*(1-R48) -> 654.36 | T48: =(Q48*AE48)/AF48 -> 34.639511 | U48: =T48+S48 -> 688.99951 | V48: 0 | W48: =1.14 -> 1.14 | X48: =X47 -> 1.1235 | Y48: =Y47 -> 1 | Z48: =U48*X48*Y48*W48*(1+V48) -> 882.46368 | AA48: =AA47 -> 0.50014493 | AB48: =AC48/P48 -> 661.91171 | AC48: =U48*X48*(1+AA48)*Y48*W48*(1+V48) -> 1323.8234 | AE48: =AE47 -> 170000 | AF48: =AF47 -> 3211396.3
A49: =VALUE(RIGHT(B49,LEN(B49)-2)) -> 46 | B49: F-46 | D49: EXF-A35-B02-02 | E49: Germany | F49: Centrifugal Fan | G49: Single | H49: Ambient | I49: 334079 | J49: PRF 355D4 | K49: 1125 | L49: 250 | M49: =IF(ISERROR(VLOOKUP(J49,'Germany price'!$B$1:$G$99001,6,0))," ",VLOOKUP(J49,'Germany price'!$B$1:$G$99001,6,0)) -> 6324 | N49: 6324 | O49: 0.58 | P49: 1 | Q49: =N49*P49*(1-O49) -> 2656.08 | R49: =R48 -> 0 | S49: =Q49*(1-R49) -> 2656.08 | T49: =(Q49*AE49)/AF49 -> 140.60351 | U49: =T49+S49 -> 2796.6835 | V49: 0 | W49: =1.14 -> 1.14 | X49: =X48 -> 1.1235 | Y49: =Y48 -> 1 | Z49: =U49*X49*Y49*W49*(1+V49) -> 3581.9643 | AA49: =AA48 -> 0.50014493 | AB49: =AC49/P49 -> 5373.4656 | AC49: =U49*X49*(1+AA49)*Y49*W49*(1+V49) -> 5373.4656 | AE49: =AE48 -> 170000 | AF49: =AF48 -> 3211396.3
A50: =VALUE(RIGHT(B50,LEN(B50)-2)) -> 47 | B50: F-47 | D50: EXF-A35-B02-03 | E50: Sweden | F50: Inline Fan | G50: Single | H50: Ambient | I50: 25360 | J50: K 100 XL sileo | K50: 45 | L50: 125 | M50: =IF(ISERROR(VLOOKUP(J50,'Germany price'!$B$1:$G$99001,6,0))," ",VLOOKUP(J50,'Germany price'!$B$1:$G$99001,6,0)) -> 140 | N50: 140 | O50: 0.58 | P50: 2 | Q50: =N50*P50*(1-O50) -> 117.6 | R50: =R49 -> 0 | S50: =Q50*(1-R50) -> 117.6 | T50: =(Q50*AE50)/AF50 -> 6.2253294 | U50: =T50+S50 -> 123.82533 | V50: 0 | W50: =1.14 -> 1.14 | X50: =X49 -> 1.1235 | Y50: =Y49 -> 1 | Z50: =U50*X50*Y50*W50*(1+V50) -> 158.59424 | AA50: =AA49 -> 0.50014493 | AB50: =AC50/P50 -> 118.95718 | AC50: =U50*X50*(1+AA50)*Y50*W50*(1+V50) -> 237.91435 | AE50: =AE49 -> 170000 | AF50: =AF49 -> 3211396.3
A51: =VALUE(RIGHT(B51,LEN(B51)-2)) -> 48 | B51: F-48 | D51: EXF-B30-B02-01 | E51: Sweden | F51: Inline Fan | G51: Single | H51: Ambient | I51: 25362 | J51: K 150 M Sileo | K51: 65 | L51: 125 | M51: =IF(ISERROR(VLOOKUP(J51,'Germany price'!$B$1:$G$99001,6,0))," ",VLOOKUP(J51,'Germany price'!$B$1:$G$99001,6,0)) -> 145 | N51: 145 | O51: 0.58 | P51: 2 | Q51: =N51*P51*(1-O51) -> 121.8 | R51: =R50 -> 0 | S51: =Q51*(1-R51) -> 121.8 | T51: =(Q51*AE51)/AF51 -> 6.4476626 | U51: =T51+S51 -> 128.24766 | V51: 0 | W51: =1.14 -> 1.14 | X51: =X50 -> 1.1235 | Y51: =Y50 -> 1 | Z51: =U51*X51*Y51*W51*(1+V51) -> 164.25832 | AA51: =AA50 -> 0.50014493 | AB51: =AC51/P51 -> 123.20565 | AC51: =U51*X51*(1+AA51)*Y51*W51*(1+V51) -> 246.41129 | AE51: =AE50 -> 170000 | AF51: =AF50 -> 3211396.3
A52: =VALUE(RIGHT(B52,LEN(B52)-2)) -> 49 | B52: F-49 | D52: EXF-B30-B02-02 | E52: Sweden | F52: Inline Fan | G52: Single | H52: Ambient | I52: 27758 | J52: K 315 M sileo** | K52: 305 | L52: 125 | M52: =IF(ISERROR(VLOOKUP(J52,'Germany price'!$B$1:$G$99001,6,0))," ",VLOOKUP(J52,'Germany price'!$B$1:$G$99001,6,0)) -> 276 | N52: 276 | O52: 0.58 | P52: 1 | Q52: =N52*P52*(1-O52) -> 115.92 | R52: =R51 -> 0 | S52: =Q52*(1-R52) -> 115.92 | T52: =(Q52*AE52)/AF52 -> 6.1363961 | U52: =T52+S52 -> 122.0564 | V52: 0 | W52: =1.14 -> 1.14 | X52: =X51 -> 1.1235 | Y52: =Y51 -> 1 | Z52: =U52*X52*Y52*W52*(1+V52) -> 156.32861 | AA52: =AA51 -> 0.50014493 | AB52: =AC52/P52 -> 234.51557 | AC52: =U52*X52*(1+AA52)*Y52*W52*(1+V52) -> 234.51557 | AE52: =AE51 -> 170000 | AF52: =AF51 -> 3211396.3
A53: =VALUE(RIGHT(B53,LEN(B53)-2)) -> 50 | B53: F-50 | D53: EXF-B35-B02-01 | E53: Sweden | F53: Inline Fan | G53: Single | H53: Ambient | I53: 27758 | J53: K 315 M sileo** | K53: 285 | L53: 125 | M53: =IF(ISERROR(VLOOKUP(J53,'Germany price'!$B$1:$G$99001,6,0))," ",VLOOKUP(J53,'Germany price'!$B$1:$G$99001,6,0)) -> 276 | N53: 276 | O53: 0.58 | P53: 1 | Q53: =N53*P53*(1-O53) -> 115.92 | R53: =R52 -> 0 | S53: =Q53*(1-R53) -> 115.92 | T53: =(Q53*AE53)/AF53 -> 6.1363961 | U53: =T53+S53 -> 122.0564 | V53: 0 | W53: =1.14 -> 1.14 | X53: =X52 -> 1.1235 | Y53: =Y52 -> 1 | Z53: =U53*X53*Y53*W53*(1+V53) -> 156.32861 | AA53: =AA52 -> 0.50014493 | AB53: =AC53/P53 -> 234.51557 | AC53: =U53*X53*(1+AA53)*Y53*W53*(1+V53) -> 234.51557 | AE53: =AE52 -> 170000 | AF53: =AF52 -> 3211396.3
A54: =VALUE(RIGHT(B54,LEN(B54)-2)) -> 51 | B54: F-51 | D54: EXF-B35-B02-03 | E54: Sweden | F54: Inline Fan | G54: Single | H54: Ambient | I54: 93097 | J54: KT 60-30-4 | K54: 760 | L54: 250 | M54: =IF(ISERROR(VLOOKUP(J54,'Germany price'!$B$1:$G$99001,6,0))," ",VLOOKUP(J54,'Germany price'!$B$1:$G$99001,6,0)) -> 1182 | N54: 1182 | O54: 0.58 | P54: 1 | Q54: =N54*P54*(1-O54) -> 496.44 | R54: =R53 -> 0 | S54: =Q54*(1-R54) -> 496.44 | T54: =(Q54*AE54)/AF54 -> 26.279783 | U54: =T54+S54 -> 522.71978 | V54: 0 | W54: =1.14 -> 1.14 | X54: =X53 -> 1.1235 | Y54: =Y53 -> 1 | Z54: =U54*X54*Y54*W54*(1+V54) -> 669.49427 | AA54: =AA53 -> 0.50014493 | AB54: =AC54/P54 -> 1004.3384 | AC54: =U54*X54*(1+AA54)*Y54*W54*(1+V54) -> 1004.3384 | AE54: =AE53 -> 170000 | AF54: =AF53 -> 3211396.3
A55: =VALUE(RIGHT(B55,LEN(B55)-2)) -> 52 | B55: F-52 | D55: EXF-B35-B02-04 | E55: Germany | F55: Axial Inline | G55: Single | H55: Ambient | I55: CAP040120001D | J55: AXC 400-6/18°-2-P (160) (1.1 kW) S IE3 | K55: 1420 | L55: 250 | M55: =IF(ISERROR(VLOOKUP(J55,'Germany price'!$B$1:$G$99001,6,0))," ",VLOOKUP(J55,'Germany price'!$B$1:$G$99001,6,0)) | N55: 1445 | O55: 0.58 | P55: 1 | Q55: =N55*P55*(1-O55) -> 606.9 | R55: =R54 -> 0 | S55: =Q55*(1-R55) -> 606.9 | T55: =(Q55*AE55)/AF55 -> 32.127146 | U55: =T55+S55 -> 639.02715 | V55: 0 | W55: =1.14 -> 1.14 | X55: =X54 -> 1.1235 | Y55: =Y54 -> 1 | Z55: =U55*X55*Y55*W55*(1+V55) -> 818.45958 | AA55: =AA54 -> 0.50014493 | AB55: =AC55/P55 -> 1227.808 | AC55: =U55*X55*(1+AA55)*Y55*W55*(1+V55) -> 1227.808 | AE55: =AE54 -> 170000 | AF55: =AF54 -> 3211396.3
A56: =VALUE(RIGHT(B56,LEN(B56)-2)) -> 53 | B56: F-53 | D56: EXF-B35-B02-05 | E56: Germany | F56: Centrifugal Inline | G56: Single | H56: Ambient | I56: 235403 | J56: MUB 042 400EV Multibox | K56: 645 | L56: 250 | M56: =IF(ISERROR(VLOOKUP(J56,'Germany price'!$B$1:$G$99001,6,0))," ",VLOOKUP(J56,'Germany price'!$B$1:$G$99001,6,0)) -> 1199 | N56: 1199 | O56: 0.58 | P56: 1 | Q56: =N56*P56*(1-O56) -> 503.58 | R56: =R55 -> 0 | S56: =Q56*(1-R56) -> 503.58 | T56: =(Q56*AE56)/AF56 -> 26.65775 | U56: =T56+S56 -> 530.23775 | V56: 0 | W56: =1.14 -> 1.14 | X56: =X55 -> 1.1235 | Y56: =Y55 -> 1 | Z56: =U56*X56*Y56*W56*(1+V56) -> 679.12321 | AA56: =AA55 -> 0.50014493 | AB56: =AC56/P56 -> 1018.7832 | AC56: =U56*X56*(1+AA56)*Y56*W56*(1+V56) -> 1018.7832 | AE56: =AE55 -> 170000 | AF56: =AF55 -> 3211396.3
A57: =VALUE(RIGHT(B57,LEN(B57)-2)) -> 54 | B57: F-54 | D57: EXF-B35-B02-07 | E57: Sweden | F57: Inline Fan | G57: Single | H57: Ambient | I57: 19512 | J57: K 250 L sileo | K57: 190 | L57: 250 | M57: =IF(ISERROR(VLOOKUP(J57,'Germany price'!$B$1:$G$99001,6,0))," ",VLOOKUP(J57,'Germany price'!$B$1:$G$99001,6,0)) -> 223 | N57: 223 | O57: 0.58 | P57: 1 | Q57: =N57*P57*(1-O57) -> 93.66 | R57: =R56 -> 0 | S57: =Q57*(1-R57) -> 93.66 | T57: =(Q57*AE57)/AF57 -> 4.9580302 | U57: =T57+S57 -> 98.61803 | V57: 0 | W57: =1.14 -> 1.14 | X57: =X56 -> 1.1235 | Y57: =Y56 -> 1 | Z57: =U57*X57*Y57*W57*(1+V57) -> 126.30899 | AA57: =AA56 -> 0.50014493 | AB57: =AC57/P57 -> 189.48179 | AC57: =U57*X57*(1+AA57)*Y57*W57*(1+V57) -> 189.48179 | AE57: =AE56 -> 170000 | AF57: =AF56 -> 3211396.3
A58: =VALUE(RIGHT(B58,LEN(B58)-2)) -> 55 | B58: F-55 | D58: EXF-C29-B02-01 | E58: Sweden | F58: Inline Fan | G58: Single | H58: Ambient | I58: 93098 | J58: KT 60-35-4 | K58: 1040 | L58: 250 | M58: =IF(ISERROR(VLOOKUP(J58,'Germany price'!$B$1:$G$99001,6,0))," ",VLOOKUP(J58,'Germany price'!$B$1:$G$99001,6,0)) -> 1443 | N58: 1443 | O58: 0.58 | P58: 1 | Q58: =N58*P58*(1-O58) -> 606.06 | R58: =R57 -> 0 | S58: =Q58*(1-R58) -> 606.06 | T58: =(Q58*AE58)/AF58 -> 32.08268 | U58: =T58+S58 -> 638.14268 | V58: 0 | W58: =1.14 -> 1.14 | X58: =X57 -> 1.1235 | Y58: =Y57 -> 1 | Z58: =U58*X58*Y58*W58*(1+V58) -> 817.32676 | AA58: =AA57 -> 0.50014493 | AB58: =AC58/P58 -> 1226.1086 | AC58: =U58*X58*(1+AA58)*Y58*W58*(1+V58) -> 1226.1086 | AE58: =AE57 -> 170000 | AF58: =AF57 -> 3211396.3
A59: =VALUE(RIGHT(B59,LEN(B59)-2)) -> 56 | B59: F-56 | D59: EXF-C29-B02-02 | E59: Germany | F59: Wall Mounted | G59: Single | H59: Ambient | I59: 34140 | J59: AW 710DV sileo Axial fan | K59: 4230 | L59: - | M59: =IF(ISERROR(VLOOKUP(J59,'Germany price'!$B$1:$G$99001,6,0))," ",VLOOKUP(J59,'Germany price'!$B$1:$G$99001,6,0)) -> 2005 | N59: 928.2 | O59: 0 | P59: 2 | Q59: =N59*P59*(1-O59) -> 1856.4 | R59: =R58 -> 0 | S59: =Q59*(1-R59) -> 1856.4 | T59: =(Q59*AE59)/AF59 -> 98.271271 | U59: =T59+S59 -> 1954.6713 | V59: 0 | W59: =1.14 -> 1.14 | X59: =X58 -> 1.1235 | Y59: =Y58 -> 1 | Z59: =U59*X59*Y59*W59*(1+V59) -> 2503.5234 | AA59: =AA58 -> 0.50014493 | AB59: =AC59/P59 -> 1877.824 | AC59: =U59*X59*(1+AA59)*Y59*W59*(1+V59) -> 3755.648 | AE59: =AE58 -> 170000 | AF59: =AF58 -> 3211396.3
A60: =VALUE(RIGHT(B60,LEN(B60)-2)) -> 57 | B60: F-57 | D60: EXF-C29-B02-03 | E60: Germany | F60: Centrifugal Inline | G60: Single | H60: Ambient | I60: 235400 | J60: MUB 025 355DV Multibox | K60: 655 | L60: 125 | M60: =IF(ISERROR(VLOOKUP(J60,'Germany price'!$B$1:$G$99001,6,0))," ",VLOOKUP(J60,'Germany price'!$B$1:$G$99001,6,0)) -> 1050 | N60: 1050 | O60: 0.58 | P60: 1 | Q60: =N60*P60*(1-O60) -> 441 | R60: =R59 -> 0 | S60: =Q60*(1-R60) -> 441 | T60: =(Q60*AE60)/AF60 -> 23.344985 | U60: =T60+S60 -> 464.34499 | V60: 0 | W60: =1.14 -> 1.14 | X60: =X59 -> 1.1235 | Y60: =Y59 -> 1 | Z60: =U60*X60*Y60*W60*(1+V60) -> 594.72841 | AA60: =AA59 -> 0.50014493 | AB60: =AC60/P60 -> 892.17882 | AC60: =U60*X60*(1+AA60)*Y60*W60*(1+V60) -> 892.17882 | AE60: =AE59 -> 170000 | AF60: =AF59 -> 3211396.3
A61: =VALUE(RIGHT(B61,LEN(B61)-2)) -> 58 | B61: F-58 | D61: EXF-C29-B02-04 | E61: Germany | F61: Centrifugal Fan | G61: Single | H61: Ambient | I61: 334079 | J61: PRF 355D4 | K61: 785 | L61: 125 | M61: =IF(ISERROR(VLOOKUP(J61,'Germany price'!$B$1:$G$99001,6,0))," ",VLOOKUP(J61,'Germany price'!$B$1:$G$99001,6,0)) -> 6324 | N61: 6324 | O61: 0.58 | P61: 1 | Q61: =N61*P61*(1-O61) -> 2656.08 | R61: =R60 -> 0 | S61: =Q61*(1-R61) -> 2656.08 | T61: =(Q61*AE61)/AF61 -> 140.60351 | U61: =T61+S61 -> 2796.6835 | V61: 0 | W61: =1.14 -> 1.14 | X61: =X60 -> 1.1235 | Y61: =Y60 -> 1 | Z61: =U61*X61*Y61*W61*(1+V61) -> 3581.9643 | AA61: =AA60 -> 0.50014493 | AB61: =AC61/P61 -> 5373.4656 | AC61: =U61*X61*(1+AA61)*Y61*W61*(1+V61) -> 5373.4656 | AE61: =AE60 -> 170000 | AF61: =AF60 -> 3211396.3
A62: =VALUE(RIGHT(B62,LEN(B62)-2)) -> 59 | B62: F-59 | D62: EXF-C35-B02-01 | E62: Germany | F62: Wall Mounted | G62: Single | H62: Ambient | I62: 37412 | J62: AW 500E4 sileo Axial fan | K62: 2130 | L62: - | M62: =IF(ISERROR(VLOOKUP(J62,'Germany price'!$B$1:$G$99001,6,0))," ",VLOOKUP(J62,'Germany price'!$B$1:$G$99001,6,0)) -> 632 | N62: 327.18 | O62: 0 | P62: 2 | Q62: =N62*P62*(1-O62) -> 654.36 | R62: =R61 -> 0 | S62: =Q62*(1-R62) -> 654.36 | T62: =(Q62*AE62)/AF62 -> 34.639511 | U62: =T62+S62 -> 688.99951 | V62: 0 | W62: =1.14 -> 1.14 | X62: =X61 -> 1.1235 | Y62: =Y61 -> 1 | Z62: =U62*X62*Y62*W62*(1+V62) -> 882.46368 | AA62: =AA61 -> 0.50014493 | AB62: =AC62/P62 -> 661.91171 | AC62: =U62*X62*(1+AA62)*Y62*W62*(1+V62) -> 1323.8234 | AE62: =AE61 -> 170000 | AF62: =AF61 -> 3211396.3
A63: =VALUE(RIGHT(B63,LEN(B63)-2)) -> 60 | B63: F-60 | D63: EXF-C35-B02-02 | E63: Sweden | F63: Inline Fan | G63: Single | H63: Ambient | I63: 19510 | J63: K 200 L sileo | K63: 225 | L63: 125 | M63: =IF(ISERROR(VLOOKUP(J63,'Germany price'!$B$1:$G$99001,6,0))," ",VLOOKUP(J63,'Germany price'!$B$1:$G$99001,6,0)) -> 208 | N63: 208 | O63: 0.58 | P63: 1 | Q63: =N63*P63*(1-O63) -> 87.36 | R63: =R62 -> 0 | S63: =Q63*(1-R63) -> 87.36 | T63: =(Q63*AE63)/AF63 -> 4.6245304 | U63: =T63+S63 -> 91.98453 | V63: 0 | W63: =1.14 -> 1.14 | X63: =X62 -> 1.1235 | Y63: =Y62 -> 1 | Z63: =U63*X63*Y63*W63*(1+V63) -> 117.81287 | AA63: =AA62 -> 0.50014493 | AB63: =AC63/P63 -> 176.73638 | AC63: =U63*X63*(1+AA63)*Y63*W63*(1+V63) -> 176.73638 | AE63: =AE62 -> 170000 | AF63: =AF62 -> 3211396.3
A64: =VALUE(RIGHT(B64,LEN(B64)-2)) -> 61 | B64: F-61 | D64: EXF-C35-B02-03 | E64: Germany | F64: Axial Inline | G64: Single | H64: Ambient | I64: CAP035120001D | J64: AXC 355-6/23°-2-P (160) (1.1 kW) S IE3 | K64: 1185 | L64: 250 | M64: =IF(ISERROR(VLOOKUP(J64,'Germany price'!$B$1:$G$99001,6,0))," ",VLOOKUP(J64,'Germany price'!$B$1:$G$99001,6,0)) | N64: 1401 | O64: 0.58 | P64: 1 | Q64: =N64*P64*(1-O64) -> 588.42 | R64: =R63 -> 0 | S64: =Q64*(1-R64) -> 588.42 | T64: =(Q64*AE64)/AF64 -> 31.14888 | U64: =T64+S64 -> 619.56888 | V64: 0 | W64: =1.14 -> 1.14 | X64: =X63 -> 1.1235 | Y64: =Y63 -> 1 | Z64: =U64*X64*Y64*W64*(1+V64) -> 793.53763 | AA64: =AA63 -> 0.50014493 | AB64: =AC64/P64 -> 1190.4214 | AC64: =U64*X64*(1+AA64)*Y64*W64*(1+V64) -> 1190.4214 | AE64: =AE63 -> 170000 | AF64: =AF63 -> 3211396.3
A65: =VALUE(RIGHT(B65,LEN(B65)-2)) -> 62 | B65: F-62 | D65: EXF-A34-B02-01 | E65: Sweden | F65: Inline Fan | G65: Single | H65: Ambient | I65: 93267 | J65: prio 315 | K65: 675 | L65: 125 | M65: =IF(ISERROR(VLOOKUP(J65,'Germany price'!$B$1:$G$99001,6,0))," ",VLOOKUP(J65,'Germany price'!$B$1:$G$99001,6,0)) -> 801 | N65: 801 | O65: 0.58 | P65: 1 | Q65: =N65*P65*(1-O65) -> 336.42 | R65: =R64 -> 0 | S65: =Q65*(1-R65) -> 336.42 | T65: =(Q65*AE65)/AF65 -> 17.808889 | U65: =T65+S65 -> 354.22889 | V65: 0 | W65: =1.14 -> 1.14 | X65: =X64 -> 1.1235 | Y65: =Y64 -> 1 | Z65: =U65*X65*Y65*W65*(1+V65) -> 453.69282 | AA65: =AA64 -> 0.50014493 | AB65: =AC65/P65 -> 680.60498 | AC65: =U65*X65*(1+AA65)*Y65*W65*(1+V65) -> 680.60498 | AE65: =AE64 -> 170000 | AF65: =AF64 -> 3211396.3
A66: =VALUE(RIGHT(B66,LEN(B66)-2)) -> 63 | B66: F-63 | D66: EXF-B35-B02-02 | E66: Germany | F66: Wall Mounted | G66: Single | H66: Ambient | I66: 34140 | J66: AW 710DV sileo Axial fan | K66: 5510 | L66: - | M66: =IF(ISERROR(VLOOKUP(J66,'Germany price'!$B$1:$G$99001,6,0))," ",VLOOKUP(J66,'Germany price'!$B$1:$G$99001,6,0)) -> 2005 | N66: 928.2 | O66: 0 | P66: 2 | Q66: =N66*P66*(1-O66) -> 1856.4 | R66: =R65 -> 0 | S66: =Q66*(1-R66) -> 1856.4 | T66: =(Q66*AE66)/AF66 -> 98.271271 | U66: =T66+S66 -> 1954.6713 | V66: 0 | W66: =1.14 -> 1.14 | X66: =X65 -> 1.1235 | Y66: =Y65 -> 1 | Z66: =U66*X66*Y66*W66*(1+V66) -> 2503.5234 | AA66: =AA65 -> 0.50014493 | AB66: =AC66/P66 -> 1877.824 | AC66: =U66*X66*(1+AA66)*Y66*W66*(1+V66) -> 3755.648 | AE66: =AE65 -> 170000 | AF66: =AF65 -> 3211396.3
A67: =VALUE(RIGHT(B67,LEN(B67)-2)) -> 64 | B67: F-64 | D67: EXF-A30-B01-01 | E67: Germany | F67: Centrifugal Inline | G67: Single | H67: Ambient | I67: 276520 | J67: MUB 042 450DV Multibox | K67: 930 | L67: 250 | M67: =IF(ISERROR(VLOOKUP(J67,'Germany price'!$B$1:$G$99001,6,0))," ",VLOOKUP(J67,'Germany price'!$B$1:$G$99001,6,0)) -> 1339 | N67: 1339 | O67: 0.58 | P67: 1 | Q67: =N67*P67*(1-O67) -> 562.38 | R67: =R66 -> 0 | S67: =Q67*(1-R67) -> 562.38 | T67: =(Q67*AE67)/AF67 -> 29.770414 | U67: =T67+S67 -> 592.15041 | V67: 0 | W67: =1.14 -> 1.14 | X67: =X66 -> 1.1235 | Y67: =Y66 -> 1 | Z67: =U67*X67*Y67*W67*(1+V67) -> 758.42033 | AA67: =AA66 -> 0.50014493 | AB67: =AC67/P67 -> 1137.7404 | AC67: =U67*X67*(1+AA67)*Y67*W67*(1+V67) -> 1137.7404 | AE67: =AE66 -> 170000 | AF67: =AF66 -> 3211396.3
A68: =VALUE(RIGHT(B68,LEN(B68)-2)) -> 65 | B68: F-65 | D68: EXF-A30-B01-02 | E68: Germany | F68: Wall Mounted | G68: Single | H68: Ambient | I68: 37412 | J68: AW 500E4 sileo Axial fan | K68: 2120 | L68: - | M68: =IF(ISERROR(VLOOKUP(J68,'Germany price'!$B$1:$G$99001,6,0))," ",VLOOKUP(J68,'Germany price'!$B$1:$G$99001,6,0)) -> 632 | N68: 327.18 | O68: 0 | P68: 2 | Q68: =N68*P68*(1-O68) -> 654.36 | R68: =R67 -> 0 | S68: =Q68*(1-R68) -> 654.36 | T68: =(Q68*AE68)/AF68 -> 34.639511 | U68: =T68+S68 -> 688.99951 | V68: 0 | W68: =1.14 -> 1.14 | X68: =X67 -> 1.1235 | Y68: =Y67 -> 1 | Z68: =U68*X68*Y68*W68*(1+V68) -> 882.46368 | AA68: =AA67 -> 0.50014493 | AB68: =AC68/P68 -> 661.91171 | AC68: =U68*X68*(1+AA68)*Y68*W68*(1+V68) -> 1323.8234 | AE68: =AE67 -> 170000 | AF68: =AF67 -> 3211396.3
A69: =VALUE(RIGHT(B69,LEN(B69)-2)) -> 66 | B69: F-66 | D69: EXF-A30-B01-03 | E69: Sweden | F69: Inline Fan | G69: Single | H69: Ambient | I69: 93294 | J69: KT 50-30-4** | K69: 565 | L69: 125 | M69: =IF(ISERROR(VLOOKUP(J69,'Germany price'!$B$1:$G$99001,6,0))," ",VLOOKUP(J69,'Germany price'!$B$1:$G$99001,6,0)) -> 859 | N69: 859 | O69: 0.58 | P69: 1 | Q69: =N69*P69*(1-O69) -> 360.78 | R69: =R68 -> 0 | S69: =Q69*(1-R69) -> 360.78 | T69: =(Q69*AE69)/AF69 -> 19.098421 | U69: =T69+S69 -> 379.87842 | V69: 0 | W69: =1.14 -> 1.14 | X69: =X68 -> 1.1235 | Y69: =Y68 -> 1 | Z69: =U69*X69*Y69*W69*(1+V69) -> 486.54448 | AA69: =AA68 -> 0.50014493 | AB69: =AC69/P69 -> 729.88724 | AC69: =U69*X69*(1+AA69)*Y69*W69*(1+V69) -> 729.88724 | AE69: =AE68 -> 170000 | AF69: =AF68 -> 3211396.3
A70: =VALUE(RIGHT(B70,LEN(B70)-2)) -> 67 | B70: F-67 | D70: EXF-A30-B01-04 | E70: Germany | F70: Centrifugal Fan | G70: Single | H70: Ambient | I70: 476764 | J70: PRF 250D4 | K70: 720 | L70: 250 | M70: =IF(ISERROR(VLOOKUP(J70,'Germany price'!$B$1:$G$99001,6,0))," ",VLOOKUP(J70,'Germany price'!$B$1:$G$99001,6,0)) -> 2020 | N70: 2020 | O70: 0.58 | P70: 1 | Q70: =N70*P70*(1-O70) -> 848.4 | R70: =R69 -> 0 | S70: =Q70*(1-R70) -> 848.4 | T70: =(Q70*AE70)/AF70 -> 44.911305 | U70: =T70+S70 -> 893.3113 | V70: 0 | W70: =1.14 -> 1.14 | X70: =X69 -> 1.1235 | Y70: =Y69 -> 1 | Z70: =U70*X70*Y70*W70*(1+V70) -> 1144.1442 | AA70: =AA69 -> 0.50014493 | AB70: =AC70/P70 -> 1716.3821 | AC70: =U70*X70*(1+AA70)*Y70*W70*(1+V70) -> 1716.3821 | AE70: =AE69 -> 170000 | AF70: =AF69 -> 3211396.3
A71: =VALUE(RIGHT(B71,LEN(B71)-2)) -> 68 | B71: F-68 | D71: EXF-A34-B01-01 | E71: Sweden | F71: Inline Fan | G71: Single | H71: Ambient | I71: 19510 | J71: K 200 L sileo | K71: 230 | L71: 125 | M71: =IF(ISERROR(VLOOKUP(J71,'Germany price'!$B$1:$G$99001,6,0))," ",VLOOKUP(J71,'Germany price'!$B$1:$G$99001,6,0)) -> 208 | N71: 208 | O71: 0.58 | P71: 1 | Q71: =N71*P71*(1-O71) -> 87.36 | R71: =R70 -> 0 | S71: =Q71*(1-R71) -> 87.36 | T71: =(Q71*AE71)/AF71 -> 4.6245304 | U71: =T71+S71 -> 91.98453 | V71: 0 | W71: =1.14 -> 1.14 | X71: =X70 -> 1.1235 | Y71: =Y70 -> 1 | Z71: =U71*X71*Y71*W71*(1+V71) -> 117.81287 | AA71: =AA70 -> 0.50014493 | AB71: =AC71/P71 -> 176.73638 | AC71: =U71*X71*(1+AA71)*Y71*W71*(1+V71) -> 176.73638 | AE71: =AE70 -> 170000 | AF71: =AF70 -> 3211396.3
A72: =VALUE(RIGHT(B72,LEN(B72)-2)) -> 69 | B72: F-69 | D72: EXF-A34-B01-02 | E72: Sweden | F72: Inline Fan | G72: Single | H72: Ambient | I72: 93267 | J72: prio 315 | K72: 675 | L72: 125 | M72: =IF(ISERROR(VLOOKUP(J72,'Germany price'!$B$1:$G$99001,6,0))," ",VLOOKUP(J72,'Germany price'!$B$1:$G$99001,6,0)) -> 801 | N72: 801 | O72: 0.58 | P72: 1 | Q72: =N72*P72*(1-O72) -> 336.42 | R72: =R71 -> 0 | S72: =Q72*(1-R72) -> 336.42 | T72: =(Q72*AE72)/AF72 -> 17.808889 | U72: =T72+S72 -> 354.22889 | V72: 0 | W72: =1.14 -> 1.14 | X72: =X71 -> 1.1235 | Y72: =Y71 -> 1 | Z72: =U72*X72*Y72*W72*(1+V72) -> 453.69282 | AA72: =AA71 -> 0.50014493 | AB72: =AC72/P72 -> 680.60498 | AC72: =U72*X72*(1+AA72)*Y72*W72*(1+V72) -> 680.60498 | AE72: =AE71 -> 170000 | AF72: =AF71 -> 3211396.3
A73: =VALUE(RIGHT(B73,LEN(B73)-2)) -> 70 | B73: F-70 | D73: EXF-A34-B01-03 | E73: Germany | F73: Centrifugal Fan | G73: Single | H73: Ambient | I73: 476764 | J73: PRF 250D4 | K73: 545 | L73: 125 | M73: =IF(ISERROR(VLOOKUP(J73,'Germany price'!$B$1:$G$99001,6,0))," ",VLOOKUP(J73,'Germany price'!$B$1:$G$99001,6,0)) -> 2020 | N73: 2020 | O73: 0.58 | P73: 1 | Q73: =N73*P73*(1-O73) -> 848.4 | R73: =R72 -> 0 | S73: =Q73*(1-R73) -> 848.4 | T73: =(Q73*AE73)/AF73 -> 44.911305 | U73: =T73+S73 -> 893.3113 | V73: 0 | W73: =1.14 -> 1.14 | X73: =X72 -> 1.1235 | Y73: =Y72 -> 1 | Z73: =U73*X73*Y73*W73*(1+V73) -> 1144.1442 | AA73: =AA72 -> 0.50014493 | AB73: =AC73/P73 -> 1716.3821 | AC73: =U73*X73*(1+AA73)*Y73*W73*(1+V73) -> 1716.3821 | AE73: =AE72 -> 170000 | AF73: =AF72 -> 3211396.3
A74: =VALUE(RIGHT(B74,LEN(B74)-2)) -> 71 | B74: F-71 | D74: EXF-A37-B01-02 | E74: Germany | F74: Wall Mounted | G74: Single | H74: Ambient | I74: 37411 | J74: AW 450E4 sileo Axial fan | K74: 1700 | L74: - | M74: =IF(ISERROR(VLOOKUP(J74,'Germany price'!$B$1:$G$99001,6,0))," ",VLOOKUP(J74,'Germany price'!$B$1:$G$99001,6,0)) -> 638 | N74: 309.54 | O74: 0 | P74: 2 | Q74: =N74*P74*(1-O74) -> 619.08 | R74: =R73 -> 0 | S74: =Q74*(1-R74) -> 619.08 | T74: =(Q74*AE74)/AF74 -> 32.771913 | U74: =T74+S74 -> 651.85191 | V74: 0 | W74: =1.14 -> 1.14 | X74: =X73 -> 1.1235 | Y74: =Y73 -> 1 | Z74: =U74*X74*Y74*W74*(1+V74) -> 834.88541 | AA74: =AA73 -> 0.50014493 | AB74: =AC74/P74 -> 626.22456 | AC74: =U74*X74*(1+AA74)*Y74*W74*(1+V74) -> 1252.4491 | AE74: =AE73 -> 170000 | AF74: =AF73 -> 3211396.3
A75: =VALUE(RIGHT(B75,LEN(B75)-2)) -> 72 | B75: F-72 | D75: EXF-A37-B01-03 | E75: Sweden | F75: Inline Fan | G75: Single | H75: Ambient | I75: 25363 | J75: K 150 XL sileo | K75: 140 | L75: 125 | M75: =IF(ISERROR(VLOOKUP(J75,'Germany price'!$B$1:$G$99001,6,0))," ",VLOOKUP(J75,'Germany price'!$B$1:$G$99001,6,0)) -> 171 | N75: 171 | O75: 0.58 | P75: 1 | Q75: =N75*P75*(1-O75) -> 71.82 | R75: =R74 -> 0 | S75: =Q75*(1-R75) -> 71.82 | T75: =(Q75*AE75)/AF75 -> 3.8018976 | U75: =T75+S75 -> 75.621898 | V75: 0 | W75: =1.14 -> 1.14 | X75: =X74 -> 1.1235 | Y75: =Y74 -> 1 | Z75: =U75*X75*Y75*W75*(1+V75) -> 96.85577 | AA75: =AA74 -> 0.50014493 | AB75: =AC75/P75 -> 145.29769 | AC75: =U75*X75*(1+AA75)*Y75*W75*(1+V75) -> 145.29769 | AE75: =AE74 -> 170000 | AF75: =AF74 -> 3211396.3
A76: =VALUE(RIGHT(B76,LEN(B76)-2)) -> 73 | B76: F-73 | D76: EXF-A37-B01-04 | E76: Germany | F76: Axial Inline | G76: Single | H76: Ambient | I76: CAP035120001D | J76: AXC 355-6/23°-2-P (160) (1.1 kW) S IE3 C | K76: 1190 | L76: 250 | M76: =IF(ISERROR(VLOOKUP(J76,'Germany price'!$B$1:$G$99001,6,0))," ",VLOOKUP(J76,'Germany price'!$B$1:$G$99001,6,0)) | N76: 1401 | O76: 0.58 | P76: 1 | Q76: =N76*P76*(1-O76) -> 588.42 | R76: =R75 -> 0 | S76: =Q76*(1-R76) -> 588.42 | T76: =(Q76*AE76)/AF76 -> 31.14888 | U76: =T76+S76 -> 619.56888 | V76: 0 | W76: =1.14 -> 1.14 | X76: =X75 -> 1.1235 | Y76: =Y75 -> 1 | Z76: =U76*X76*Y76*W76*(1+V76) -> 793.53763 | AA76: =AA75 -> 0.50014493 | AB76: =AC76/P76 -> 1190.4214 | AC76: =U76*X76*(1+AA76)*Y76*W76*(1+V76) -> 1190.4214 | AE76: =AE75 -> 170000 | AF76: =AF75 -> 3211396.3
A77: =VALUE(RIGHT(B77,LEN(B77)-2)) -> 74 | B77: F-74 | D77: EXF-A37-B01-05 | E77: Sweden | F77: Inline Fan | G77: Single | H77: Ambient | I77: 25363 | J77: K 150 XL sileo | K77: 140 | L77: 125 | M77: =IF(ISERROR(VLOOKUP(J77,'Germany price'!$B$1:$G$99001,6,0))," ",VLOOKUP(J77,'Germany price'!$B$1:$G$99001,6,0)) -> 171 | N77: 171 | O77: 0.58 | P77: 2 | Q77: =N77*P77*(1-O77) -> 143.64 | R77: =R76 -> 0 | S77: =Q77*(1-R77) -> 143.64 | T77: =(Q77*AE77)/AF77 -> 7.6037952 | U77: =T77+S77 -> 151.2438 | V77: 0 | W77: =1.14 -> 1.14 | X77: =X76 -> 1.1235 | Y77: =Y76 -> 1 | Z77: =U77*X77*Y77*W77*(1+V77) -> 193.71154 | AA77: =AA76 -> 0.50014493 | AB77: =AC77/P77 -> 145.29769 | AC77: =U77*X77*(1+AA77)*Y77*W77*(1+V77) -> 290.59539 | AE77: =AE76 -> 170000 | AF77: =AF76 -> 3211396.3
A78: =VALUE(RIGHT(B78,LEN(B78)-2)) -> 75 | B78: F-75 | D78: EXF-B30-B01-01 | E78: Germany | F78: Centrifugal Inline | G78: Single | H78: Ambient | I78: 235401 | J78: MUB 025 355EV Multibox | K78: 465 | L78: 125 | M78: =IF(ISERROR(VLOOKUP(J78,'Germany price'!$B$1:$G$99001,6,0))," ",VLOOKUP(J78,'Germany price'!$B$1:$G$99001,6,0)) -> 999 | N78: 999 | O78: 0.58 | P78: 1 | Q78: =N78*P78*(1-O78) -> 419.58 | R78: =R77 -> 0 | S78: =Q78*(1-R78) -> 419.58 | T78: =(Q78*AE78)/AF78 -> 22.211086 | U78: =T78+S78 -> 441.79109 | V78: 0 | W78: =1.14 -> 1.14 | X78: =X77 -> 1.1235 | Y78: =Y77 -> 1 | Z78: =U78*X78*Y78*W78*(1+V78) -> 565.8416 | AA78: =AA77 -> 0.50014493 | AB78: =AC78/P78 -> 848.84442 | AC78: =U78*X78*(1+AA78)*Y78*W78*(1+V78) -> 848.84442 | AE78: =AE77 -> 170000 | AF78: =AF77 -> 3211396.3
A79: =VALUE(RIGHT(B79,LEN(B79)-2)) -> 76 | B79: F-76 | D79: EXF-B30-B01-03 | E79: Sweden | F79: Inline Fan | G79: Single | H79: Ambient | I79: 19514 | J79: K 315 L Sileo** | K79: 340 | L79: 125 | M79: =IF(ISERROR(VLOOKUP(J79,'Germany price'!$B$1:$G$99001,6,0))," ",VLOOKUP(J79,'Germany price'!$B$1:$G$99001,6,0)) -> 330 | N79: 330 | O79: 0.58 | P79: 1 | Q79: =N79*P79*(1-O79) -> 138.6 | R79: =R78 -> 0 | S79: =Q79*(1-R79) -> 138.6 | T79: =(Q79*AE79)/AF79 -> 7.3369953 | U79: =T79+S79 -> 145.937 | V79: 0 | W79: =1.14 -> 1.14 | X79: =X78 -> 1.1235 | Y79: =Y78 -> 1 | Z79: =U79*X79*Y79*W79*(1+V79) -> 186.91464 | AA79: =AA78 -> 0.50014493 | AB79: =AC79/P79 -> 280.39906 | AC79: =U79*X79*(1+AA79)*Y79*W79*(1+V79) -> 280.39906 | AE79: =AE78 -> 170000 | AF79: =AF78 -> 3211396.3
A80: =VALUE(RIGHT(B80,LEN(B80)-2)) -> 77 | B80: F-77 | D80: EXF-B30-B01-04 | E80: Germany | F80: Wall Mounted | G80: Single | H80: Ambient | I80: 37415 | J80: AW 630DV sileo Axial fan | K80: 3400 | L80: - | M80: =IF(ISERROR(VLOOKUP(J80,'Germany price'!$B$1:$G$99001,6,0))," ",VLOOKUP(J80,'Germany price'!$B$1:$G$99001,6,0)) -> 1352 | N80: 633.36 | O80: 0 | P80: 2 | Q80: =N80*P80*(1-O80) -> 1266.72 | R80: =R79 -> 0 | S80: =Q80*(1-R80) -> 1266.72 | T80: =(Q80*AE80)/AF80 -> 67.055691 | U80: =T80+S80 -> 1333.7757 | V80: 0 | W80: =1.14 -> 1.14 | X80: =X79 -> 1.1235 | Y80: =Y79 -> 1 | Z80: =U80*X80*Y80*W80*(1+V80) -> 1708.2866 | AA80: =AA79 -> 0.50014493 | AB80: =AC80/P80 -> 1281.3387 | AC80: =U80*X80*(1+AA80)*Y80*W80*(1+V80) -> 2562.6774 | AE80: =AE79 -> 170000 | AF80: =AF79 -> 3211396.3
A81: =VALUE(RIGHT(B81,LEN(B81)-2)) -> 78 | B81: F-78 | D81: EXF-B34-B01-01 | E81: Sweden | F81: Inline Fan | G81: Single | H81: Ambient | I81: 19510 | J81: K 200 L sileo | K81: 205 | L81: 125 | M81: =IF(ISERROR(VLOOKUP(J81,'Germany price'!$B$1:$G$99001,6,0))," ",VLOOKUP(J81,'Germany price'!$B$1:$G$99001,6,0)) -> 208 | N81: 208 | O81: 0.58 | P81: 1 | Q81: =N81*P81*(1-O81) -> 87.36 | R81: =R80 -> 0 | S81: =Q81*(1-R81) -> 87.36 | T81: =(Q81*AE81)/AF81 -> 4.6245304 | U81: =T81+S81 -> 91.98453 | V81: 0 | W81: =1.14 -> 1.14 | X81: =X80 -> 1.1235 | Y81: =Y80 -> 1 | Z81: =U81*X81*Y81*W81*(1+V81) -> 117.81287 | AA81: =AA80 -> 0.50014493 | AB81: =AC81/P81 -> 176.73638 | AC81: =U81*X81*(1+AA81)*Y81*W81*(1+V81) -> 176.73638 | AE81: =AE80 -> 170000 | AF81: =AF80 -> 3211396.3
A82: =VALUE(RIGHT(B82,LEN(B82)-2)) -> 79 | B82: F-79 | D82: EXF-B34-B01-02 | E82: Sweden | F82: Inline Fan | G82: Single | H82: Ambient | I82: 25361 | J82: K 125 XL sileo | K82: 60 | L82: 125 | M82: =IF(ISERROR(VLOOKUP(J82,'Germany price'!$B$1:$G$99001,6,0))," ",VLOOKUP(J82,'Germany price'!$B$1:$G$99001,6,0)) -> 141 | N82: 141 | O82: 0.58 | P82: 2 | Q82: =N82*P82*(1-O82) -> 118.44 | R82: =R81 -> 0 | S82: =Q82*(1-R82) -> 118.44 | T82: =(Q82*AE82)/AF82 -> 6.269796 | U82: =T82+S82 -> 124.7098 | V82: 0 | W82: =1.14 -> 1.14 | X82: =X81 -> 1.1235 | Y82: =Y81 -> 1 | Z82: =U82*X82*Y82*W82*(1+V82) -> 159.72706 | AA82: =AA81 -> 0.50014493 | AB82: =AC82/P82 -> 119.80687 | AC82: =U82*X82*(1+AA82)*Y82*W82*(1+V82) -> 239.61374 | AE82: =AE81 -> 170000 | AF82: =AF81 -> 3211396.3
A83: =VALUE(RIGHT(B83,LEN(B83)-2)) -> 80 | B83: F-80 | D83: EXF-B34-B01-03 | E83: Germany | F83: Wall Mounted | G83: Single | H83: Ambient | I83: 37412 | J83: AW 500E4 sileo Axial fan | K83: 2130 | L83: - | M83: =IF(ISERROR(VLOOKUP(J83,'Germany price'!$B$1:$G$99001,6,0))," ",VLOOKUP(J83,'Germany price'!$B$1:$G$99001,6,0)) -> 632 | N83: 327.18 | O83: 0 | P83: 2 | Q83: =N83*P83*(1-O83) -> 654.36 | R83: =R82 -> 0 | S83: =Q83*(1-R83) -> 654.36 | T83: =(Q83*AE83)/AF83 -> 34.639511 | U83: =T83+S83 -> 688.99951 | V83: 0 | W83: =1.14 -> 1.14 | X83: =X82 -> 1.1235 | Y83: =Y82 -> 1 | Z83: =U83*X83*Y83*W83*(1+V83) -> 882.46368 | AA83: =AA82 -> 0.50014493 | AB83: =AC83/P83 -> 661.91171 | AC83: =U83*X83*(1+AA83)*Y83*W83*(1+V83) -> 1323.8234 | AE83: =AE82 -> 170000 | AF83: =AF82 -> 3211396.3
A84: =VALUE(RIGHT(B84,LEN(B84)-2)) -> 81 | B84: F-81 | D84: EXF-B37-B01-01 | E84: Sweden | F84: Inline Fan | G84: Single | H84: Ambient | I84: 27758 | J84: K 315 M sileo** | K84: 260 | L84: 250 | M84: =IF(ISERROR(VLOOKUP(J84,'Germany price'!$B$1:$G$99001,6,0))," ",VLOOKUP(J84,'Germany price'!$B$1:$G$99001,6,0)) -> 276 | N84: 276 | O84: 0.58 | P84: 1 | Q84: =N84*P84*(1-O84) -> 115.92 | R84: =R83 -> 0 | S84: =Q84*(1-R84) -> 115.92 | T84: =(Q84*AE84)/AF84 -> 6.1363961 | U84: =T84+S84 -> 122.0564 | V84: 0 | W84: =1.14 -> 1.14 | X84: =X83 -> 1.1235 | Y84: =Y83 -> 1 | Z84: =U84*X84*Y84*W84*(1+V84) -> 156.32861 | AA84: =AA83 -> 0.50014493 | AB84: =AC84/P84 -> 234.51557 | AC84: =U84*X84*(1+AA84)*Y84*W84*(1+V84) -> 234.51557 | AE84: =AE83 -> 170000 | AF84: =AF83 -> 3211396.3
A85: =VALUE(RIGHT(B85,LEN(B85)-2)) -> 82 | B85: F-82 | D85: EXF-B37-B01-02 | E85: Germany | F85: Wall Mounted | G85: Single | H85: Ambient | I85: 37411 | J85: AW 450E4 sileo Axial fan | K85: 1700 | L85: - | M85: =IF(ISERROR(VLOOKUP(J85,'Germany price'!$B$1:$G$99001,6,0))," ",VLOOKUP(J85,'Germany price'!$B$1:$G$99001,6,0)) -> 638 | N85: 309.54 | O85: 0 | P85: 2 | Q85: =N85*P85*(1-O85) -> 619.08 | R85: =R84 -> 0 | S85: =Q85*(1-R85) -> 619.08 | T85: =(Q85*AE85)/AF85 -> 32.771913 | U85: =T85+S85 -> 651.85191 | V85: 0 | W85: =1.14 -> 1.14 | X85: =X84 -> 1.1235 | Y85: =Y84 -> 1 | Z85: =U85*X85*Y85*W85*(1+V85) -> 834.88541 | AA85: =AA84 -> 0.50014493 | AB85: =AC85/P85 -> 626.22456 | AC85: =U85*X85*(1+AA85)*Y85*W85*(1+V85) -> 1252.4491 | AE85: =AE84 -> 170000 | AF85: =AF84 -> 3211396.3
A86: =VALUE(RIGHT(B86,LEN(B86)-2)) -> 83 | B86: F-83 | D86: EXF-B37-B01-03 | E86: Germany | F86: Axial Inline | G86: Single | H86: Ambient | I86: CAP040120001E | J86: AXC 400-6/20°-2-P (160) (1.5 kW) S IE3 | K86: 1575 | L86: 250 | M86: =IF(ISERROR(VLOOKUP(J86,'Germany price'!$B$1:$G$99001,6,0))," ",VLOOKUP(J86,'Germany price'!$B$1:$G$99001,6,0)) | N86: 1499 | O86: 0.58 | P86: 1 | Q86: =N86*P86*(1-O86) -> 629.58 | R86: =R85 -> 0 | S86: =Q86*(1-R86) -> 629.58 | T86: =(Q86*AE86)/AF86 -> 33.327746 | U86: =T86+S86 -> 662.90775 | V86: 0 | W86: =1.14 -> 1.14 | X86: =X85 -> 1.1235 | Y86: =Y85 -> 1 | Z86: =U86*X86*Y86*W86*(1+V86) -> 849.04561 | AA86: =AA85 -> 0.50014493 | AB86: =AC86/P86 -> 1273.6915 | AC86: =U86*X86*(1+AA86)*Y86*W86*(1+V86) -> 1273.6915 | AE86: =AE85 -> 170000 | AF86: =AF85 -> 3211396.3
A87: =VALUE(RIGHT(B87,LEN(B87)-2)) -> 84 | B87: F-84 | D87: EXF-B37-B01-04 | E87: Germany | F87: Centrifugal Fan | G87: Single | H87: Ambient | I87: 334079 | J87: PRF 355D4 | K87: 1035 | L87: 250 | M87: =IF(ISERROR(VLOOKUP(J87,'Germany price'!$B$1:$G$99001,6,0))," ",VLOOKUP(J87,'Germany price'!$B$1:$G$99001,6,0)) -> 6324 | N87: 6324 | O87: 0.58 | P87: 1 | Q87: =N87*P87*(1-O87) -> 2656.08 | R87: =R86 -> 0 | S87: =Q87*(1-R87) -> 2656.08 | T87: =(Q87*AE87)/AF87 -> 140.60351 | U87: =T87+S87 -> 2796.6835 | V87: 0 | W87: =1.14 -> 1.14 | X87: =X86 -> 1.1235 | Y87: =Y86 -> 1 | Z87: =U87*X87*Y87*W87*(1+V87) -> 3581.9643 | AA87: =AA86 -> 0.50014493 | AB87: =AC87/P87 -> 5373.4656 | AC87: =U87*X87*(1+AA87)*Y87*W87*(1+V87) -> 5373.4656 | AE87: =AE86 -> 170000 | AF87: =AF86 -> 3211396.3
A88: =VALUE(RIGHT(B88,LEN(B88)-2)) -> 85 | B88: F-85 | D88: EXF-C30-B01-01 | E88: Germany | F88: Inline Fan | G88: Single | H88: Ambient | I88: 36381 | J88: prio 200E2 circular duct fan | K88: 90 | L88: 125 | M88: =IF(ISERROR(VLOOKUP(J88,'Germany price'!$B$1:$G$99001,6,0))," ",VLOOKUP(J88,'Germany price'!$B$1:$G$99001,6,0)) -> 227 | N88: 227 | O88: 0.58 | P88: 2 | Q88: =N88*P88*(1-O88) -> 190.68 | R88: =R87 -> 0 | S88: =Q88*(1-R88) -> 190.68 | T88: =(Q88*AE88)/AF88 -> 10.093927 | U88: =T88+S88 -> 200.77393 | V88: 0 | W88: =1.14 -> 1.14 | X88: =X87 -> 1.1235 | Y88: =Y87 -> 1 | Z88: =U88*X88*Y88*W88*(1+V88) -> 257.14924 | AA88: =AA87 -> 0.50014493 | AB88: =AC88/P88 -> 192.88056 | AC88: =U88*X88*(1+AA88)*Y88*W88*(1+V88) -> 385.76113 | AE88: =AE87 -> 170000 | AF88: =AF87 -> 3211396.3
A89: =VALUE(RIGHT(B89,LEN(B89)-2)) -> 86 | B89: F-86 | D89: EXF-C30-B01-02 | E89: Germany | F89: Axial Inline | G89: Single | H89: Ambient | I89: CAP035120001D | J89: AXC 355-6/23°-2-P (160) (1.1 kW) S IE3 C | K89: 1190 | L89: 250 | M89: =IF(ISERROR(VLOOKUP(J89,'Germany price'!$B$1:$G$99001,6,0))," ",VLOOKUP(J89,'Germany price'!$B$1:$G$99001,6,0)) | N89: 1401 | O89: 0.58 | P89: 1 | Q89: =N89*P89*(1-O89) -> 588.42 | R89: =R88 -> 0 | S89: =Q89*(1-R89) -> 588.42 | T89: =(Q89*AE89)/AF89 -> 31.14888 | U89: =T89+S89 -> 619.56888 | V89: 0 | W89: =1.14 -> 1.14 | X89: =X88 -> 1.1235 | Y89: =Y88 -> 1 | Z89: =U89*X89*Y89*W89*(1+V89) -> 793.53763 | AA89: =AA88 -> 0.50014493 | AB89: =AC89/P89 -> 1190.4214 | AC89: =U89*X89*(1+AA89)*Y89*W89*(1+V89) -> 1190.4214 | AE89: =AE88 -> 170000 | AF89: =AF88 -> 3211396.3
A90: =VALUE(RIGHT(B90,LEN(B90)-2)) -> 87 | B90: F-87 | D90: EXF-C30-B01-03 | E90: Germany | F90: Wall Mounted | G90: Single | H90: Ambient | I90: 37411 | J90: AW 450E4 sileo Axial fan | K90: 1330 | L90: - | M90: =IF(ISERROR(VLOOKUP(J90,'Germany price'!$B$1:$G$99001,6,0))," ",VLOOKUP(J90,'Germany price'!$B$1:$G$99001,6,0)) -> 638 | N90: 309.54 | O90: 0 | P90: 2 | Q90: =N90*P90*(1-O90) -> 619.08 | R90: =R89 -> 0 | S90: =Q90*(1-R90) -> 619.08 | T90: =(Q90*AE90)/AF90 -> 32.771913 | U90: =T90+S90 -> 651.85191 | V90: 0 | W90: =1.14 -> 1.14 | X90: =X89 -> 1.1235 | Y90: =Y89 -> 1 | Z90: =U90*X90*Y90*W90*(1+V90) -> 834.88541 | AA90: =AA89 -> 0.50014493 | AB90: =AC90/P90 -> 626.22456 | AC90: =U90*X90*(1+AA90)*Y90*W90*(1+V90) -> 1252.4491 | AE90: =AE89 -> 170000 | AF90: =AF89 -> 3211396.3
A91: =VALUE(RIGHT(B91,LEN(B91)-2)) -> 88 | B91: F-88 | D91: EXF-C34-B01-04 | E91: Germany | F91: Wall Mounted | G91: Single | H91: Ambient | I91: 34140 | J91: AW 710DV sileo Axial fan | K91: 4250 | L91: - | M91: =IF(ISERROR(VLOOKUP(J91,'Germany price'!$B$1:$G$99001,6,0))," ",VLOOKUP(J91,'Germany price'!$B$1:$G$99001,6,0)) -> 2005 | N91: 928.2 | O91: 0 | P91: 2 | Q91: =N91*P91*(1-O91) -> 1856.4 | R91: =R90 -> 0 | S91: =Q91*(1-R91) -> 1856.4 | T91: =(Q91*AE91)/AF91 -> 98.271271 | U91: =T91+S91 -> 1954.6713 | V91: 0 | W91: =1.14 -> 1.14 | X91: =X90 -> 1.1235 | Y91: =Y90 -> 1 | Z91: =U91*X91*Y91*W91*(1+V91) -> 2503.5234 | AA91: =AA90 -> 0.50014493 | AB91: =AC91/P91 -> 1877.824 | AC91: =U91*X91*(1+AA91)*Y91*W91*(1+V91) -> 3755.648 | AE91: =AE90 -> 170000 | AF91: =AF90 -> 3211396.3
A92: =VALUE(RIGHT(B92,LEN(B92)-2)) -> 89 | B92: F-89 | D92: EXF-C37-B01-01 | E92: Germany | F92: Wall Mounted | G92: Single | H92: Ambient | I92: 37415 | J92: AW 630DV sileo Axial fan | K92: 3390 | L92: - | M92: =IF(ISERROR(VLOOKUP(J92,'Germany price'!$B$1:$G$99001,6,0))," ",VLOOKUP(J92,'Germany price'!$B$1:$G$99001,6,0)) -> 1352 | N92: 633.36 | O92: 0 | P92: 2 | Q92: =N92*P92*(1-O92) -> 1266.72 | R92: =R91 -> 0 | S92: =Q92*(1-R92) -> 1266.72 | T92: =(Q92*AE92)/AF92 -> 67.055691 | U92: =T92+S92 -> 1333.7757 | V92: 0 | W92: =1.14 -> 1.14 | X92: =X91 -> 1.1235 | Y92: =Y91 -> 1 | Z92: =U92*X92*Y92*W92*(1+V92) -> 1708.2866 | AA92: =AA91 -> 0.50014493 | AB92: =AC92/P92 -> 1281.3387 | AC92: =U92*X92*(1+AA92)*Y92*W92*(1+V92) -> 2562.6774 | AE92: =AE91 -> 170000 | AF92: =AF91 -> 3211396.3
A93: =VALUE(RIGHT(B93,LEN(B93)-2)) -> 90 | B93: F-90 | D93: EX.F-BS02-PARKING-01:04 | E93: Germany | F93: Axial Inline | G93: Single | H93: 300°C/2Hr | I93: CAPVB112140301P | J93: AXC 1120-12/25°-4(B)-PV (500) (37 kW) S IE3 E | K93: 11400/17400 | L93: 500/1165 | M93: =IF(ISERROR(VLOOKUP(J93,'Germany price'!$B$1:$G$99001,6,0))," ",VLOOKUP(J93,'Germany price'!$B$1:$G$99001,6,0)) | N93: 16630 | O93: 0.58 | P93: 4 | Q93: =N93*P93*(1-O93) -> 27938.4 | R93: =R92 -> 0 | S93: =Q93*(1-R93) -> 27938.4 | T93: =(Q93*AE93)/AF93 -> 1478.9604 | U93: =T93+S93 -> 29417.36 | V93: 0 | W93: =1.14 -> 1.14 | X93: =X92 -> 1.1235 | Y93: =Y92 -> 1 | Z93: =U93*X93*Y93*W93*(1+V93) -> 37677.461 | AA93: =AA92 -> 0.50014493 | AB93: =AC93/P93 -> 14130.413 | AC93: =U93*X93*(1+AA93)*Y93*W93*(1+V93) -> 56521.652 | AE93: =AE92 -> 170000 | AF93: =AF92 -> 3211396.3
A94: =VALUE(RIGHT(B94,LEN(B94)-2)) -> 91 | B94: F-91 | D94: EX.F-BS02-PARKING-05:08 | E94: Germany | F94: Axial Inline | G94: Single | H94: 300°C/2Hr | I94: CAPVB112140301Q | J94: AXC 1120-12/27°-4(B)-PV (500) (45 kW) S IE3 E | K94: 11300/17600 | L94: 500/1213 | M94: =IF(ISERROR(VLOOKUP(J94,'Germany price'!$B$1:$G$99001,6,0))," ",VLOOKUP(J94,'Germany price'!$B$1:$G$99001,6,0)) | N94: 17794 | O94: 0.58 | P94: 4 | Q94: =N94*P94*(1-O94) -> 29893.92 | R94: =R93 -> 0 | S94: =Q94*(1-R94) -> 29893.92 | T94: =(Q94*AE94)/AF94 -> 1582.4787 | U94: =T94+S94 -> 31476.399 | V94: 0 | W94: =1.14 -> 1.14 | X94: =X93 -> 1.1235 | Y94: =Y93 -> 1 | Z94: =U94*X94*Y94*W94*(1+V94) -> 40314.657 | AA94: =AA93 -> 0.50014493 | AB94: =AC94/P94 -> 15119.457 | AC94: =U94*X94*(1+AA94)*Y94*W94*(1+V94) -> 60477.828 | AE94: =AE93 -> 170000 | AF94: =AF93 -> 3211396.3
A95: =VALUE(RIGHT(B95,LEN(B95)-2)) -> 92 | B95: F-92 | D95: EX.F-BS02-PARKING-09:12 | E95: Germany | F95: Axial Inline | G95: Single | H95: 300°C/2Hr | I95: CAPVB125140301R | J95: AXC 1250-12/20°-4(B)-PV (500) (55 kW) S IE3 E | K95: 13400/22300 | L95: 500/1385 | M95: =IF(ISERROR(VLOOKUP(J95,'Germany price'!$B$1:$G$99001,6,0))," ",VLOOKUP(J95,'Germany price'!$B$1:$G$99001,6,0)) | N95: 20413 | O95: 0.58 | P95: 4 | Q95: =N95*P95*(1-O95) -> 34293.84 | R95: =R94 -> 0 | S95: =Q95*(1-R95) -> 34293.84 | T95: =(Q95*AE95)/AF95 -> 1815.395 | U95: =T95+S95 -> 36109.235 | V95: 0 | W95: =1.14 -> 1.14 | X95: =X94 -> 1.1235 | Y95: =Y94 -> 1 | Z95: =U95*X95*Y95*W95*(1+V95) -> 46248.347 | AA95: =AA94 -> 0.50014493 | AB95: =AC95/P95 -> 17344.806 | AC95: =U95*X95*(1+AA95)*Y95*W95*(1+V95) -> 69379.224 | AE95: =AE94 -> 170000 | AF95: =AF94 -> 3211396.3
A96: =VALUE(RIGHT(B96,LEN(B96)-2)) -> 93 | B96: F-93 | D96: EX.F-BS02-PARKING-13:16 | E96: Germany | F96: Axial Inline | G96: Single | H96: 300°C/2Hr | I96: CAPVB125140301Q | J96: AXC 1250-12/18°-4(B)-PV (500) (45 kW) S IE3 E | K96: 11200/18600 | L96: 500/1379 | M96: =IF(ISERROR(VLOOKUP(J96,'Germany price'!$B$1:$G$99001,6,0))," ",VLOOKUP(J96,'Germany price'!$B$1:$G$99001,6,0)) | N96: 18629 | O96: 0.58 | P96: 4 | Q96: =N96*P96*(1-O96) -> 31296.72 | R96: =R95 -> 0 | S96: =Q96*(1-R96) -> 31296.72 | T96: =(Q96*AE96)/AF96 -> 1656.738 | U96: =T96+S96 -> 32953.458 | V96: 0 | W96: =1.14 -> 1.14 | X96: =X95 -> 1.1235 | Y96: =Y95 -> 1 | Z96: =U96*X96*Y96*W96*(1+V96) -> 42206.459 | AA96: =AA95 -> 0.50014493 | AB96: =AC96/P96 -> 15828.952 | AC96: =U96*X96*(1+AA96)*Y96*W96*(1+V96) -> 63315.806 | AE96: =AE95 -> 170000 | AF96: =AF95 -> 3211396.3
A97: =VALUE(RIGHT(B97,LEN(B97)-2)) -> 94 | B97: F-94 | D97: EX.F-BS02-PARKING-17:20 | E97: Germany | F97: Axial Inline | G97: Single | H97: 300°C/2Hr | I97: CAPVB112140301P | J97: AXC 1120-12/26°-4(B)-PV (500) (37 kW) S IE3 E | K97: 11000/17200 | L97: 500/1222 | M97: =IF(ISERROR(VLOOKUP(J97,'Germany price'!$B$1:$G$99001,6,0))," ",VLOOKUP(J97,'Germany price'!$B$1:$G$99001,6,0)) | N97: 16630 | O97: 0.58 | P97: 4 | Q97: =N97*P97*(1-O97) -> 27938.4 | R97: =R96 -> 0 | S97: =Q97*(1-R97) -> 27938.4 | T97: =(Q97*AE97)/AF97 -> 1478.9604 | U97: =T97+S97 -> 29417.36 | V97: 0 | W97: =1.14 -> 1.14 | X97: =X96 -> 1.1235 | Y97: =Y96 -> 1 | Z97: =U97*X97*Y97*W97*(1+V97) -> 37677.461 | AA97: =AA96 -> 0.50014493 | AB97: =AC97/P97 -> 14130.413 | AC97: =U97*X97*(1+AA97)*Y97*W97*(1+V97) -> 56521.652 | AE97: =AE96 -> 170000 | AF97: =AF96 -> 3211396.3
A98: =VALUE(RIGHT(B98,LEN(B98)-2)) -> 95 | B98: F-95 | D98: EX.F-BS02-PARKING-21:24 | E98: Germany | F98: Axial Inline | G98: Single | H98: 300°C/2Hr | I98: CAPVB125140301R | J98: AXC 1250-12/20°-4(B)-PV (500) (55 kW) S IE3 E | K98: 13800/22900 | L98: 500/1377 | M98: =IF(ISERROR(VLOOKUP(J98,'Germany price'!$B$1:$G$99001,6,0))," ",VLOOKUP(J98,'Germany price'!$B$1:$G$99001,6,0)) | N98: 20413 | O98: 0.58 | P98: 4 | Q98: =N98*P98*(1-O98) -> 34293.84 | R98: =R97 -> 0 | S98: =Q98*(1-R98) -> 34293.84 | T98: =(Q98*AE98)/AF98 -> 1815.395 | U98: =T98+S98 -> 36109.235 | V98: 0 | W98: =1.14 -> 1.14 | X98: =X97 -> 1.1235 | Y98: =Y97 -> 1 | Z98: =U98*X98*Y98*W98*(1+V98) -> 46248.347 | AA98: =AA97 -> 0.50014493 | AB98: =AC98/P98 -> 17344.806 | AC98: =U98*X98*(1+AA98)*Y98*W98*(1+V98) -> 69379.224 | AE98: =AE97 -> 170000 | AF98: =AF97 -> 3211396.3
A99: =VALUE(RIGHT(B99,LEN(B99)-2)) -> 96 | B99: F-96 | D99: EX.F-BS02-PARKING-25:28 | E99: Germany | F99: Axial Inline | G99: Single | H99: 300°C/2Hr | I99: CAPVB125140301R | J99: AXC 1250-12/20°-4(B)-PV (500) (55 kW) S IE3 E | K99: 13900/23100 | L99: 500/1381 | M99: =IF(ISERROR(VLOOKUP(J99,'Germany price'!$B$1:$G$99001,6,0))," ",VLOOKUP(J99,'Germany price'!$B$1:$G$99001,6,0)) | N99: 20413 | O99: 0.58 | P99: 4 | Q99: =N99*P99*(1-O99) -> 34293.84 | R99: =R98 -> 0 | S99: =Q99*(1-R99) -> 34293.84 | T99: =(Q99*AE99)/AF99 -> 1815.395 | U99: =T99+S99 -> 36109.235 | V99: 0 | W99: =1.14 -> 1.14 | X99: =X98 -> 1.1235 | Y99: =Y98 -> 1 | Z99: =U99*X99*Y99*W99*(1+V99) -> 46248.347 | AA99: =AA98 -> 0.50014493 | AB99: =AC99/P99 -> 17344.806 | AC99: =U99*X99*(1+AA99)*Y99*W99*(1+V99) -> 69379.224 | AE99: =AE98 -> 170000 | AF99: =AF98 -> 3211396.3
A100: =VALUE(RIGHT(B100,LEN(B100)-2)) -> 97 | B100: F-97 | D100: EX.F-BS02-PARKING-29:32 | E100: Germany | F100: Axial Inline | G100: Single | H100: 300°C/2Hr | I100: CAPVB125140311S | J100: AXC 1250-12/25°-4(B)-PV (500) (75 kW) S IE4 E | K100: 16100/26800 | L100: 500/1385 | M100: =IF(ISERROR(VLOOKUP(J100,'Germany price'!$B$1:$G$99001,6,0))," ",VLOOKUP(J100,'Germany price'!$B$1:$G$99001,6,0)) | N100: 28326.37 | O100: 0.58 | P100: 4 | Q100: =N100*P100*(1-O100) -> 47588.302 | R100: =R99 -> 0 | S100: =Q100*(1-R100) -> 47588.302 | T100: =(Q100*AE100)/AF100 -> 2519.1569 | U100: =T100+S100 -> 50107.459 | V100: 0 | W100: =1.14 -> 1.14 | X100: =X99 -> 1.1235 | Y100: =Y99 -> 1 | Z100: =U100*X100*Y100*W100*(1+V100) -> 64177.132 | AA100: =AA99 -> 0.50014493 | AB100: =AC100/P100 -> 24068.75 | AC100: =U100*X100*(1+AA100)*Y100*W100*(1+V100) -> 96274.999 | AE100: =AE99 -> 170000 | AF100: =AF99 -> 3211396.3
A101: =VALUE(RIGHT(B101,LEN(B101)-2)) -> 98 | B101: F-98 | D101: EX.F-BS02-PARKING-33:36 | E101: Germany | F101: Axial Inline | G101: Single | H101: 300°C/2Hr | I101: CAPVB125140311S | J101: AXC 1250-12/26°-4(B)-PV (500) (75 kW) S IE4 E | K101: 17000/28400 | L101: 500/1395 | M101: =IF(ISERROR(VLOOKUP(J101,'Germany price'!$B$1:$G$99001,6,0))," ",VLOOKUP(J101,'Germany price'!$B$1:$G$99001,6,0)) | N101: 28326.37 | O101: 0.58 | P101: 4 | Q101: =N101*P101*(1-O101) -> 47588.302 | R101: =R100 -> 0 | S101: =Q101*(1-R101) -> 47588.302 | T101: =(Q101*AE101)/AF101 -> 2519.1569 | U101: =T101+S101 -> 50107.459 | V101: 0 | W101: =1.14 -> 1.14 | X101: =X100 -> 1.1235 | Y101: =Y100 -> 1 | Z101: =U101*X101*Y101*W101*(1+V101) -> 64177.132 | AA101: =AA100 -> 0.50014493 | AB101: =AC101/P101 -> 24068.75 | AC101: =U101*X101*(1+AA101)*Y101*W101*(1+V101) -> 96274.999 | AE101: =AE100 -> 170000 | AF101: =AF100 -> 3211396.3
...

Sheet QUOTATION
B2: sr | C2: =COST!B3 -> SN | D2: =COST!C3 -> Location | E2: =COST!D3 -> Fan Ref. (SN) | F2: =COST!E3 -> Origin | G2: =COST!F3 -> Fan Type | H2: =COST!G3 -> Speed | I2: =COST!H3 -> Smoke Rating | J2: =COST!J3 -> Item Code (Model) | K2: =COST!K3 -> Flow l/s | L2: =COST!L3 -> ESP Pa | M2: =COST!P3 -> Qty. | N2: =COST!AB3 -> Unit Price € | O2: =COST!AC3 -> Total Price €
B3: 1 | C3: =COST!B4 -> F-01 | D3: =COST!C4 -> 0 | E3: =COST!D4 -> FAF-A29-B02-01 | F3: =COST!E4 -> Germany | G3: =COST!F4 -> Axial Inline | H3: =COST!G4 -> Single | I3: =COST!H4 -> Ambient | J3: =COST!J4 -> AXC 710-9/20°-4-P (350) (3 kW) S IE3 | K3: =COST!K4 -> 3560 | L3: =COST!L4 -> 375 | M3: =COST!P4 -> 2 | N3: =COST!AB4 -> 2136.9807 | O3: =M3*N3 -> 4273.9614
B4: 2 | C4: =COST!B5 -> F-02 | D4: =COST!C5 -> 0 | E4: =COST!D5 -> FAF-A29-B02-02 | F4: =COST!E5 -> Germany | G4: =COST!F5 -> Centrifugal Inline | H4: =COST!G5 -> Single | I4: =COST!H5 -> Ambient | J4: =COST!J5 -> MUB 042 400EV Multibox | K4: =COST!K5 -> 580 | L4: =COST!L5 -> 250 | M4: =COST!P5 -> 1 | N4: =COST!AB5 -> 1018.7832 | O4: =M4*N4 -> 1018.7832
B5: 3 | C5: =COST!B6 -> F-03 | D5: =COST!C6 -> 0 | E5: =COST!D6 -> FAF-A30-B02-01 | F5: =COST!E6 -> Sweden | G5: =COST!F6 -> Inline Fan | H5: =COST!G6 -> Single | I5: =COST!H6 -> Ambient | J5: =COST!J6 -> KT 60-30-4 | K5: =COST!K6 -> 855 | L5: =COST!L6 -> 250 | M5: =COST!P6 -> 1 | N5: =COST!AB6 -> 1004.3384 | O5: =M5*N5 -> 1004.3384
B6: 4 | C6: =COST!B7 -> F-04 | D6: =COST!C7 -> 0 | E6: =COST!D7 -> FAF-A35-B02-01 | F6: =COST!E7 -> Germany | G6: =COST!F7 -> Axial Inline | H6: =COST!G7 -> Single | I6: =COST!H7 -> Ambient | J6: =COST!J7 -> AXC 400-6/31°-2-P (160) (2.2 kW) S IE3 C | K6: =COST!K7 -> 2240 | L6: =COST!L7 -> 250 | M6: =COST!P7 -> 2 | N6: =COST!AB7 -> 1273.6915 | O6: =M6*N6 -> 2547.3829
B7: 5 | C7: =COST!B8 -> F-05 | D7: =COST!C8 -> 0 | E7: =COST!D8 -> FAF-A35-B02-02 | F7: =COST!E8 -> Germany | G7: =COST!F8 -> Centrifugal Fan | H7: =COST!G8 -> Single | I7: =COST!H8 -> Ambient | J7: =COST!J8 -> PRF 355D4 | K7: =COST!K8 -> 1125 | L7: =COST!L8 -> 250 | M7: =COST!P8 -> 1 | N7: =COST!AB8 -> 5373.4656 | O7: =M7*N7 -> 5373.4656
B8: 6 | C8: =COST!B9 -> F-06 | D8: =COST!C9 -> 0 | E8: =COST!D9 -> FAF-B30-B02-02 | F8: =COST!E9 -> Sweden | G8: =COST!F9 -> Inline Fan | H8: =COST!G9 -> Single | I8: =COST!H9 -> Ambient | J8: =COST!J9 -> K 315 L Sileo** | K8: =COST!K9 -> 340 | L8: =COST!L9 -> 125 | M8: =COST!P9 -> 1 | N8: =COST!AB9 -> 280.39906 | O8: =M8*N8 -> 280.39906
B9: 7 | C9: =COST!B10 -> F-07 | D9: =COST!C10 -> 0 | E9: =COST!D10 -> FAF-B35-B02-01 | F9: =COST!E10 -> Sweden | G9: =COST!F10 -> Inline Fan | H9: =COST!G10 -> Single | I9: =COST!H10 -> Ambient | J9: =COST!J10 -> KT 60-35-4 | K9: =COST!K10 -> 1025 | L9: =COST!L10 -> 250 | M9: =COST!P10 -> 1 | N9: =COST!AB10 -> 1226.1086 | O9: =M9*N9 -> 1226.1086
B10: 8 | C10: =COST!B11 -> F-08 | D10: =COST!C11 -> 0 | E10: =COST!D11 -> FAF-B35-B02-02 | F10: =COST!E11 -> Germany | G10: =COST!F11 -> Axial Inline | H10: =COST!G11 -> Single | I10: =COST!H11 -> Ambient | J10: =COST!J11 -> AXC 800-6/20°-4-PV (350) (4 kW) S IE3 A | K10: =COST!K11 -> 5800 | L10: =COST!L11 -> 375 | M10: =COST!P11 -> 2 | N10: =COST!AB11 -> 2753.0089 | O10: =M10*N10 -> 5506.0178
B11: 9 | C11: =COST!B12 -> F-09 | D11: =COST!C12 -> 0 | E11: =COST!D12 -> FAF-B35-B02-03 | F11: =COST!E12 -> Germany | G11: =COST!F12 -> Axial Inline | H11: =COST!G12 -> Single | I11: =COST!H12 -> Ambient | J11: =COST!J12 -> AXC 450-6/23°-2-P (200) (2.2 kW) S IE3 | K11: =COST!K12 -> 2405 | L11: =COST!L12 -> 375 | M11: =COST!P12 -> 1 | N11: =COST!AB12 -> 1415.5904 | O11: =M11*N11 -> 1415.5904
B12: 10 | C12: =COST!B13 -> F-10 | D12: =COST!C13 -> 0 | E12: =COST!D13 -> FAF-B35-B02-04 | F12: =COST!E13 -> Sweden | G12: =COST!F13 -> Inline Fan | H12: =COST!G13 -> Single | I12: =COST!H13 -> Ambient | J12: =COST!J13 -> K 315 M sileo** | K12: =COST!K13 -> 210 | L12: =COST!L13 -> 250 | M12: =COST!P13 -> 1 | N12: =COST!AB13 -> 234.51557 | O12: =M12*N12 -> 234.51557
B13: 11 | C13: =COST!B14 -> F-11 | D13: =COST!C14 -> 0 | E13: =COST!D14 -> FAF-C29-B02-01 | F13: =COST!E14 -> Sweden | G13: =COST!F14 -> Inline Fan | H13: =COST!G14 -> Single | I13: =COST!H14 -> Ambient | J13: =COST!J14 -> KT 60-35-4 | K13: =COST!K14 -> 1145 | L13: =COST!L14 -> 250 | M13: =COST!P14 -> 1 | N13: =COST!AB14 -> 1226.1086 | O13: =M13*N13 -> 1226.1086
B14: 12 | C14: =COST!B15 -> F-12 | D14: =COST!C15 -> 0 | E14: =COST!D15 -> FAF-C29-B02-02 | F14: =COST!E15 -> Sweden | G14: =COST!F15 -> Inline Fan | H14: =COST!G15 -> Single | I14: =COST!H15 -> Ambient | J14: =COST!J15 -> KT 60-30-4 | K14: =COST!K15 -> 725 | L14: =COST!L15 -> 250 | M14: =COST!P15 -> 1 | N14: =COST!AB15 -> 1004.3384 | O14: =M14*N14 -> 1004.3384
... B268: 266 | C268: =COST!B269 -> F-263 | D268: =COST!C269 -> 0 | E268: =COST!D269 -> P.FR-FAN-B01-003 | F268: =COST!E269 -> Germany | G268: =COST!F269 -> Axial Inline | H268: =COST!G269 -> Single | I268: =COST!H269 -> 300°C/2Hr | J268: =COST!J269 -> AXC 1250-8/14°-4(B)-P (500) (30 kW) S IE3 | K268: =COST!K269 -> 11041/18403 | L268: =COST!L269 -> 750 | M268: =COST!P269 -> 1 | N268: =COST!AB269 -> 10084.17 | O268: =M268*N268 -> 10084.17
C269: =COST!B270 -> F-264 | D269: =COST!C270 -> 0 | E269: =COST!D270 -> P.FR-FAN-B01-004 | F269: =COST!E270 -> Germany | G269: =COST!F270 -> Axial Inline | H269: =COST!G270 -> Single | I269: =COST!H270 -> 300°C/2Hr | J269: =COST!J270 -> AXC 1250-8/14°-4(B)-P (500) (30 kW) S IE3 | K269: =COST!K270 -> 11041/18403 | L269: =COST!L270 -> 750 | M269: =COST!P270 -> 1 | N269: =COST!AB270 -> 10084.17 | O269: =M269*N269 -> 10084.17
C270: =COST!B271 -> F-265 | D270: =COST!C271 -> 0 | E270: =COST!D271 -> P.FR-FAN-B01-005 | F270: =COST!E271 -> Germany | G270: =COST!F271 -> Axial Inline | H270: =COST!G271 -> Single | I270: =COST!H271 -> 300°C/2Hr | J270: =COST!J271 -> AXC 1000-10/23°-4(B)-PV (450) (18.5 kW) S IE3 E | K270: =COST!K271 -> 7872/13119 | L270: =COST!L271 -> 750 | M270: =COST!P271 -> 1 | N270: =COST!AB271 -> 8332.9501 | O270: =M270*N270 -> 8332.9501
C271: =COST!B272 -> F-266 | D271: =COST!C272 -> 0 | E271: =COST!D272 -> P.FR-FAN-B01-006 | F271: =COST!E272 -> Germany | G271: =COST!F272 -> Axial Inline | H271: =COST!G272 -> Single | I271: =COST!H272 -> 300°C/2Hr | J271: =COST!J272 -> AXC 1000-10/23°-4(B)-PV (450) (18.5 kW) S IE3 E | K271: =COST!K272 -> 7872/13119 | L271: =COST!L272 -> 750 | M271: =COST!P272 -> 1 | N271: =COST!AB272 -> 8332.9501 | O271: =M271*N271 -> 8332.9501
C272: =COST!B273 -> F-267 | D272: =COST!C273 -> 0 | E272: =COST!D273 -> P.FR-FAN-B01-007 | F272: =COST!E273 -> Germany | G272: =COST!F273 -> Axial Inline | H272: =COST!G273 -> Single | I272: =COST!H273 -> 300°C/2Hr | J272: =COST!J273 -> AXC 1000-10/23°-4(B)-PV (450) (18.5 kW) S IE3 E | K272: =COST!K273 -> 7872/13119 | L272: =COST!L273 -> 750 | M272: =COST!P273 -> 1 | N272: =COST!AB273 -> 8332.9501 | O272: =M272*N272 -> 8332.9501
C273: =COST!B274 -> F-268 | D273: =COST!C274 -> 0 | E273: =COST!D274 -> P.FR-FAN-B01-008 | F273: =COST!E274 -> Germany | G273: =COST!F274 -> Axial Inline | H273: =COST!G274 -> Single | I273: =COST!H274 -> 300°C/2Hr | J273: =COST!J274 -> AXC 1000-10/23°-4(B)-PV (450) (18.5 kW) S IE3 E | K273: =COST!K274 -> 7872/13119 | L273: =COST!L274 -> 750 | M273: =COST!P274 -> 1 | N273: =COST!AB274 -> 8332.9501 | O273: =M273*N273 -> 8332.9501
C274: =COST!B275 -> F-269 | D274: =COST!C275 -> 0 | E274: =COST!D275 -> P.FR-FAN-B01-009 | F274: =COST!E275 -> Germany | G274: =COST!F275 -> Axial Inline | H274: =COST!G275 -> Single | I274: =COST!H275 -> 300°C/2Hr | J274: =COST!J275 -> AXC 1250-8/15°-4(B)-P (500) (30 kW) S IE3 E | K274: =COST!K275 -> 12272/20453 | L274: =COST!L275 -> 650 | M274: =COST!P275 -> 1 | N274: =COST!AB275 -> 10084.17 | O274: =M274*N274 -> 10084.17
C275: =COST!B276 -> F-270 | D275: =COST!C276 -> 0 | E275: =COST!D276 -> P.FR-FAN-B01-010 | F275: =COST!E276 -> Germany | G275: =COST!F276 -> Axial Inline | H275: =COST!G276 -> Single | I275: =COST!H276 -> 300°C/2Hr | J275: =COST!J276 -> AXC 1250-8/15°-4(B)-P (500) (30 kW) S IE3 E | K275: =COST!K276 -> 12272/20453 | L275: =COST!L276 -> 650 | M275: =COST!P276 -> 1 | N275: =COST!AB276 -> 10084.17 | O275: =M275*N275 -> 10084.17
C276: =COST!B277 -> F-271 | D276: =COST!C277 -> 0 | E276: =COST!D277 -> P.FR-FAN-B01-011 | F276: =COST!E277 -> Germany | G276: =COST!F277 -> Axial Inline | H276: =COST!G277 -> Single | I276: =COST!H277 -> 300°C/2Hr | J276: =COST!J277 -> AXC 1250-8/15°-4(B)-P (500) (30 kW) S IE3 E | K276: =COST!K277 -> 12272/20453 | L276: =COST!L277 -> 650 | M276: =COST!P277 -> 1 | N276: =COST!AB277 -> 10084.17 | O276: =M276*N276 -> 10084.17
C277: =COST!B278 -> F-272 | D277: =COST!C278 -> 0 | E277: =COST!D278 -> P.FR-FAN-B02-001 | F277: =COST!E278 -> Germany | G277: =COST!F278 -> Axial Inline | H277: =COST!G278 -> Single | I277: =COST!H278 -> 300°C/2Hr | J277: =COST!J278 -> AXC 1000-10/32°-4(B)-PV (450) (30 kW) S IE3 E | K277: =COST!K278 -> 10028/16713 | L277: =COST!L278 -> 800 | M277: =COST!P278 -> 1 | N277: =COST!AB278 -> 9842.8566 | O277: =M277*N277 -> 9842.8566
C278: =COST!B279 -> F-273 | D278: =COST!C279 -> 0 | E278: =COST!D279 -> P.FR-FAN-B02-002 | F278: =COST!E279 -> Germany | G278: =COST!F279 -> Axial Inline | H278: =COST!G279 -> Single | I278: =COST!H279 -> 300°C/2Hr | J278: =COST!J279 -> AXC 1000-10/32°-4(B)-PV (450) (30 kW) S IE3 E | K278: =COST!K279 -> 10028/16713 | L278: =COST!L279 -> 800 | M278: =COST!P279 -> 1 | N278: =COST!AB279 -> 9842.8566 | O278: =M278*N278 -> 9842.8566
C279: =COST!B280 -> F-274 | D279: =COST!C280 -> 0 | E279: =COST!D280 -> P.FR-FAN-B02-003 | F279: =COST!E280 -> Germany | G279: =COST!F280 -> Axial Inline | H279: =COST!G280 -> Single | I279: =COST!H280 -> 300°C/2Hr | J279: =COST!J280 -> AXC 1000-10/32°-4(B)-PV (450) (30 kW) S IE3 E | K279: =COST!K280 -> 10028/16713 | L279: =COST!L280 -> 800 | M279: =COST!P280 -> 1 | N279: =COST!AB280 -> 9842.8566 | O279: =M279*N279 -> 9842.8566
C280: =COST!B281 -> F-275 | D280: =COST!C281 -> 0 | E280: =COST!D281 -> P.FR-FAN-B02-004 | F280: =COST!E281 -> Germany | G280: =COST!F281 -> Axial Inline | H280: =COST!G281 -> Single | I280: =COST!H281 -> 300°C/2Hr | J280: =COST!J281 -> AXC 1000-10/32°-4(B)-PV (450) (30 kW) S IE3 E | K280: =COST!K281 -> 10028/16713 | L280: =COST!L281 -> 800 | M280: =COST!P281 -> 1 | N280: =COST!AB281 -> 9842.8566 | O280: =M280*N280 -> 9842.8566
... C748: =COST!B749 -> F-746 | D748: =COST!C749 -> 0 | E748: =COST!D749 -> 0 | F748: =COST!E749 -> 0 | G748: =COST!F749 -> 0 | H748: =COST!G749 -> 0 | I748: =COST!H749 -> 0 | J748: =COST!J749 -> 0 | K748: =COST!K749 -> 0 | L748: =COST!L749 -> 0 | M748: =COST!P749 -> 0.0001 | N748: =COST!AB749 -> 2.0230812e-07 | O748: =M748*N748 -> 2.0230812e-11
B749: 267 | C749: =COST!B750 -> F-747 | D749: =COST!C750 -> 0 | E749: =COST!D750 -> 0 | F749: =COST!E750 -> 0 | G749: =COST!F750 -> 0 | H749: =COST!G750 -> 0 | I749: =COST!H750 -> 0 | J749: =COST!J750 -> 0 | K749: =COST!K750 -> 0 | L749: =COST!L750 -> 0 | M749: =COST!P750 -> 0.0001 | N749: =COST!AB750 -> 2.0230812e-07 | O749: =M749*N749 -> 2.0230812e-11
B750: 268 | C750: =COST!B751 -> F-748 | D750: =COST!C751 -> 0 | E750: =COST!D751 -> 0 | F750: =COST!E751 -> 0 | G750: =COST!F751 -> 0 | H750: =COST!G751 -> 0 | I750: =COST!H751 -> 0 | J750: =COST!J751 -> 0 | K750: =COST!K751 -> 0 | L750: =COST!L751 -> 0 | M750: =COST!P751 -> 0.0001 | N750: =COST!AB751 -> 2.0230812e-07 | O750: =M750*N750 -> 2.0230812e-11
B751: 269 | C751: =COST!B752 -> F-749 | D751: =COST!C752 -> 0 | E751: =COST!D752 -> 0 | F751: =COST!E752 -> 0 | G751: =COST!F752 -> 0 | H751: =COST!G752 -> 0 | I751: =COST!H752 -> 0 | J751: =COST!J752 -> 0 | K751: =COST!K752 -> 0 | L751: =COST!L752 -> 0 | M751: =COST!P752 -> 0.0001 | N751: =COST!AB752 -> 2.0230812e-07 | O751: =M751*N751 -> 2.0230812e-11
B752: 270 | C752: =COST!B753 -> F-750 | D752: =COST!C753 -> 0 | E752: =COST!D753 -> 0 | F752: =COST!E753 -> 0 | G752: =COST!F753 -> 0 | H752: =COST!G753 -> 0 | I752: =COST!H753 -> 0 | J752: =COST!J753 -> 0 | K752: =COST!K753 -> 0 | L752: =COST!L753 -> 0 | M752: =COST!P753 -> 0.0001 | N752: =COST!AB753 -> 2.0230812e-07 | O752: =M752*N752 -> 2.0230812e-11
B753: 271 | C753: =COST!B754 -> F-751 | D753: =COST!C754 -> 0 | E753: =COST!D754 -> 0 | F753: =COST!E754 -> 0 | G753: =COST!F754 -> 0 | H753: =COST!G754 -> 0 | I753: =COST!H754 -> 0 | J753: =COST!J754 -> 0 | K753: =COST!K754 -> 0 | L753: =COST!L754 -> 0 | M753: =COST!P754 -> 0.0001 | N753: =COST!AB754 -> 2.0230812e-07 | O753: =M753*N753 -> 2.0230812e-11
B754: 272 | C754: =COST!B755 -> F-752 | D754: =COST!C755 -> 0 | E754: =COST!D755 -> 0 | F754: =COST!E755 -> 0 | G754: =COST!F755 -> 0 | H754: =COST!G755 -> 0 | I754: =COST!H755 -> 0 | J754: =COST!J755 -> 0 | K754: =COST!K755 -> 0 | L754: =COST!L755 -> 0 | M754: =COST!P755 -> 0.0001 | N754: =COST!AB755 -> 2.0230812e-07 | O754: =M754*N754 -> 2.0230812e-11
B755: 273 | C755: =COST!B756 -> F-753 | D755: =COST!C756 -> 0 | E755: =COST!D756 -> 0 | F755: =COST!E756 -> 0 | G755: =COST!F756 -> 0 | H755: =COST!G756 -> 0 | I755: =COST!H756 -> 0 | J755: =COST!J756 -> 0 | K755: =COST!K756 -> 0 | L755: =COST!L756 -> 0 | M755: =COST!P756 -> 0.0001 | N755: =COST!AB756 -> 2.0230812e-07 | O755: =M755*N755 -> 2.0230812e-11
B756: 274 | C756: =COST!B757 -> F-754 | D756: =COST!C757 -> 0 | E756: =COST!D757 -> 0 | F756: =COST!E757 -> 0 | G756: =COST!F757 -> 0 | H756: =COST!G757 -> 0 | I756: =COST!H757 -> 0 | J756: =COST!J757 -> 0 | K756: =COST!K757 -> 0 | L756: =COST!L757 -> 0 | M756: =COST!P757 -> 0.0001 | N756: =COST!AB757 -> 2.0230812e-07 | O756: =M756*N756 -> 2.0230812e-11
B757: 275 | C757: =COST!B758 -> F-755 | D757: =COST!C758 -> 0 | E757: =COST!D758 -> 0 | F757: =COST!E758 -> 0 | G757: =COST!F758 -> 0 | H757: =COST!G758 -> 0 | I757: =COST!H758 -> 0 | J757: =COST!J758 -> 0 | K757: =COST!K758 -> 0 | L757: =COST!L758 -> 0 | M757: =COST!P758 -> 0.0001 | N757: =COST!AB758 -> 2.0230812e-07 | O757: =M757*N757 -> 2.0230812e-11
B758: 276 | C758: =COST!B759 -> F-756 | D758: =COST!C759 -> 0 | E758: =COST!D759 -> 0 | F758: =COST!E759 -> 0 | G758: =COST!F759 -> 0 | H758: =COST!G759 -> 0 | I758: =COST!H759 -> 0 | J758: =COST!J759 -> 0 | K758: =COST!K759 -> 0 | L758: =COST!L759 -> 0 | M758: =COST!P759 -> 0.0001 | N758: =COST!AB759 -> 2.0230812e-07 | O758: =M758*N758 -> 2.0230812e-11
B759: 277 | C759: =COST!B760 -> F-757 | D759: =COST!C760 -> 0 | E759: =COST!D760 -> 0 | F759: =COST!E760 -> 0 | G759: =COST!F760 -> 0 | H759: =COST!G760 -> 0 | I759: =COST!H760 -> 0 | J759: =COST!J760 -> 0 | K759: =COST!K760 -> 0 | L759: =COST!L760 -> 0 | M759: =COST!P760 -> 0.0001 | N759: =COST!AB760 -> 2.0230812e-07 | O759: =M759*N759 -> 2.0230812e-11
B760: 278 | C760: =COST!B761 -> F-758 | D760: =COST!C761 -> 0 | E760: =COST!D761 -> 0 | F760: =COST!E761 -> 0 | G760: =COST!F761 -> 0 | H760: =COST!G761 -> 0 | I760: =COST!H761 -> 0 | J760: =COST!J761 -> 0 | K760: =COST!K761 -> 0 | L760: =COST!L761 -> 0 | M760: =COST!P761 -> 0.0001 | N760: =COST!AB761 -> 2.0230812e-07 | O760: =M760*N760 -> 2.0230812e-11
... B785: 303 | C785: =COST!B786 -> F-783 | D785: =COST!C786 -> 0 | E785: =COST!D786 -> 0 | F785: =COST!E786 -> 0 | G785: =COST!F786 -> 0 | H785: =COST!G786 -> 0 | I785: =COST!H786 -> 0 | J785: =COST!J786 -> 0 | K785: =COST!K786 -> 0 | L785: =COST!L786 -> 0 | M785: =COST!P786 -> 0.0001 | N785: =COST!AB786 -> 2.0230812e-07 | O785: =M785*N785 -> 2.0230812e-11
C786: Total DDP Including 14% VAT | M786: =SUM(M3:M785) -> 934.0095 | N786: =SUM(O3:O785) -> 6500000

Sheet SUPPLIER
A9: SN | B9: Reference | C9: Origin | D9: Fan Type | E9: Speed | F9: Smoke Rating | G9: Article No. | H9: Model | I9: =COST!K3 -> Flow l/s | J9: =COST!L3 -> ESP Pa | K9: Qty.
A10: =COST!B4 -> F-01 | B10: =COST!D4 -> FAF-A29-B02-01 | C10: =COST!E4 -> Germany | D10: =COST!F4 -> Axial Inline | E10: =COST!G4 -> Single | F10: =COST!H4 -> Ambient | G10: =COST!I4 -> CAP071140001G | H10: =COST!J4 -> AXC 710-9/20°-4-P (350) (3 kW) S IE3 | I10: =COST!K4 -> 3560 | J10: =COST!L4 -> 375 | K10: =COST!P4 -> 2
A11: =COST!B5 -> F-02 | B11: =COST!D5 -> FAF-A29-B02-02 | C11: =COST!E5 -> Germany | D11: =COST!F5 -> Centrifugal Inline | E11: =COST!G5 -> Single | F11: =COST!H5 -> Ambient | G11: =COST!I5 -> 235403 | H11: =COST!J5 -> MUB 042 400EV Multibox | I11: =COST!K5 -> 580 | J11: =COST!L5 -> 250 | K11: =COST!P5 -> 1
A12: =COST!B6 -> F-03 | B12: =COST!D6 -> FAF-A30-B02-01 | C12: =COST!E6 -> Sweden | D12: =COST!F6 -> Inline Fan | E12: =COST!G6 -> Single | F12: =COST!H6 -> Ambient | G12: =COST!I6 -> 93097 | H12: =COST!J6 -> KT 60-30-4 | I12: =COST!K6 -> 855 | J12: =COST!L6 -> 250 | K12: =COST!P6 -> 1
A13: =COST!B7 -> F-04 | B13: =COST!D7 -> FAF-A35-B02-01 | C13: =COST!E7 -> Germany | D13: =COST!F7 -> Axial Inline | E13: =COST!G7 -> Single | F13: =COST!H7 -> Ambient | G13: =COST!I7 -> CAP040120001F | H13: =COST!J7 -> AXC 400-6/31°-2-P (160) (2.2 kW) S IE3 C | I13: =COST!K7 -> 2240 | J13: =COST!L7 -> 250 | K13: =COST!P7 -> 2
A14: =COST!B8 -> F-05 | B14: =COST!D8 -> FAF-A35-B02-02 | C14: =COST!E8 -> Germany | D14: =COST!F8 -> Centrifugal Fan | E14: =COST!G8 -> Single | F14: =COST!H8 -> Ambient | G14: =COST!I8 -> 334079 | H14: =COST!J8 -> PRF 355D4 | I14: =COST!K8 -> 1125 | J14: =COST!L8 -> 250 | K14: =COST!P8 -> 1
A15: =COST!B9 -> F-06 | B15: =COST!D9 -> FAF-B30-B02-02 | C15: =COST!E9 -> Sweden | D15: =COST!F9 -> Inline Fan | E15: =COST!G9 -> Single | F15: =COST!H9 -> Ambient | G15: =COST!I9 -> 19514 | H15: =COST!J9 -> K 315 L Sileo** | I15: =COST!K9 -> 340 | J15: =COST!L9 -> 125 | K15: =COST!P9 -> 1
A16: =COST!B10 -> F-07 | B16: =COST!D10 -> FAF-B35-B02-01 | C16: =COST!E10 -> Sweden | D16: =COST!F10 -> Inline Fan | E16: =COST!G10 -> Single | F16: =COST!H10 -> Ambient | G16: =COST!I10 -> 93098 | H16: =COST!J10 -> KT 60-35-4 | I16: =COST!K10 -> 1025 | J16: =COST!L10 -> 250 | K16: =COST!P10 -> 1
A17: =COST!B11 -> F-08 | B17: =COST!D11 -> FAF-B35-B02-02 | C17: =COST!E11 -> Germany | D17: =COST!F11 -> Axial Inline | E17: =COST!G11 -> Single | F17: =COST!H11 -> Ambient | G17: =COST!I11 -> CAPV080340001H | H17: =COST!J11 -> AXC 800-6/20°-4-PV (350) (4 kW) S IE3 A | I17: =COST!K11 -> 5800 | J17: =COST!L11 -> 375 | K17: =COST!P11 -> 2
A18: =COST!B12 -> F-09 | B18: =COST!D12 -> FAF-B35-B02-03 | C18: =COST!E12 -> Germany | D18: =COST!F12 -> Axial Inline | E18: =COST!G12 -> Single | F18: =COST!H12 -> Ambient | G18: =COST!I12 -> CAP045120001F | H18: =COST!J12 -> AXC 450-6/23°-2-P (200) (2.2 kW) S IE3 | I18: =COST!K12 -> 2405 | J18: =COST!L12 -> 375 | K18: =COST!P12 -> 1
A19: =COST!B13 -> F-10 | B19: =COST!D13 -> FAF-B35-B02-04 | C19: =COST!E13 -> Sweden | D19: =COST!F13 -> Inline Fan | E19: =COST!G13 -> Single | F19: =COST!H13 -> Ambient | G19: =COST!I13 -> 27758 | H19: =COST!J13 -> K 315 M sileo** | I19: =COST!K13 -> 210 | J19: =COST!L13 -> 250 | K19: =COST!P13 -> 1
A20: =COST!B14 -> F-11 | B20: =COST!D14 -> FAF-C29-B02-01 | C20: =COST!E14 -> Sweden | D20: =COST!F14 -> Inline Fan | E20: =COST!G14 -> Single | F20: =COST!H14 -> Ambient | G20: =COST!I14 -> 93098 | H20: =COST!J14 -> KT 60-35-4 | I20: =COST!K14 -> 1145 | J20: =COST!L14 -> 250 | K20: =COST!P14 -> 1
A21: =COST!B15 -> F-12 | B21: =COST!D15 -> FAF-C29-B02-02 | C21: =COST!E15 -> Sweden | D21: =COST!F15 -> Inline Fan | E21: =COST!G15 -> Single | F21: =COST!H15 -> Ambient | G21: =COST!I15 -> 93097 | H21: =COST!J15 -> KT 60-30-4 | I21: =COST!K15 -> 725 | J21: =COST!L15 -> 250 | K21: =COST!P15 -> 1
... A53: =COST!B47 -> F-44 | B53: =COST!D47 -> EXF-A30-B02-03 | C53: =COST!E47 -> Sweden | D53: =COST!F47 -> Inline Fan | E53: =COST!G47 -> Single | F53: =COST!H47 -> Ambient | G53: =COST!I47 -> 19510 | H53: =COST!J47 -> K 200 L sileo | I53: =COST!K47 -> 195 | J53: =COST!L47 -> 125 | K53: =COST!P47 -> 1
A54: =COST!B168 -> F-164 | B54: =COST!D168 -> PR.FAN-C29-RF-01 | C54: =COST!E168 -> Germany | D54: =COST!F168 -> Axial Inline | E54: =COST!G168 -> Single | F54: =COST!H168 -> Ambient | G54: =COST!I168 -> CAPV080140001J | H54: =COST!J168 -> AXC 800-9/25°-4-PV (350) (7.5 kW) S IE3 A | I54: =COST!K168 -> 7255 | J54: =COST!L168 -> 500 | K54: =COST!P168 -> 1
A55: =COST!B169 -> F-165 | B55: =COST!D169 -> PR.FAN-A29-RF-01 | C55: =COST!E169 -> Germany | D55: =COST!F169 -> Axial Inline | E55: =COST!G169 -> Single | F55: =COST!H169 -> Ambient | G55: =COST!I169 -> CAPV080140001J | H55: =COST!J169 -> AXC 800-9/25°-4-PV (350) (7.5 kW) S IE3 A | I55: =COST!K169 -> 7260 | J55: =COST!L169 -> 500 | K55: =COST!P169 -> 1
A56: =COST!B170 -> F-166 | B56: =COST!D170 -> PR.FAN-A29-L05-01 | C56: =COST!E170 -> Germany | D56: =COST!F170 -> Axial Inline | E56: =COST!G170 -> Single | F56: =COST!H170 -> Ambient | G56: =COST!I170 -> CAP090140001J | H56: =COST!J170 -> AXC 900-10/18°-4-P (450) (7.5 kW) S IE3 A | I56: =COST!K170 -> 7465 | J56: =COST!L170 -> 500 | K56: =COST!P170 -> 1
A57: =COST!B171 -> F-167 | B57: =COST!D171 -> PR.FAN-C29-L05-01 | C57: =COST!E171 -> Germany | D57: =COST!F171 -> Axial Inline | E57: =COST!G171 -> Single | F57: =COST!H171 -> Ambient | G57: =COST!I171 -> CAP090140001J | H57: =COST!J171 -> AXC 900-10/18°-4-P (450) (7.5 kW) S IE3 A | I57: =COST!K171 -> 7460 | J57: =COST!L171 -> 500 | K57: =COST!P171 -> 1
A58: =COST!B172 -> F-168 | B58: =COST!D172 -> PR.FAN-B29-RF-01 | C58: =COST!E172 -> Germany | D58: =COST!F172 -> Axial Inline | E58: =COST!G172 -> Single | F58: =COST!H172 -> Ambient | G58: =COST!I172 -> CAP090140001J | H58: =COST!J172 -> AXC 900-10/17°-4-P (450) (7.5 kW) S IE3 A | I58: =COST!K172 -> 6915 | J58: =COST!L172 -> 500 | K58: =COST!P172 -> 1
A59: =COST!B173 -> F-169 | B59: =COST!D173 -> EXF-A29-GF-01 | C59: =COST!E173 -> Germany | D59: =COST!F173 -> Wall Mounted | E59: =COST!G173 -> Single | F59: =COST!H173 -> Ambient | G59: =COST!I173 -> 246889 | H59: =COST!J173 -> AW 350E4 sileo Axial fan | I59: =COST!K173 -> 670 | J59: =COST!L173 -> - | K59: =COST!P173 -> 1
A60: =COST!B174 -> F-170 | B60: =COST!D174 -> EXF-A29-RF-01 | C60: =COST!E174 -> Sweden | D60: =COST!F174 -> Inline Fan | E60: =COST!G174 -> Single | F60: =COST!H174 -> Ambient | G60: =COST!I174 -> 27758 | H60: =COST!J174 -> K 315 M sileo** | I60: =COST!K174 -> 240 | J60: =COST!L174 -> 150 | K60: =COST!P174 -> 1
A61: =COST!B175 -> F-171 | B61: =COST!D175 -> EXF-A29-L05-01 | C61: =COST!E175 -> Germany | D61: =COST!F175 -> Centrifugal Inline | E61: =COST!G175 -> Single | F61: =COST!H175 -> Ambient | G61: =COST!I175 -> 235403 | H61: =COST!J175 -> MUB 042 400EV Multibox | I61: =COST!K175 -> 655 | J61: =COST!L175 -> 200 | K61: =COST!P175 -> 1
A62: =COST!B176 -> F-172 | B62: =COST!D176 -> EXF-B29-RF-01 | C62: =COST!E176 -> Sweden | D62: =COST!F176 -> Inline Fan | E62: =COST!G176 -> Single | F62: =COST!H176 -> Ambient | G62: =COST!I176 -> 1487 | H62: =COST!J176 -> KT 50-25-4 | I62: =COST!K176 -> 410 | J62: =COST!L176 -> 150 | K62: =COST!P176 -> 1
A63: =COST!B177 -> F-173 | B63: =COST!D177 -> EXF-C29-RF-01 | C63: =COST!E177 -> Sweden | D63: =COST!F177 -> Inline Fan | E63: =COST!G177 -> Single | F63: =COST!H177 -> Ambient | G63: =COST!I177 -> 27758 | H63: =COST!J177 -> K 315 M sileo** | I63: =COST!K177 -> 265 | J63: =COST!L177 -> 150 | K63: =COST!P177 -> 1
A64: =COST!B178 -> F-174 | B64: =COST!D178 -> EXF-C29-L05-01 | C64: =COST!E178 -> Sweden | D64: =COST!F178 -> Inline Fan | E64: =COST!G178 -> Single | F64: =COST!H178 -> Ambient | G64: =COST!I178 -> 19512 | H64: =COST!J178 -> K 250 L sileo | I64: =COST!K178 -> 220 | J64: =COST!L178 -> 150 | K64: =COST!P178 -> 1
A65: =COST!B179 -> F-175 | B65: =COST!D179 -> EXF-A29-GR-02 | C65: =COST!E179 -> Germany | D65: =COST!F179 -> Wall Mounted | E65: =COST!G179 -> Single | F65: =COST!H179 -> Ambient | G65: =COST!I179 -> 37411 | H65: =COST!J179 -> AW 450E4 sileo Axial fan | I65: =COST!K179 -> 1185 | J65: =COST!L179 -> - | K65: =COST!P179 -> 1
... A67: =COST!B181 -> F-177 | B67: =COST!D181 -> FAF-A29-GR-01 | C67: =COST!E181 -> Germany | D67: =COST!F181 -> Wall Mounted | E67: =COST!G181 -> Single | F67: =COST!H181 -> Ambient | G67: =COST!I181 -> 37411 | H67: =COST!J181 -> AW 450E4 sileo Axial fan | I67: =COST!K181 -> 1250 | J67: =COST!L181 -> - | K67: =COST!P181 -> 1
A68: =COST!B866 -> F-863 | B68: =COST!D866 -> 0 | C68: =COST!E866 -> 0 | D68: =COST!F866 -> 0 | E68: =COST!G866 -> 0 | F68: =COST!H866 -> 0 | G68: =COST!I866 -> 0 | H68: =COST!J866 -> 0 | I68: =COST!K866 -> 0 | J68: =COST!L866 -> 0 | K68: =COST!P866 -> 0.0001
A69: =COST!B867 -> F-864 | B69: =COST!D867 -> 0 | C69: =COST!E867 -> 0 | D69: =COST!F867 -> 0 | E69: =COST!G867 -> 0 | F69: =COST!H867 -> 0 | G69: =COST!I867 -> 0 | H69: =COST!J867 -> 0 | I69: =COST!K867 -> 0 | J69: =COST!L867 -> 0 | K69: =COST!P867 -> 0.0001
A70: =COST!B868 -> F-865 | B70: =COST!D868 -> 0 | C70: =COST!E868 -> 0 | D70: =COST!F868 -> 0 | E70: =COST!G868 -> 0 | F70: =COST!H868 -> 0 | G70: =COST!I868 -> 0 | H70: =COST!J868 -> 0 | I70: =COST!K868 -> 0 | J70: =COST!L868 -> 0 | K70: =COST!P868 -> 0.0001
A71: =COST!B869 -> F-866 | B71: =COST!D869 -> 0 | C71: =COST!E869 -> 0 | D71: =COST!F869 -> 0 | E71: =COST!G869 -> 0 | F71: =COST!H869 -> 0 | G71: =COST!I869 -> 0 | H71: =COST!J869 -> 0 | I71: =COST!K869 -> 0 | J71: =COST!L869 -> 0 | K71: =COST!P869 -> 0.0001
A72: =COST!B870 -> F-867 | B72: =COST!D870 -> 0 | C72: =COST!E870 -> 0 | D72: =COST!F870 -> 0 | E72: =COST!G870 -> 0 | F72: =COST!H870 -> 0 | G72: =COST!I870 -> 0 | H72: =COST!J870 -> 0 | I72: =COST!K870 -> 0 | J72: =COST!L870 -> 0 | K72: =COST!P870 -> 0.0001
A73: =COST!B871 -> F-868 | B73: =COST!D871 -> 0 | C73: =COST!E871 -> 0 | D73: =COST!F871 -> 0 | E73: =COST!G871 -> 0 | F73: =COST!H871 -> 0 | G73: =COST!I871 -> 0 | H73: =COST!J871 -> 0 | I73: =COST!K871 -> 0 | J73: =COST!L871 -> 0 | K73: =COST!P871 -> 0.0001
A74: =COST!B872 -> F-869 | B74: =COST!D872 -> 0 | C74: =COST!E872 -> 0 | D74: =COST!F872 -> 0 | E74: =COST!G872 -> 0 | F74: =COST!H872 -> 0 | G74: =COST!I872 -> 0 | H74: =COST!J872 -> 0 | I74: =COST!K872 -> 0 | J74: =COST!L872 -> 0 | K74: =COST!P872 -> 0.0001
A75: =COST!B873 -> F-870 | B75: =COST!D873 -> 0 | C75: =COST!E873 -> 0 | D75: =COST!F873 -> 0 | E75: =COST!G873 -> 0 | F75: =COST!H873 -> 0 | G75: =COST!I873 -> 0 | H75: =COST!J873 -> 0 | I75: =COST!K873 -> 0 | J75: =COST!L873 -> 0 | K75: =COST!P873 -> 0.0001
A76: =COST!B874 -> F-871 | B76: =COST!D874 -> 0 | C76: =COST!E874 -> 0 | D76: =COST!F874 -> 0 | E76: =COST!G874 -> 0 | F76: =COST!H874 -> 0 | G76: =COST!I874 -> 0 | H76: =COST!J874 -> 0 | I76: =COST!K874 -> 0 | J76: =COST!L874 -> 0 | K76: =COST!P874 -> 0.0001
A77: =COST!B875 -> F-872 | B77: =COST!D875 -> 0 | C77: =COST!E875 -> 0 | D77: =COST!F875 -> 0 | E77: =COST!G875 -> 0 | F77: =COST!H875 -> 0 | G77: =COST!I875 -> 0 | H77: =COST!J875 -> 0 | I77: =COST!K875 -> 0 | J77: =COST!L875 -> 0 | K77: =COST!P875 -> 0.0001
A78: =COST!B876 -> F-873 | B78: =COST!D876 -> 0 | C78: =COST!E876 -> 0 | D78: =COST!F876 -> 0 | E78: =COST!G876 -> 0 | F78: =COST!H876 -> 0 | G78: =COST!I876 -> 0 | H78: =COST!J876 -> 0 | I78: =COST!K876 -> 0 | J78: =COST!L876 -> 0 | K78: =COST!P876 -> 0.0001
A79: =COST!B877 -> F-874 | B79: =COST!D877 -> 0 | C79: =COST!E877 -> 0 | D79: =COST!F877 -> 0 | E79: =COST!G877 -> 0 | F79: =COST!H877 -> 0 | G79: =COST!I877 -> 0 | H79: =COST!J877 -> 0 | I79: =COST!K877 -> 0 | J79: =COST!L877 -> 0 | K79: =COST!P877 -> 0.0001
... A84: =COST!B882 -> F-879 | B84: =COST!D882 -> 0 | C84: =COST!E882 -> 0 | D84: =COST!F882 -> 0 | E84: =COST!G882 -> 0 | F84: =COST!H882 -> 0 | G84: =COST!I882 -> 0 | H84: =COST!J882 -> 0 | I84: =COST!K882 -> 0 | J84: =COST!L882 -> 0 | K84: =COST!P882 -> 0.0001
G91: ACCESSORIES
G92: Article No. | H92: NAME | I92: Qty
G93: =COST!I887 -> 0 | H93: =COST!J887 -> 0 | I93: =COST!K887 -> 0
G94: =COST!I888 -> 0 | H94: =COST!J888 -> 0 | I94: =COST!K888 -> 0
G95: =COST!I889 -> 0 | H95: =COST!J889 -> 0 | I95: =COST!K889 -> 0
G96: =COST!I890 -> 0 | H96: =COST!J890 -> 0 | I96: =COST!K890 -> 0
G97: =COST!I891 -> 0 | H97: =COST!J891 -> 0 | I97: =COST!K891 -> 0
G98: =COST!I892 -> 0 | H98: =COST!J892 -> 0 | I98: =COST!K892 -> 0
G99: =COST!I893 -> 0 | H99: =COST!J893 -> 0 | I99: =COST!K893 -> 0
G100: =COST!I894 -> 0 | H100: =COST!J894 -> 0 | I100: =COST!K894 -> 0
G101: =COST!I895 -> 0 | H101: =COST!J895 -> 0 | I101: =COST!K895 -> 0
G102: =COST!I896 -> 0 | H102: =COST!J896 -> 0 | I102: =COST!K896 -> 0
G103: =COST!I897 -> 0 | H103: =COST!J897 -> 0 | I103: =COST!K897 -> 0
G104: =COST!I898 -> 0 | H104: =COST!J898 -> 0 | I104: =COST!K898 -> 0
... G108: =COST!I902 -> 0 | H108: =COST!J902 -> 0 | I108: =COST!K902 -> 0

Sheet Germany price
A1: Item no | B1: Item name | C1: Business area descr | D1: Product group descr | E1: Item group descr | F1: Family name | G1: Sales price | H1: Price list Currency
A2: 1001 | B2: K 100 M sileo | D2: 201 Circular duct fans | E2: 20101 Circular duct fans | F2: K | G2: 130 | H2: EUR
A3: 1002 | B3: K 125 M sileo | D3: 201 Circular duct fans | E3: 20101 Circular duct fans | F3: K | G3: 131 | H3: EUR
A4: 19510 | B4: K 200 L sileo | D4: 201 Circular duct fans | E4: 20101 Circular duct fans | F4: K | G4: 208 | H4: EUR
A5: 19512 | B5: K 250 L sileo | D5: 201 Circular duct fans | E5: 20101 Circular duct fans | F5: K | G5: 223 | H5: EUR
A6: 19514 | B6: K 315 L Sileo** | D6: 201 Circular duct fans | E6: 20101 Circular duct fans | F6: K | G6: 330 | H6: EUR
A7: 25360 | B7: K 100 XL sileo | D7: 201 Circular duct fans | E7: 20101 Circular duct fans | F7: K | G7: 140 | H7: EUR
A8: 25361 | B8: K 125 XL sileo | D8: 201 Circular duct fans | E8: 20101 Circular duct fans | F8: K | G8: 141 | H8: EUR
A9: 25362 | B9: K 150 M Sileo | D9: 201 Circular duct fans | E9: 20101 Circular duct fans | F9: K | G9: 145 | H9: EUR
A10: 25363 | B10: K 150 XL sileo | D10: 201 Circular duct fans | E10: 20101 Circular duct fans | F10: K | G10: 171 | H10: EUR
A11: 25364 | B11: K 160 M sileo | D11: 201 Circular duct fans | E11: 20101 Circular duct fans | F11: K | G11: 145 | H11: EUR
A12: 25365 | B12: K 160 XL sileo | D12: 201 Circular duct fans | E12: 20101 Circular duct fans | F12: K | G12: 171 | H12: EUR
A13: 25366 | B13: K 200 M sileo | D13: 201 Circular duct fans | E13: 20101 Circular duct fans | F13: K | G13: 172 | H13: EUR
... A899: 311653 | B899: TF24 Damper Actuator | D899: 206 Electrical accessories Ventilation | E899: 20605 Electrical Actuators & valves | F899: TF | G899: 211 | H899: EUR
A900: 382777 | B900: Room fine dust sensor RPS-SD | D900: 206 Electrical accessories Ventilation | E900: 20606 Sensors and transmitters | G900: 1288 | H900: EUR
A901: 382779 | B901: Dew point switch KW-W-SD | D901: 206 Electrical accessories Ventilation | E901: 20606 Sensors and transmitters | G901: 256 | H901: EUR
A902: 382780 | B902: Presence detector DBWF-W | D902: 206 Electrical accessories Ventilation | E902: 20606 Sensors and transmitters | G902: 783 | H902: EUR
A903: 14906 | B903: Systemair-1 CO2 duct sensor | D903: 206 Electrical accessories Ventilation | E903: 20606 Sensors and transmitters | F903: 1CO2 | G903: 304 | H903: EUR
A904: 382786 | B904: Wireless module W-Modbus | D904: 206 Electrical accessories Ventilation | E904: 20606 Sensors and transmitters | F904: ACC | G904: 411 | H904: EUR
A905: 286251 | B905: Room hygrostat HR-S | D905: 206 Electrical accessories Ventilation | E905: 20606 Sensors and transmitters | F905: BRAVO HU | G905: 138 | H905: EUR
A906: 14905 | B906: Systemair-E-D CO2 sensor | D906: 206 Electrical accessories Ventilation | E906: 20606 Sensors and transmitters | F906: CO2 | G906: 432 | H906: EUR
A907: 14907 | B907: Systemair-2 CO2 duct sensor | D907: 206 Electrical accessories Ventilation | E907: 20606 Sensors and transmitters | F907: CO2 | G907: 300 | H907: EUR
A908: 14908 | B908: Systemair-1M CO2 duct sensor | D908: 206 Electrical accessories Ventilation | E908: 20606 Sensors and transmitters | F908: CO2 | G908: 275 | H908: EUR
A909: 235145 | B909: Housing for measuring point | D909: 206 Electrical accessories Ventilation | E909: 20606 Sensors and transmitters | F909: CO2 | G909: 29 | H909: EUR
A910: 251355 | B910: CO2 traffic light | D910: 206 Electrical accessories Ventilation | E910: 20606 Sensors and transmitters | F910: CO2 | G910: 433 | H910: EUR
A911: 251924 | B911: M-SENSE III CO/CO2-sensor | D911: 206 Electrical accessories Ventilation | E911: 20606 Sensors and transmitters | F911: CO2 | G911: 2081 | H911: EUR
A912: 466457 | B912: CO2 room sensor RCO2-W-LCD | D912: 206 Electrical accessories Ventilation | E912: 20606 Sensors and transmitters | F912: CO2 | G912: 644 | H912: EUR
A913: 466458 | B913: CO2 room sensor RCO2-W | D913: 206 Electrical accessories Ventilation | E913: 20606 Sensors and transmitters | F913: CO2 | G913: 536 | H913: EUR
A914: 266263 | B914: CTDT2 | D914: 206 Electrical accessories Ventilation | E914: 20606 Sensors and transmitters | F914: CO2DT | G914: 803 | H914: EUR
... A941: 5164 | B941: TG-R630 External sensor | D941: 206 Electrical accessories Ventilation | E941: 20606 Sensors and transmitters | F941: TG-R | G941: 79 | H941: EUR
A942: 333484 | B942: Inclined tube manometer MV600 | D942: 206 Electrical accessories Ventilation | E942: 20609 Other Electrical. vent. Control equipmen | G942: 205 | H942: EUR
A943: 382051 | B943: Contact thermostat AT-2090U | D943: 206 Electrical accessories Ventilation | E943: 20609 Other Electrical. vent. Control equipmen | G943: 108 | H943: EUR
A944: 524263 | B944: VTR time relay | D944: 206 Electrical accessories Ventilation | E944: 20609 Other Electrical. vent. Control equipmen | F944: ACC | G944: 60 | H944: EUR
A945: 93042 | B945: ACO8AC/EC ACO Panel IP40 | D945: 206 Electrical accessories Ventilation | E945: 20609 Other Electrical. vent. Control equipmen | F945: ACO | G945: 362 | H945: EUR
A946: 5136 | B946: AQUA 24TF Heat Regulator | D946: 206 Electrical accessories Ventilation | E946: 20609 Other Electrical. vent. Control equipmen | F946: AQUA | G946: 264 | H946: EUR
A947: 5138 | B947: AWE-SK Motorprotection 2A/230V | D947: 206 Electrical accessories Ventilation | E947: 20609 Other Electrical. vent. Control equipmen | F947: AWE | G947: 189 | H947: EUR
A948: 458315 | B948: Modbus RTU - Modbus TCP/IP Gat | D948: 206 Electrical accessories Ventilation | E948: 20609 Other Electrical. vent. Control equipmen | F948: CORRIGO | G948: 617 | H948: EUR
A949: 13209 | B949: HMH Tube Humidistat IP 54 | D949: 206 Electrical accessories Ventilation | E949: 20609 Other Electrical. vent. Control equipmen | F949: HMH | G949: 295 | H949: EUR
A950: 298183 | B950: Humidity sensor HTRT10A | D950: 206 Electrical accessories Ventilation | E950: 20609 Other Electrical. vent. Control equipmen | F950: HTRT | G950: 263 | H950: EUR
A951: 332795 | B951: Antifrost thermostat FT30 | D951: 206 Electrical accessories Ventilation | E951: 20609 Other Electrical. vent. Control equipmen | F951: K-FST | G951: 129 | H951: EUR
A952: 452400 | B952: Air flow monitor KLSW-W230 | D952: 206 Electrical accessories Ventilation | E952: 20609 Other Electrical. vent. Control equipmen | F952: K-LSW | G952: 419 | H952: EUR
A953: 333279 | B953: Air flow switch AFS1 | D953: 206 Electrical accessories Ventilation | E953: 20609 Other Electrical. vent. Control equipmen | F953: K-WFR | G953: 109 | H953: EUR
A954: 6688 | B954: MFRO Manometer | D954: 206 Electrical accessories Ventilation | E954: 20609 Other Electrical. vent. Control equipmen | F954: MFRO | G954: 42 | H954: EUR
A955: 17822 | B955: MicroREX D21 Plus Time Switch | D955: 206 Electrical accessories Ventilation | E955: 20609 Other Electrical. vent. Control equipmen | F955: MICROREX | G955: 260 | H955: EUR
... A3240: 157226 | B3240: Front cover W VTR150B | D3240: 313 Accessories residential systems | E3240: 31301 Acc. Residential Units | F3240: VTVTR | G3240: 220 | H3240: EUR
A3241: 212987 | B3241: Pressure guard with pitot tube | D3241: 313 Accessories residential systems | E3241: 31303 Acc. Combi units | G3241: 54 | H3241: EUR
A3242: 37064 | B3242: FGR-I 125 Filter cassette insu | D3242: 313 Accessories residential systems | E3242: 31306 Acc. Ducts | F3242: FGR-I | G3242: 210 | H3242: EUR
A3243: 37065 | B3243: FGR-I 160 Filter cassette insu | D3243: 313 Accessories residential systems | E3243: 31306 Acc. Ducts | F3243: FGR-I | G3243: 250 | H3243: EUR
A3244: 37066 | B3244: FGR-I 200 Filter cassette insu | D3244: 313 Accessories residential systems | E3244: 31306 Acc. Ducts | F3244: FGR-I | G3244: 255 | H3244: EUR
A3245: 37316 | B3245: FGR-I 250 Filter cassette insu | D3245: 313 Accessories residential systems | E3245: 31306 Acc. Ducts | F3245: FGR-I | G3245: 282 | H3245: EUR
A3246: 84789 | B3246: DIS 100 25mm insulation | D3246: 313 Accessories residential systems | E3246: 31306 Acc. Ducts | F3246: IS | G3246: 30 | H3246: EUR
A3247: 85034 | B3247: DIS 125 25mm insulation | D3247: 313 Accessories residential systems | E3247: 31306 Acc. Ducts | F3247: IS | G3247: 31 | H3247: EUR
A3248: 87546 | B3248: DIS 160 25mm insulation | D3248: 313 Accessories residential systems | E3248: 31306 Acc. Ducts | F3248: IS | G3248: 34 | H3248: EUR
A3249: 87547 | B3249: DIS 200 25mm insulation | D3249: 313 Accessories residential systems | E3249: 31306 Acc. Ducts | F3249: IS | G3249: 38 | H3249: EUR
A3250: 87548 | B3250: DIS 100 50mm insulation | D3250: 313 Accessories residential systems | E3250: 31306 Acc. Ducts | F3250: IS | G3250: 37 | H3250: EUR
A3251: 87549 | B3251: DIS 125 50mm insulation | D3251: 313 Accessories residential systems | E3251: 31306 Acc. Ducts | F3251: IS | G3251: 38 | H3251: EUR
A3252: 87562 | B3252: DIS 160 50mm insulation | D3252: 313 Accessories residential systems | E3252: 31306 Acc. Ducts | F3252: IS | G3252: 45 | H3252: EUR
A3253: 87563 | B3253: DIS 200 50mm insulation | D3253: 313 Accessories residential systems | E3253: 31306 Acc. Ducts | F3253: IS | G3253: 39 | H3253: EUR
... A7154: 572992 | B7154: SR L 74-76 B Board | D7154: 705 Fan coils (all types) | E7154: 70595 Control for FCUs | F7154: SERENA | G7154: 578.86 | H7154: EUR

Sheet MY Price
A1: Item Name | B1: Description | F1: Sales Price | G1: Price list Currency
A2: 10083 | B2: AJR 315-2/4 TR (B)0.8/0.16kw | F2: 1682 | G2: EUR
A3: 10084 | B3: AJR 355-2/4 TR (B)1.2/0.24kw | F3: 1820 | G3: EUR
A4: 10085 | B4: AJR 400-2/4 TR (B)1.7/0.34kw | F4: 1896 | G4: EUR
A5: 14832 | B5: MUB(A) 100 630D4-T (5.5kW) | F5: 2477 | G5: EUR
A6: 157227 | B6: CDRD-500-4 (1.5KW-IE3) | F6: 1328 | G6: EUR
A7: 157228 | B7: CDRD-560-4 (3KW-IE3) | F7: 1637 | G7: EUR
A8: 157229 | B8: CDRD-630-4 (4KW-IE3) | F8: 1922 | G8: EUR
A9: 19434 | B9: IV50-4/8(B) (1.7/0.34kw) | F9: 2523 | G9: EUR
A10: 256066 | B10: 50MM FILTER INLET- CDRE 315 | F10: 32.9 | G10: EUR
A11: 256067 | B11: 50MM FILTER INLET- CDRE 355 | F11: 35 | G11: EUR
A12: 256068 | B12: 50MM FILTER INLET- CDRE 400 | F12: 35.7 | G12: EUR
A13: 256069 | B13: 50MM FILTER INLET- CDRE 450 | F13: 39.5 | G13: EUR
... A782: 94766 | B782: ASP1650 CENTRIFUGAL FAN, SWSI | F782: 18500 | G782: EUR

Sheet AW-with Shutter
A2: 0 | B2: Item | C2: Gross Price | D2: Sales price | E2: Currency | F2: Sales price with shutter | G2: Description | H2: Sales price unit | I2: Business area descr | J2: Product group descr | K2: Article group descr | L2: Family
A3: 1 | B3: 246889 | C3: 374 | D3: =C3*0.42 -> 157.08 | E3: EUR | F3: =D3+D37 -> 177.66 | G3: AW 350E4 sileo Axial fan | H3: Pcs | I3: 2 Fans & Accessories | J3: 211 Axial fans | K3: 21106 Low pressure Axial fans wall mounted | L3: AW
A4: 2 | B4: 246890 | C4: 381 | D4: =C4*0.42 -> 160.02 | E4: EUR | F4: =D4+D37 -> 180.6 | G4: AW 350DV sileo Axial fan | H4: Pcs | I4: 2 Fans & Accessories | J4: 211 Axial fans | K4: 21106 Low pressure Axial fans wall mounted | L4: AW
A5: 3 | B5: 281421 | C5: 200 | D5: =C5*0.42 -> 84 | E5: EUR | F5: =D5+D34 -> 99.96 | G5: AW 200E2-C | H5: Pcs | I5: 2 Fans & Accessories | J5: 211 Axial fans | K5: 21106 Low pressure Axial fans wall mounted | L5: AW
A6: 4 | B6: 281422 | C6: 160 | D6: =C6*0.42 -> 67.2 | E6: EUR | F6: =D6+D34 -> 83.16 | G6: AW 200E4-C | H6: Pcs | I6: 2 Fans & Accessories | J6: 211 Axial fans | K6: 21106 Low pressure Axial fans wall mounted | L6: AW
A7: 5 | B7: 281423 | C7: 194 | D7: =C7*0.42 -> 81.48 | E7: EUR | F7: =D7+D36 -> 99.96 | G7: AW 250E2-C | H7: Pcs | I7: 2 Fans & Accessories | J7: 211 Axial fans | K7: 21106 Low pressure Axial fans wall mounted | L7: AW
A8: 6 | B8: 281424 | C8: 173 | D8: =C8*0.42 -> 72.66 | E8: EUR | F8: =D8+D36 -> 91.14 | G8: AW 250E4-C | H8: Pcs | I8: 2 Fans & Accessories | J8: 211 Axial fans | K8: 21106 Low pressure Axial fans wall mounted | L8: AW
A9: 7 | B9: 281425 | C9: 216 | D9: =C9*0.42 -> 90.72 | E9: EUR | F9: =D9+D37 -> 111.3 | G9: AW 300E4-C | H9: Pcs | I9: 2 Fans & Accessories | J9: 211 Axial fans | K9: 21106 Low pressure Axial fans wall mounted | L9: AW
A10: 8 | B10: 34124 | C10: 437 | D10: =C10*0.42 -> 183.54 | E10: EUR | F10: =D10+D38 -> 210.84 | G10: AW 400DV sileo Axial fan | H10: Pcs | I10: 2 Fans & Accessories | J10: 211 Axial fans | K10: 21106 Low pressure Axial fans wall mounted | L10: AW
A11: 9 | B11: 34125 | C11: 420 | D11: =C11*0.42 -> 176.4 | E11: EUR | F11: =D11+D38 -> 203.7 | G11: AW 400E4 sileo Axial fan | H11: Pcs | I11: 2 Fans & Accessories | J11: 211 Axial fans | K11: 21106 Low pressure Axial fans wall mounted | L11: AW
A12: 10 | B12: 34126 | C12: 576 | D12: =C12*0.42 -> 241.92 | E12: EUR | F12: =D12+D41 -> 283.5 | G12: AW 450DV sileo Axial fan | H12: Pcs | I12: 2 Fans & Accessories | J12: 211 Axial fans | K12: 21106 Low pressure Axial fans wall mounted | L12: AW
A13: 11 | B13: 34131 | C13: 632 | D13: =C13*0.42 -> 265.44 | E13: EUR | F13: =D13+D41 -> 307.02 | G13: AW 500DV sileo Axial fan | H13: Pcs | I13: 2 Fans & Accessories | J13: 211 Axial fans | K13: 21106 Low pressure Axial fans wall mounted | L13: AW
A14: 12 | B14: 34134 | C14: 793 | D14: =C14*0.42 -> 333.06 | E14: EUR | F14: =D14+D46 -> 398.58 | G14: AW 560DV sileo Axial fan | H14: Pcs | I14: 2 Fans & Accessories | J14: 211 Axial fans | K14: 21106 Low pressure Axial fans wall mounted | L14: AW
A15: 13 | B15: 34138 | C15: 942 | D15: =C15*0.42 -> 395.64 | E15: EUR | F15: =D15+D46 -> 461.16 | G15: AW 630DS sileo Axial fan | H15: Pcs | I15: 2 Fans & Accessories | J15: 211 Axial fans | K15: 21106 Low pressure Axial fans wall mounted | L15: AW
A16: 14 | B16: 34140 | C16: 2005 | D16: =C16*0.42 -> 842.1 | E16: EUR | F16: =D16+D48 -> 928.2 | G16: AW 710DV sileo Axial fan | H16: Pcs | I16: 2 Fans & Accessories | J16: 211 Axial fans | K16: 21106 Low pressure Axial fans wall mounted | L16: AW
A17: 15 | B17: 34141 | C17: 1507 | D17: =C17*0.42 -> 632.94 | E17: EUR | F17: =D17+D48 -> 719.04 | G17: AW 710DS sileo Axial fan | H17: Pcs | I17: 2 Fans & Accessories | J17: 211 Axial fans | K17: 21106 Low pressure Axial fans wall mounted | L17: AW
A18: 16 | B18: 34142 | C18: 1507 | D18: =C18*0.42 -> 632.94 | E18: EUR | F18: =D18+D48 -> 719.04 | G18: AW 710E6 sileo Axial fan | H18: Pcs | I18: 2 Fans & Accessories | J18: 211 Axial fans | K18: 21106 Low pressure Axial fans wall mounted | L18: AW
A19: 17 | B19: 34144 | C19: 3472 | D19: =C19*0.42 -> 1458.24 | E19: EUR | F19: =D19+D53 -> 1668.24 | G19: AW 1000DS sileo Axial fan | H19: Pcs | I19: 2 Fans & Accessories | J19: 211 Axial fans | K19: 21106 Low pressure Axial fans wall mounted | L19: AW
A20: 18 | B20: 34157 | C20: 3513 | D20: =C20*0.42 -> 1475.46 | E20: EUR | F20: =D20+D53 -> 1685.46 | G20: AW 910DS sileo Axial fan | H20: Pcs | I20: 2 Fans & Accessories | J20: 211 Axial fans | K20: 21106 Low pressure Axial fans wall mounted | L20: AW
A21: 19 | B21: 37407 | C21: 317 | D21: =C21*0.42 -> 133.14 | E21: EUR | F21: =D21+D36 -> 151.62 | G21: AW 315E4 sileo Axial fan | H21: Pcs | I21: 2 Fans & Accessories | J21: 211 Axial fans | K21: 21106 Low pressure Axial fans wall mounted | L21: AW
A22: 20 | B22: 37408 | C22: 330 | D22: =C22*0.42 -> 138.6 | E22: EUR | F22: =D22+D37 -> 159.18 | G22: AW 315DV sileo Axial fan | H22: Pcs | I22: 2 Fans & Accessories | J22: 211 Axial fans | K22: 21106 Low pressure Axial fans wall mounted | L22: AW
A23: 21 | B23: 37411 | C23: 638 | D23: =C23*0.42 -> 267.96 | E23: EUR | F23: =D23+D41 -> 309.54 | G23: AW 450E4 sileo Axial fan | H23: Pcs | I23: 2 Fans & Accessories | J23: 211 Axial fans | K23: 21106 Low pressure Axial fans wall mounted | L23: AW
A24: 22 | B24: 37412 | C24: 632 | D24: =C24*0.42 -> 265.44 | E24: EUR | F24: =D24+D52 -> 327.18 | G24: AW 500E4 sileo Axial fan | H24: Pcs | I24: 2 Fans & Accessories | J24: 211 Axial fans | K24: 21106 Low pressure Axial fans wall mounted | L24: AW
A25: 23 | B25: 37413 | C25: 1122 | D25: =C25*0.42 -> 471.24 | E25: EUR | F25: =D25+D52 -> 532.98 | G25: AW 560E4 sileo Axial fan | H25: Pcs | I25: 2 Fans & Accessories | J25: 211 Axial fans | K25: 21106 Low pressure Axial fans wall mounted | L25: AW
A26: 24 | B26: 37414 | C26: 1220 | D26: =C26*0.42 -> 512.4 | E26: EUR | F26: =D26+D46 -> 577.92 | G26: AW 630E6 sileo Axial fan | H26: Pcs | I26: 2 Fans & Accessories | J26: 211 Axial fans | K26: 21106 Low pressure Axial fans wall mounted | L26: AW
A27: 25 | B27: 37415 | C27: 1352 | D27: =C27*0.42 -> 567.84 | E27: EUR | F27: =D27+D46 -> 633.36 | G27: AW 630DV sileo Axial fan | H27: Pcs | I27: 2 Fans & Accessories | J27: 211 Axial fans | K27: 21106 Low pressure Axial fans wall mounted | L27: AW
A28: 26 | B28: 37416 | C28: 1904 | D28: =C28*0.42 -> 799.68 | E28: EUR | F28: =D28+D51 -> 934.92 | G28: AW 800DS sileo Axial fan | H28: Pcs | I28: 2 Fans & Accessories | J28: 211 Axial fans | K28: 21106 Low pressure Axial fans wall mounted | L28: AW
A29: 28 | B29: 5801 | C29: 345 | D29: =C29*0.42 -> 144.9 | E29: EUR | F29: =D29+D37 -> 165.48 | G29: AW 300E2 sileo Axial fan | H29: Pcs | I29: 2 Fans & Accessories | J29: 211 Axial fans | K29: 21106 Low pressure Axial fans wall mounted | L29: AW
A30: 33 | B30: 87679 | C30: 33 | D30: =C30*0.42 -> 13.86 | E30: EUR | G30: VK-15 Louvre shutter | H30: Pcs | I30: 2 Fans & Accessories | J30: 208 Accessories Ventilation | K30: 20813 Shutters ventilation | L30: VK
A31: 34 | B31: 87682 | C31: 13 | D31: =C31*0.42 -> 5.46 | E31: EUR | G31: VK-10 Louvre shutter | H31: Pcs | I31: 2 Fans & Accessories | J31: 208 Accessories Ventilation | K31: 20813 Shutters ventilation | L31: VK
A32: 35 | B32: 87684 | C32: 294 | D32: =C32*0.42 -> 123.48 | E32: EUR | G32: VK-100-50 Louvre shutter | H32: Pcs | I32: 2 Fans & Accessories | J32: 208 Accessories Ventilation | K32: 20813 Shutters ventilation | L32: VK
A33: 36 | B33: 87685 | C33: 20 | D33: =C33*0.42 -> 8.4 | E33: EUR | G33: VK-12 Louvre-shutter | H33: Pcs | I33: 2 Fans & Accessories | J33: 208 Accessories Ventilation | K33: 20813 Shutters ventilation | L33: VK
A34: 37 | B34: 87686 | C34: 38 | D34: =C34*0.42 -> 15.96 | E34: EUR | G34: VK-20 Louvre shutter | H34: Pcs | I34: 2 Fans & Accessories | J34: 208 Accessories Ventilation | K34: 20813 Shutters ventilation | L34: VK
A35: 38 | B35: 87687 | C35: 40 | D35: =C35*0.42 -> 16.8 | E35: EUR | G35: VK-25 Louvre shutter | H35: Pcs | I35: 2 Fans & Accessories | J35: 208 Accessories Ventilation | K35: 20813 Shutters ventilation | L35: VK
A36: 39 | B36: 87688 | C36: 44 | D36: =C36*0.42 -> 18.48 | E36: EUR | G36: VK-30 Louvre shutter | H36: Pcs | I36: 2 Fans & Accessories | J36: 208 Accessories Ventilation | K36: 20813 Shutters ventilation | L36: VK
A37: 40 | B37: 87689 | C37: 49 | D37: =C37*0.42 -> 20.58 | E37: EUR | G37: VK-35 Louvre shutter | H37: Pcs | I37: 2 Fans & Accessories | J37: 208 Accessories Ventilation | K37: 20813 Shutters ventilation | L37: VK
A38: 41 | B38: 87691 | C38: 65 | D38: =C38*0.42 -> 27.3 | E38: EUR | G38: VK-40 Louvre shutter | H38: Pcs | I38: 2 Fans & Accessories | J38: 208 Accessories Ventilation | K38: 20813 Shutters ventilation | L38: VK
A39: 42 | B39: 87692 | C39: 96 | D39: =C39*0.42 -> 40.32 | E39: EUR | G39: VK-40-20 Louvre shutter | H39: Pcs | I39: 2 Fans & Accessories | J39: 208 Accessories Ventilation | K39: 20813 Shutters ventilation | L39: VK
A40: 43 | B40: 87693 | C40: 74 | D40: =C40*0.42 -> 31.08 | E40: EUR | G40: VK-45 Louvre shutter | H40: Pcs | I40: 2 Fans & Accessories | J40: 208 Accessories Ventilation | K40: 20813 Shutters ventilation | L40: VK
A41: 44 | B41: 87694 | C41: 99 | D41: =C41*0.42 -> 41.58 | E41: EUR | G41: VK-50 Louvre shutter | H41: Pcs | I41: 2 Fans & Accessories | J41: 208 Accessories Ventilation | K41: 20813 Shutters ventilation | L41: VK
... A53: 56 | B53: 87715 | C53: 500 | D53: =C53*0.42 -> 210 | E53: EUR | G53: VK-100 Louvre shutter | H53: Pcs | I53: 2 Fans & Accessories | J53: 208 Accessories Ventilation | K53: 20813 Shutters ventilation | L53: VK
A54: 57 | D54: =C54*0.42 -> 0
